Workbook

Sheet Lisez-moi
A1: Achats n3-universal — 4 projets
A2: Carte universelle rev 0.2.2 (hardware/n3-universal). Prix relevés le 18/10/2026 chez les boutiques marocaines en ligne.
A4: Feuilles
A5: Global — tout ce qu'il faut acheter pour les 4 unités, rechange comprise, arrondi aux lots vendus, avec le coût total.
A6: msp1, n3pp, ffp5cs 230V, ffp5cs 12V — une feuille par projet : consignes de pose, composants à poser sur la carte et ce qui se branche autour, coût d'une unité.
A7: Prix — catalogue unique (fournisseur, prix, lien). Changer un prix ici met tout le classeur à jour.
A9: Cellules modifiables (texte bleu)
A10: Qté dans les feuilles projet ; Rechange dans Global ; Prix du lot et Taille du lot dans Prix. Le reste est calculé.
A12: Statuts et couleurs
A13: À acheter — compté dans les totaux. Fond rose = introuvable au Maroc, à mettre dans le colis LCSC combiné avec la commande JLCPCB (COMMANDE.md §2).
A14: Option — fond jaune : utile mais pas indispensable (BME280, INA226 supplémentaires, microSD). Total séparé.
A15: Déjà possédé — fond vert : TP4056, batterie AGM, régulateur PWM, panneau 12 V. Valeur indicative, hors total.
... A32: Prix tels qu'affichés au relevé ; stocks variables (plusieurs articles en rupture, signalés). Certains prix viennent d'une fourchette de variantes (bas de fourchette retenu) : à confirmer au panier. Les quantités de câble et de presse-étoupes sont des estimations à ajuster à l'installation.

Sheet Global
A1: Liste globale d'achats — 4 unités n3-universal (msp1, n3pp, ffp5cs 230 V, ffp5cs 12 V)
A2: Quantités tirées des feuilles projet (formules) + rechange conseillée (bleu, modifiable), arrondies aux lots vendus par les boutiques. Prix du 18/10/2026, feuille Prix.
C4: Total à acheter, 4 unités, arrondi aux lots (DH) | O4: =SUMIFS(O15:O87,D15:D87,"À acheter")+SUM(O91:O93) -> 5459.5
C5: dont outillage et consommables partagés (DH) | O5: =SUM(O91:O93) -> 674
C6: Options, si toutes prises (DH) | O6: =SUMIFS(O15:O87,D15:D87,"Option") -> 373
C7: Déjà possédé — valeur indicative (DH) | O7: =SUMIFS(O15:O87,D15:D87,"Déjà possédé") -> 983
C8: Lignes à acheter sans prix en ligne (import LCSC, quincaillerie, PCB) | O8: =SUMPRODUCT((D15:D87="À acheter")*(K15:K87>0)*(N15:N87="")) -> 5
C10: Coût d'UNE unité (à l'unité, sans arrondi aux lots) | E10: msp1 | F10: n3pp | G10: ffp5cs 230V | H10: ffp5cs 12V
C11: À acheter (DH) | E11: =msp1!J11 -> 1072.1 | F11: =n3pp!J11 -> 929.8 | G11: ='ffp5cs 230V'!J11 -> 1199.6 | H11: ='ffp5cs 12V'!J11 -> 1189.4
C12: Options (DH) | E12: =msp1!J12 -> 170 | F12: =n3pp!J12 -> 85 | G12: ='ffp5cs 230V'!J12 -> 18 | H12: ='ffp5cs 12V'!J12 -> 100
A14: ID | B14: Catégorie | C14: Article | D14: Statut | E14: msp1 | F14: n3pp | G14: ffp5cs 230V | H14: ffp5cs 12V | I14: Total 4 unités | J14: Rechange | K14: Qté à acheter | L14: Taille du lot | M14: Nb de lots | N14: Prix du lot (DH) | O14: Coût (DH) | P14: Fournisseur | Q14: Source | R14: Remarque achat | S14: Lien
A15: PCB | B15: 1. Carte et cerveau | C15: Circuit imprimé n3-universal rev 0.2.2 (JLCPCB, 2 oz) | D15: À acheter | E15: =SUMIFS(msp1!$F:$F,msp1!$A:$A,$A15,msp1!$G:$G,$D15) -> 1 | F15: =SUMIFS(n3pp!$F:$F,n3pp!$A:$A,$A15,n3pp!$G:$G,$D15) -> 1 | G15: =SUMIFS('ffp5cs 230V'!$F:$F,'ffp5cs 230V'!$A:$A,$A15,'ffp5cs 230V'!$G:$G,$D15) -> 1 | H15: =SUMIFS('ffp5cs 12V'!$F:$F,'ffp5cs 12V'!$A:$A,$A15,'ffp5cs 12V'!$G:$G,$D15) -> 1 | I15: =SUM(E15:H15) -> 4 | J15: 0 | K15: =IF(I15=0,0,I15+J15) -> 4 | L15: =INDEX(Prix!$E$5:$E$79,MATCH($A15,Prix!$A$5:$A$79,0)) -> 1 | M15: =IF(K15=0,0,ROUNDUP(K15/L15,0)) -> 4 | N15: =IF(INDEX(Prix!$D$5:$D$79,MATCH($A15,Prix!$A$5:$A$79,0))="","",INDEX(Prix!$D$5:$D$79,MATCH($A15,Prix!$A$5:$A$79,0))) | O15: =IF(N15="","",M15*N15) | P15: =INDEX(Prix!$C$5:$C$79,MATCH($A15,Prix!$A$5:$A$79,0)) -> JLCPCB | Q15: =INDEX(Prix!$H$5:$H$79,MATCH($A15,Prix!$A$5:$A$79,0)) -> Import | R15: Commande unique de 10 cartes : ≈ 55–85 $ les 5 + port (COMMANDE.md) ; prix réel au devis JLCPCB. | S15: lien
A16: ESP32_DEVKIT | B16: 1. Carte et cerveau | C16: ESP32 DevKit V1 30 broches (WROOM-32) | D16: À acheter | E16: =SUMIFS(msp1!$F:$F,msp1!$A:$A,$A16,msp1!$G:$G,$D16) -> 1 | F16: =SUMIFS(n3pp!$F:$F,n3pp!$A:$A,$A16,n3pp!$G:$G,$D16) -> 1 | G16: =SUMIFS('ffp5cs 230V'!$F:$F,'ffp5cs 230V'!$A:$A,$A16,'ffp5cs 230V'!$G:$G,$D16) -> 1 | H16: =SUMIFS('ffp5cs 12V'!$F:$F,'ffp5cs 12V'!$A:$A,$A16,'ffp5cs 12V'!$G:$G,$D16) -> 1 | I16: =SUM(E16:H16) -> 4 | J16: 1 | K16: =IF(I16=0,0,I16+J16) -> 5 | L16: =INDEX(Prix!$E$5:$E$79,MATCH($A16,Prix!$A$5:$A$79,0)) -> 1 | M16: =IF(K16=0,0,ROUNDUP(K16/L16,0)) -> 5 | N16: =IF(INDEX(Prix!$D$5:$D$79,MATCH($A16,Prix!$A$5:$A$79,0))="","",INDEX(Prix!$D$5:$D$79,MATCH($A16,Prix!$A$5:$A$79,0))) -> 113 | O16: =IF(N16="","",M16*N16) -> 565 | P16: =INDEX(Prix!$C$5:$C$79,MATCH($A16,Prix!$A$5:$A$79,0)) -> Shop4Makers | Q16: =INDEX(Prix!$H$5:$H$79,MATCH($A16,Prix!$A$5:$A$79,0)) -> Maroc | R16: ESP32 WROOM CP2102 30 broches. Ne pas importer (ANRT). Repli A2itronic 120 DH. | S16: lien
A17: R_220 | B17: 2. Résistances | C17: Résistance 220 Ω 1/4 W | D17: À acheter | E17: =SUMIFS(msp1!$F:$F,msp1!$A:$A,$A17,msp1!$G:$G,$D17) -> 2 | F17: =SUMIFS(n3pp!$F:$F,n3pp!$A:$A,$A17,n3pp!$G:$G,$D17) -> 0 | G17: =SUMIFS('ffp5cs 230V'!$F:$F,'ffp5cs 230V'!$A:$A,$A17,'ffp5cs 230V'!$G:$G,$D17) -> 2 | H17: =SUMIFS('ffp5cs 12V'!$F:$F,'ffp5cs 12V'!$A:$A,$A17,'ffp5cs 12V'!$G:$G,$D17) -> 2 | I17: =SUM(E17:H17) -> 6 | J17: 2 | K17: =IF(I17=0,0,I17+J17) -> 8 | L17: =INDEX(Prix!$E$5:$E$79,MATCH($A17,Prix!$A$5:$A$79,0)) -> 5 | M17: =IF(K17=0,0,ROUNDUP(K17/L17,0)) -> 2 | N17: =IF(INDEX(Prix!$D$5:$D$79,MATCH($A17,Prix!$A$5:$A$79,0))="","",INDEX(Prix!$D$5:$D$79,MATCH($A17,Prix!$A$5:$A$79,0))) -> 1.5 | O17: =IF(N17="","",M17*N17) -> 3 | P17: =INDEX(Prix!$C$5:$C$79,MATCH($A17,Prix!$A$5:$A$79,0)) -> MicroPlanet | Q17: =INDEX(Prix!$H$5:$H$79,MATCH($A17,Prix!$A$5:$A$79,0)) -> Maroc | R17: 1/4 W 1 %, vendues par 5. | S17: lien
A18: R_1k | B18: 2. Résistances | C18: Résistance 1 kΩ 1/4 W | D18: À acheter | E18: =SUMIFS(msp1!$F:$F,msp1!$A:$A,$A18,msp1!$G:$G,$D18) -> 7 | F18: =SUMIFS(n3pp!$F:$F,n3pp!$A:$A,$A18,n3pp!$G:$G,$D18) -> 10 | G18: =SUMIFS('ffp5cs 230V'!$F:$F,'ffp5cs 230V'!$A:$A,$A18,'ffp5cs 230V'!$G:$G,$D18) -> 23 | H18: =SUMIFS('ffp5cs 12V'!$F:$F,'ffp5cs 12V'!$A:$A,$A18,'ffp5cs 12V'!$G:$G,$D18) -> 24 | I18: =SUM(E18:H18) -> 64 | J18: 5 | K18: =IF(I18=0,0,I18+J18) -> 69 | L18: =INDEX(Prix!$E$5:$E$79,MATCH($A18,Prix!$A$5:$A$79,0)) -> 5 | M18: =IF(K18=0,0,ROUNDUP(K18/L18,0)) -> 14 | N18: =IF(INDEX(Prix!$D$5:$D$79,MATCH($A18,Prix!$A$5:$A$79,0))="","",INDEX(Prix!$D$5:$D$79,MATCH($A18,Prix!$A$5:$A$79,0))) -> 1.5 | O18: =IF(N18="","",M18*N18) -> 21 | P18: =INDEX(Prix!$C$5:$C$79,MATCH($A18,Prix!$A$5:$A$79,0)) -> MicroPlanet | Q18: =INDEX(Prix!$H$5:$H$79,MATCH($A18,Prix!$A$5:$A$79,0)) -> Maroc | R18: 1/4 W 1 %, vendues par 5. | S18: lien
A19: R_2k | B19: 2. Résistances | C19: Résistance 2 kΩ 1/4 W (2,2 kΩ convient) | D19: À acheter | E19: =SUMIFS(msp1!$F:$F,msp1!$A:$A,$A19,msp1!$G:$G,$D19) -> 0 | F19: =SUMIFS(n3pp!$F:$F,n3pp!$A:$A,$A19,n3pp!$G:$G,$D19) -> 0 | G19: =SUMIFS('ffp5cs 230V'!$F:$F,'ffp5cs 230V'!$A:$A,$A19,'ffp5cs 230V'!$G:$G,$D19) -> 3 | H19: =SUMIFS('ffp5cs 12V'!$F:$F,'ffp5cs 12V'!$A:$A,$A19,'ffp5cs 12V'!$G:$G,$D19) -> 3 | I19: =SUM(E19:H19) -> 6 | J19: 2 | K19: =IF(I19=0,0,I19+J19) -> 8 | L19: =INDEX(Prix!$E$5:$E$79,MATCH($A19,Prix!$A$5:$A$79,0)) -> 5 | M19: =IF(K19=0,0,ROUNDUP(K19/L19,0)) -> 2 | N19: =IF(INDEX(Prix!$D$5:$D$79,MATCH($A19,Prix!$A$5:$A$79,0))="","",INDEX(Prix!$D$5:$D$79,MATCH($A19,Prix!$A$5:$A$79,0))) -> 1.5 | O19: =IF(N19="","",M19*N19) -> 3 | P19: =INDEX(Prix!$C$5:$C$79,MATCH($A19,Prix!$A$5:$A$79,0)) -> MicroPlanet | Q19: =INDEX(Prix!$H$5:$H$79,MATCH($A19,Prix!$A$5:$A$79,0)) -> Maroc | R19: 1/4 W 1 %, vendues par 5. | S19: lien
A20: R_4.7k | B20: 2. Résistances | C20: Résistance 4,7 kΩ 1/4 W | D20: À acheter | E20: =SUMIFS(msp1!$F:$F,msp1!$A:$A,$A20,msp1!$G:$G,$D20) -> 3 | F20: =SUMIFS(n3pp!$F:$F,n3pp!$A:$A,$A20,n3pp!$G:$G,$D20) -> 2 | G20: =SUMIFS('ffp5cs 230V'!$F:$F,'ffp5cs 230V'!$A:$A,$A20,'ffp5cs 230V'!$G:$G,$D20) -> 3 | H20: =SUMIFS('ffp5cs 12V'!$F:$F,'ffp5cs 12V'!$A:$A,$A20,'ffp5cs 12V'!$G:$G,$D20) -> 3 | I20: =SUM(E20:H20) -> 11 | J20: 2 | K20: =IF(I20=0,0,I20+J20) -> 13 | L20: =INDEX(Prix!$E$5:$E$79,MATCH($A20,Prix!$A$5:$A$79,0)) -> 5 | M20: =IF(K20=0,0,ROUNDUP(K20/L20,0)) -> 3 | N20: =IF(INDEX(Prix!$D$5:$D$79,MATCH($A20,Prix!$A$5:$A$79,0))="","",INDEX(Prix!$D$5:$D$79,MATCH($A20,Prix!$A$5:$A$79,0))) -> 1.5 | O20: =IF(N20="","",M20*N20) -> 4.5 | P20: =INDEX(Prix!$C$5:$C$79,MATCH($A20,Prix!$A$5:$A$79,0)) -> MicroPlanet | Q20: =INDEX(Prix!$H$5:$H$79,MATCH($A20,Prix!$A$5:$A$79,0)) -> Maroc | R20: 1/4 W 1 %, vendues par 5. | S20: lien
A21: R_10k | B21: 2. Résistances | C21: Résistance 10 kΩ 1/4 W | D21: À acheter | E21: =SUMIFS(msp1!$F:$F,msp1!$A:$A,$A21,msp1!$G:$G,$D21) -> 7 | F21: =SUMIFS(n3pp!$F:$F,n3pp!$A:$A,$A21,n3pp!$G:$G,$D21) -> 4 | G21: =SUMIFS('ffp5cs 230V'!$F:$F,'ffp5cs 230V'!$A:$A,$A21,'ffp5cs 230V'!$G:$G,$D21) -> 9 | H21: =SUMIFS('ffp5cs 12V'!$F:$F,'ffp5cs 12V'!$A:$A,$A21,'ffp5cs 12V'!$G:$G,$D21) -> 9 | I21: =SUM(E21:H21) -> 29 | J21: 5 | K21: =IF(I21=0,0,I21+J21) -> 34 | L21: =INDEX(Prix!$E$5:$E$79,MATCH($A21,Prix!$A$5:$A$79,0)) -> 5 | M21: =IF(K21=0,0,ROUNDUP(K21/L21,0)) -> 7 | N21: =IF(INDEX(Prix!$D$5:$D$79,MATCH($A21,Prix!$A$5:$A$79,0))="","",INDEX(Prix!$D$5:$D$79,MATCH($A21,Prix!$A$5:$A$79,0))) -> 1.5 | O21: =IF(N21="","",M21*N21) -> 10.5 | P21: =INDEX(Prix!$C$5:$C$79,MATCH($A21,Prix!$A$5:$A$79,0)) -> MicroPlanet | Q21: =INDEX(Prix!$H$5:$H$79,MATCH($A21,Prix!$A$5:$A$79,0)) -> Maroc | R21: 1/4 W 1 %, vendues par 5. | S21: lien
A22: R_18k | B22: 2. Résistances | C22: Résistance 18 kΩ 1/4 W | D22: À acheter | E22: =SUMIFS(msp1!$F:$F,msp1!$A:$A,$A22,msp1!$G:$G,$D22) -> 1 | F22: =SUMIFS(n3pp!$F:$F,n3pp!$A:$A,$A22,n3pp!$G:$G,$D22) -> 1 | G22: =SUMIFS('ffp5cs 230V'!$F:$F,'ffp5cs 230V'!$A:$A,$A22,'ffp5cs 230V'!$G:$G,$D22) -> 0 | H22: =SUMIFS('ffp5cs 12V'!$F:$F,'ffp5cs 12V'!$A:$A,$A22,'ffp5cs 12V'!$G:$G,$D22) -> 1 | I22: =SUM(E22:H22) -> 3 | J22: 2 | K22: =IF(I22=0,0,I22+J22) -> 5 | L22: =INDEX(Prix!$E$5:$E$79,MATCH($A22,Prix!$A$5:$A$79,0)) -> 5 | M22: =IF(K22=0,0,ROUNDUP(K22/L22,0)) -> 1 | N22: =IF(INDEX(Prix!$D$5:$D$79,MATCH($A22,Prix!$A$5:$A$79,0))="","",INDEX(Prix!$D$5:$D$79,MATCH($A22,Prix!$A$5:$A$79,0))) -> 1.5 | O22: =IF(N22="","",M22*N22) -> 1.5 | P22: =INDEX(Prix!$C$5:$C$79,MATCH($A22,Prix!$A$5:$A$79,0)) -> MicroPlanet | Q22: =INDEX(Prix!$H$5:$H$79,MATCH($A22,Prix!$A$5:$A$79,0)) -> Maroc | R22: 1/4 W 1 %, vendues par 5. | S22: lien
A23: R_100k | B23: 2. Résistances | C23: Résistance 100 kΩ 1/4 W | D23: À acheter | E23: =SUMIFS(msp1!$F:$F,msp1!$A:$A,$A23,msp1!$G:$G,$D23) -> 4 | F23: =SUMIFS(n3pp!$F:$F,n3pp!$A:$A,$A23,n3pp!$G:$G,$D23) -> 4 | G23: =SUMIFS('ffp5cs 230V'!$F:$F,'ffp5cs 230V'!$A:$A,$A23,'ffp5cs 230V'!$G:$G,$D23) -> 2 | H23: =SUMIFS('ffp5cs 12V'!$F:$F,'ffp5cs 12V'!$A:$A,$A23,'ffp5cs 12V'!$G:$G,$D23) -> 5 | I23: =SUM(E23:H23) -> 15 | J23: 3 | K23: =IF(I23=0,0,I23+J23) -> 18 | L23: =INDEX(Prix!$E$5:$E$79,MATCH($A23,Prix!$A$5:$A$79,0)) -> 5 | M23: =IF(K23=0,0,ROUNDUP(K23/L23,0)) -> 4 | N23: =IF(INDEX(Prix!$D$5:$D$79,MATCH($A23,Prix!$A$5:$A$79,0))="","",INDEX(Prix!$D$5:$D$79,MATCH($A23,Prix!$A$5:$A$79,0))) -> 1.5 | O23: =IF(N23="","",M23*N23) -> 6 | P23: =INDEX(Prix!$C$5:$C$79,MATCH($A23,Prix!$A$5:$A$79,0)) -> MicroPlanet | Q23: =INDEX(Prix!$H$5:$H$79,MATCH($A23,Prix!$A$5:$A$79,0)) -> Maroc | R23: 1/4 W 1 %, vendues par 5. | S23: lien
A24: C_100n | B24: 3. Condensateurs | C24: Condensateur céramique 100 nF (pas 5 mm) | D24: À acheter | E24: =SUMIFS(msp1!$F:$F,msp1!$A:$A,$A24,msp1!$G:$G,$D24) -> 8 | F24: =SUMIFS(n3pp!$F:$F,n3pp!$A:$A,$A24,n3pp!$G:$G,$D24) -> 8 | G24: =SUMIFS('ffp5cs 230V'!$F:$F,'ffp5cs 230V'!$A:$A,$A24,'ffp5cs 230V'!$G:$G,$D24) -> 3 | H24: =SUMIFS('ffp5cs 12V'!$F:$F,'ffp5cs 12V'!$A:$A,$A24,'ffp5cs 12V'!$G:$G,$D24) -> 4 | I24: =SUM(E24:H24) -> 23 | J24: 5 | K24: =IF(I24=0,0,I24+J24) -> 28 | L24: =INDEX(Prix!$E$5:$E$79,MATCH($A24,Prix!$A$5:$A$79,0)) -> 1 | M24: =IF(K24=0,0,ROUNDUP(K24/L24,0)) -> 28 | N24: =IF(INDEX(Prix!$D$5:$D$79,MATCH($A24,Prix!$A$5:$A$79,0))="","",INDEX(Prix!$D$5:$D$79,MATCH($A24,Prix!$A$5:$A$79,0))) -> 0.5 | O24: =IF(N24="","",M24*N24) -> 14 | P24: =INDEX(Prix!$C$5:$C$79,MATCH($A24,Prix!$A$5:$A$79,0)) -> A2itronic | Q24: =INDEX(Prix!$H$5:$H$79,MATCH($A24,Prix!$A$5:$A$79,0)) -> Maroc | R24: Céramique 50 V. | S24: lien
A25: C_10u25 | B25: 3. Condensateurs | C25: Condensateur électrolytique 10 µF 25 V | D25: À acheter | E25: =SUMIFS(msp1!$F:$F,msp1!$A:$A,$A25,msp1!$G:$G,$D25) -> 1 | F25: =SUMIFS(n3pp!$F:$F,n3pp!$A:$A,$A25,n3pp!$G:$G,$D25) -> 1 | G25: =SUMIFS('ffp5cs 230V'!$F:$F,'ffp5cs 230V'!$A:$A,$A25,'ffp5cs 230V'!$G:$G,$D25) -> 1 | H25: =SUMIFS('ffp5cs 12V'!$F:$F,'ffp5cs 12V'!$A:$A,$A25,'ffp5cs 12V'!$G:$G,$D25) -> 1 | I25: =SUM(E25:H25) -> 4 | J25: 1 | K25: =IF(I25=0,0,I25+J25) -> 5 | L25: =INDEX(Prix!$E$5:$E$79,MATCH($A25,Prix!$A$5:$A$79,0)) -> 1 | M25: =IF(K25=0,0,ROUNDUP(K25/L25,0)) -> 5 | N25: =IF(INDEX(Prix!$D$5:$D$79,MATCH($A25,Prix!$A$5:$A$79,0))="","",INDEX(Prix!$D$5:$D$79,MATCH($A25,Prix!$A$5:$A$79,0))) -> 1 | O25: =IF(N25="","",M25*N25) -> 5 | P25: =INDEX(Prix!$C$5:$C$79,MATCH($A25,Prix!$A$5:$A$79,0)) -> A2itronic | Q25: =INDEX(Prix!$H$5:$H$79,MATCH($A25,Prix!$A$5:$A$79,0)) -> Maroc | R25: Proposé en 50 V (mieux que 25 V). | S25: lien
A26: C_100u16 | B26: 3. Condensateurs | C26: Condensateur électrolytique 100 µF 16 V | D26: À acheter | E26: =SUMIFS(msp1!$F:$F,msp1!$A:$A,$A26,msp1!$G:$G,$D26) -> 1 | F26: =SUMIFS(n3pp!$F:$F,n3pp!$A:$A,$A26,n3pp!$G:$G,$D26) -> 1 | G26: =SUMIFS('ffp5cs 230V'!$F:$F,'ffp5cs 230V'!$A:$A,$A26,'ffp5cs 230V'!$G:$G,$D26) -> 1 | H26: =SUMIFS('ffp5cs 12V'!$F:$F,'ffp5cs 12V'!$A:$A,$A26,'ffp5cs 12V'!$G:$G,$D26) -> 1 | I26: =SUM(E26:H26) -> 4 | J26: 1 | K26: =IF(I26=0,0,I26+J26) -> 5 | L26: =INDEX(Prix!$E$5:$E$79,MATCH($A26,Prix!$A$5:$A$79,0)) -> 1 | M26: =IF(K26=0,0,ROUNDUP(K26/L26,0)) -> 5 | N26: =IF(INDEX(Prix!$D$5:$D$79,MATCH($A26,Prix!$A$5:$A$79,0))="","",INDEX(Prix!$D$5:$D$79,MATCH($A26,Prix!$A$5:$A$79,0))) -> 1 | O26: =IF(N26="","",M26*N26) -> 5 | P26: =INDEX(Prix!$C$5:$C$79,MATCH($A26,Prix!$A$5:$A$79,0)) -> A2itronic | Q26: =INDEX(Prix!$H$5:$H$79,MATCH($A26,Prix!$A$5:$A$79,0)) -> Maroc | R26: 5×7 mm. | S26: lien
... A29: C_1000u16 | B29: 3. Condensateurs | C29: Condensateur électrolytique 1000 µF 16 V (diam. 10 mm) | D29: À acheter | E29: =SUMIFS(msp1!$F:$F,msp1!$A:$A,$A29,msp1!$G:$G,$D29) -> 1 | F29: =SUMIFS(n3pp!$F:$F,n3pp!$A:$A,$A29,n3pp!$G:$G,$D29) -> 1 | G29: =SUMIFS('ffp5cs 230V'!$F:$F,'ffp5cs 230V'!$A:$A,$A29,'ffp5cs 230V'!$G:$G,$D29) -> 1 | H29: =SUMIFS('ffp5cs 12V'!$F:$F,'ffp5cs 12V'!$A:$A,$A29,'ffp5cs 12V'!$G:$G,$D29) -> 1 | I29: =SUM(E29:H29) -> 4 | J29: 1 | K29: =IF(I29=0,0,I29+J29) -> 5 | L29: =INDEX(Prix!$E$5:$E$79,MATCH($A29,Prix!$A$5:$A$79,0)) -> 1 | M29: =IF(K29=0,0,ROUNDUP(K29/L29,0)) -> 5 | N29: =IF(INDEX(Prix!$D$5:$D$79,MATCH($A29,Prix!$A$5:$A$79,0))="","",INDEX(Prix!$D$5:$D$79,MATCH($A29,Prix!$A$5:$A$79,0))) -> 3 | O29: =IF(N29="","",M29*N29) -> 15 | P29: =INDEX(Prix!$C$5:$C$79,MATCH($A29,Prix!$A$5:$A$79,0)) -> A2itronic | Q29: =INDEX(Prix!$H$5:$H$79,MATCH($A29,Prix!$A$5:$A$79,0)) -> Maroc | R29: Page ambiguë 16/25 V : les deux conviennent, mais diamètre ≤ 10 mm et pas 5 mm. | S29: lien
A30: 1N4007 | B30: 4. Semi-conducteurs | C30: Diode 1N4007 (roue libre des bobines de relais) | D30: À acheter | E30: =SUMIFS(msp1!$F:$F,msp1!$A:$A,$A30,msp1!$G:$G,$D30) -> 0 | F30: =SUMIFS(n3pp!$F:$F,n3pp!$A:$A,$A30,n3pp!$G:$G,$D30) -> 1 | G30: =SUMIFS('ffp5cs 230V'!$F:$F,'ffp5cs 230V'!$A:$A,$A30,'ffp5cs 230V'!$G:$G,$D30) -> 6 | H30: =SUMIFS('ffp5cs 12V'!$F:$F,'ffp5cs 12V'!$A:$A,$A30,'ffp5cs 12V'!$G:$G,$D30) -> 6 | I30: =SUM(E30:H30) -> 13 | J30: 3 | K30: =IF(I30=0,0,I30+J30) -> 16 | L30: =INDEX(Prix!$E$5:$E$79,MATCH($A30,Prix!$A$5:$A$79,0)) -> 1 | M30: =IF(K30=0,0,ROUNDUP(K30/L30,0)) -> 16 | N30: =IF(INDEX(Prix!$D$5:$D$79,MATCH($A30,Prix!$A$5:$A$79,0))="","",INDEX(Prix!$D$5:$D$79,MATCH($A30,Prix!$A$5:$A$79,0))) -> 0.9 | O30: =IF(N30="","",M30*N30) -> 14.4 | P30: =INDEX(Prix!$C$5:$C$79,MATCH($A30,Prix!$A$5:$A$79,0)) -> Shop4Makers | Q30: =INDEX(Prix!$H$5:$H$79,MATCH($A30,Prix!$A$5:$A$79,0)) -> Maroc | S30: lien
A31: BAT85 | B31: 4. Semi-conducteurs | C31: Diode Schottky BAT85 / BAT43 / BAT42 (DO-35) | D31: À acheter | E31: =SUMIFS(msp1!$F:$F,msp1!$A:$A,$A31,msp1!$G:$G,$D31) -> 1 | F31: =SUMIFS(n3pp!$F:$F,n3pp!$A:$A,$A31,n3pp!$G:$G,$D31) -> 1 | G31: =SUMIFS('ffp5cs 230V'!$F:$F,'ffp5cs 230V'!$A:$A,$A31,'ffp5cs 230V'!$G:$G,$D31) -> 0 | H31: =SUMIFS('ffp5cs 12V'!$F:$F,'ffp5cs 12V'!$A:$A,$A31,'ffp5cs 12V'!$G:$G,$D31) -> 1 | I31: =SUM(E31:H31) -> 3 | J31: 1 | K31: =IF(I31=0,0,I31+J31) -> 4 | L31: =INDEX(Prix!$E$5:$E$79,MATCH($A31,Prix!$A$5:$A$79,0)) -> 1 | M31: =IF(K31=0,0,ROUNDUP(K31/L31,0)) -> 4 | N31: =IF(INDEX(Prix!$D$5:$D$79,MATCH($A31,Prix!$A$5:$A$79,0))="","",INDEX(Prix!$D$5:$D$79,MATCH($A31,Prix!$A$5:$A$79,0))) -> 2 | O31: =IF(N31="","",M31*N31) -> 8 | P31: =INDEX(Prix!$C$5:$C$79,MATCH($A31,Prix!$A$5:$A$79,0)) -> Moussasoft | Q31: =INDEX(Prix!$H$5:$H$79,MATCH($A31,Prix!$A$5:$A$79,0)) -> Maroc | R31: Boîtier DO-34, se pose sur les trous DO-35. BAT43/42/54 introuvables au Maroc. | S31: lien
A32: TVS_6V8 | B32: 4. Semi-conducteurs | C32: Diode TVS 1.5KE6.8A (ou P6KE6.8A) | D32: À acheter | E32: =SUMIFS(msp1!$F:$F,msp1!$A:$A,$A32,msp1!$G:$G,$D32) -> 1 | F32: =SUMIFS(n3pp!$F:$F,n3pp!$A:$A,$A32,n3pp!$G:$G,$D32) -> 1 | G32: =SUMIFS('ffp5cs 230V'!$F:$F,'ffp5cs 230V'!$A:$A,$A32,'ffp5cs 230V'!$G:$G,$D32) -> 1 | H32: =SUMIFS('ffp5cs 12V'!$F:$F,'ffp5cs 12V'!$A:$A,$A32,'ffp5cs 12V'!$G:$G,$D32) -> 1 | I32: =SUM(E32:H32) -> 4 | J32: 1 | K32: =IF(I32=0,0,I32+J32) -> 5 | L32: =INDEX(Prix!$E$5:$E$79,MATCH($A32,Prix!$A$5:$A$79,0)) -> 1 | M32: =IF(K32=0,0,ROUNDUP(K32/L32,0)) -> 5 | N32: =IF(INDEX(Prix!$D$5:$D$79,MATCH($A32,Prix!$A$5:$A$79,0))="","",INDEX(Prix!$D$5:$D$79,MATCH($A32,Prix!$A$5:$A$79,0))) | O32: =IF(N32="","",M32*N32) | P32: =INDEX(Prix!$C$5:$C$79,MATCH($A32,Prix!$A$5:$A$79,0)) -> LCSC | Q32: =INDEX(Prix!$H$5:$H$79,MATCH($A32,Prix!$A$5:$A$79,0)) -> Import LCSC | R32: Introuvable au Maroc : LCSC C412500 (repli P6KE6.8A C409413), colis combiné JLCPCB. | S32: lien
A33: TVS_18 | B33: 4. Semi-conducteurs | C33: Diode TVS 1.5KE18A (ou P6KE18A) — PAS 15 V | D33: À acheter | E33: =SUMIFS(msp1!$F:$F,msp1!$A:$A,$A33,msp1!$G:$G,$D33) -> 0 | F33: =SUMIFS(n3pp!$F:$F,n3pp!$A:$A,$A33,n3pp!$G:$G,$D33) -> 0 | G33: =SUMIFS('ffp5cs 230V'!$F:$F,'ffp5cs 230V'!$A:$A,$A33,'ffp5cs 230V'!$G:$G,$D33) -> 0 | H33: =SUMIFS('ffp5cs 12V'!$F:$F,'ffp5cs 12V'!$A:$A,$A33,'ffp5cs 12V'!$G:$G,$D33) -> 1 | I33: =SUM(E33:H33) -> 1 | J33: 1 | K33: =IF(I33=0,0,I33+J33) -> 2 | L33: =INDEX(Prix!$E$5:$E$79,MATCH($A33,Prix!$A$5:$A$79,0)) -> 1 | M33: =IF(K33=0,0,ROUNDUP(K33/L33,0)) -> 2 | N33: =IF(INDEX(Prix!$D$5:$D$79,MATCH($A33,Prix!$A$5:$A$79,0))="","",INDEX(Prix!$D$5:$D$79,MATCH($A33,Prix!$A$5:$A$79,0))) | O33: =IF(N33="","",M33*N33) | P33: =INDEX(Prix!$C$5:$C$79,MATCH($A33,Prix!$A$5:$A$79,0)) -> LCSC | Q33: =INDEX(Prix!$H$5:$H$79,MATCH($A33,Prix!$A$5:$A$79,0)) -> Import LCSC | R33: Introuvable au Maroc : LCSC C1666858. Ne pas remplacer par une 15 V. | S33: lien
A34: Z15 | B34: 4. Semi-conducteurs | C34: Diode Zener 15 V 1 W 1N4744A | D34: À acheter | E34: =SUMIFS(msp1!$F:$F,msp1!$A:$A,$A34,msp1!$G:$G,$D34) -> 0 | F34: =SUMIFS(n3pp!$F:$F,n3pp!$A:$A,$A34,n3pp!$G:$G,$D34) -> 0 | G34: =SUMIFS('ffp5cs 230V'!$F:$F,'ffp5cs 230V'!$A:$A,$A34,'ffp5cs 230V'!$G:$G,$D34) -> 0 | H34: =SUMIFS('ffp5cs 12V'!$F:$F,'ffp5cs 12V'!$A:$A,$A34,'ffp5cs 12V'!$G:$G,$D34) -> 1 | I34: =SUM(E34:H34) -> 1 | J34: 1 | K34: =IF(I34=0,0,I34+J34) -> 2 | L34: =INDEX(Prix!$E$5:$E$79,MATCH($A34,Prix!$A$5:$A$79,0)) -> 1 | M34: =IF(K34=0,0,ROUNDUP(K34/L34,0)) -> 2 | N34: =IF(INDEX(Prix!$D$5:$D$79,MATCH($A34,Prix!$A$5:$A$79,0))="","",INDEX(Prix!$D$5:$D$79,MATCH($A34,Prix!$A$5:$A$79,0))) -> 2 | O34: =IF(N34="","",M34*N34) -> 4 | P34: =INDEX(Prix!$C$5:$C$79,MATCH($A34,Prix!$A$5:$A$79,0)) -> MicroPlanet | Q34: =INDEX(Prix!$H$5:$H$79,MATCH($A34,Prix!$A$5:$A$79,0)) -> Maroc | R34: Zener 1 W, variante 15 V (équivalent 1N4744A). | S34: lien
A35: BC337 | B35: 4. Semi-conducteurs | C35: Transistor NPN BC337-40 (TO-92) | D35: À acheter | E35: =SUMIFS(msp1!$F:$F,msp1!$A:$A,$A35,msp1!$G:$G,$D35) -> 1 | F35: =SUMIFS(n3pp!$F:$F,n3pp!$A:$A,$A35,n3pp!$G:$G,$D35) -> 2 | G35: =SUMIFS('ffp5cs 230V'!$F:$F,'ffp5cs 230V'!$A:$A,$A35,'ffp5cs 230V'!$G:$G,$D35) -> 7 | H35: =SUMIFS('ffp5cs 12V'!$F:$F,'ffp5cs 12V'!$A:$A,$A35,'ffp5cs 12V'!$G:$G,$D35) -> 7 | I35: =SUM(E35:H35) -> 17 | J35: 3 | K35: =IF(I35=0,0,I35+J35) -> 20 | L35: =INDEX(Prix!$E$5:$E$79,MATCH($A35,Prix!$A$5:$A$79,0)) -> 1 | M35: =IF(K35=0,0,ROUNDUP(K35/L35,0)) -> 20 | N35: =IF(INDEX(Prix!$D$5:$D$79,MATCH($A35,Prix!$A$5:$A$79,0))="","",INDEX(Prix!$D$5:$D$79,MATCH($A35,Prix!$A$5:$A$79,0))) -> 1 | O35: =IF(N35="","",M35*N35) -> 20 | P35: =INDEX(Prix!$C$5:$C$79,MATCH($A35,Prix!$A$5:$A$79,0)) -> A2itronic | Q35: =INDEX(Prix!$H$5:$H$79,MATCH($A35,Prix!$A$5:$A$79,0)) -> Maroc | R35: Annoncé BC337B/-40 : tout BC337 convient (brochage C-B-E). | S35: lien
A36: IRF4905 | B36: 4. Semi-conducteurs | C36: MOSFET P IRF4905 (TO-220) | D36: À acheter | E36: =SUMIFS(msp1!$F:$F,msp1!$A:$A,$A36,msp1!$G:$G,$D36) -> 2 | F36: =SUMIFS(n3pp!$F:$F,n3pp!$A:$A,$A36,n3pp!$G:$G,$D36) -> 2 | G36: =SUMIFS('ffp5cs 230V'!$F:$F,'ffp5cs 230V'!$A:$A,$A36,'ffp5cs 230V'!$G:$G,$D36) -> 2 | H36: =SUMIFS('ffp5cs 12V'!$F:$F,'ffp5cs 12V'!$A:$A,$A36,'ffp5cs 12V'!$G:$G,$D36) -> 3 | I36: =SUM(E36:H36) -> 9 | J36: 1 | K36: =IF(I36=0,0,I36+J36) -> 10 | L36: =INDEX(Prix!$E$5:$E$79,MATCH($A36,Prix!$A$5:$A$79,0)) -> 1 | M36: =IF(K36=0,0,ROUNDUP(K36/L36,0)) -> 10 | N36: =IF(INDEX(Prix!$D$5:$D$79,MATCH($A36,Prix!$A$5:$A$79,0))="","",INDEX(Prix!$D$5:$D$79,MATCH($A36,Prix!$A$5:$A$79,0))) -> 10 | O36: =IF(N36="","",M36*N36) -> 100 | P36: =INDEX(Prix!$C$5:$C$79,MATCH($A36,Prix!$A$5:$A$79,0)) -> A2itronic | Q36: =INDEX(Prix!$H$5:$H$79,MATCH($A36,Prix!$A$5:$A$79,0)) -> Maroc | R36: Stock non vérifié : appeler avant. Repli LCSC C2564. | S36: lien
A37: LD1117 | B37: 4. Semi-conducteurs | C37: Régulateur LD1117V33 TO-220 (1=GND 2=OUT 3=IN) | D37: À acheter | E37: =SUMIFS(msp1!$F:$F,msp1!$A:$A,$A37,msp1!$G:$G,$D37) -> 1 | F37: =SUMIFS(n3pp!$F:$F,n3pp!$A:$A,$A37,n3pp!$G:$G,$D37) -> 1 | G37: =SUMIFS('ffp5cs 230V'!$F:$F,'ffp5cs 230V'!$A:$A,$A37,'ffp5cs 230V'!$G:$G,$D37) -> 1 | H37: =SUMIFS('ffp5cs 12V'!$F:$F,'ffp5cs 12V'!$A:$A,$A37,'ffp5cs 12V'!$G:$G,$D37) -> 1 | I37: =SUM(E37:H37) -> 4 | J37: 1 | K37: =IF(I37=0,0,I37+J37) -> 5 | L37: =INDEX(Prix!$E$5:$E$79,MATCH($A37,Prix!$A$5:$A$79,0)) -> 1 | M37: =IF(K37=0,0,ROUNDUP(K37/L37,0)) -> 5 | N37: =IF(INDEX(Prix!$D$5:$D$79,MATCH($A37,Prix!$A$5:$A$79,0))="","",INDEX(Prix!$D$5:$D$79,MATCH($A37,Prix!$A$5:$A$79,0))) -> 7.5 | O37: =IF(N37="","",M37*N37) -> 37.5 | P37: =INDEX(Prix!$C$5:$C$79,MATCH($A37,Prix!$A$5:$A$79,0)) -> Megma | Q37: =INDEX(Prix!$H$5:$H$79,MATCH($A37,Prix!$A$5:$A$79,0)) -> Maroc | R37: LM1117T-3.3 TO-220, même brochage que le LD1117V33. Pas de version SOT-223 (CMS). | S37: lien
A38: LED_R | B38: 4. Semi-conducteurs | C38: LED 5 mm rouge | D38: À acheter | E38: =SUMIFS(msp1!$F:$F,msp1!$A:$A,$A38,msp1!$G:$G,$D38) -> 0 | F38: =SUMIFS(n3pp!$F:$F,n3pp!$A:$A,$A38,n3pp!$G:$G,$D38) -> 1 | G38: =SUMIFS('ffp5cs 230V'!$F:$F,'ffp5cs 230V'!$A:$A,$A38,'ffp5cs 230V'!$G:$G,$D38) -> 6 | H38: =SUMIFS('ffp5cs 12V'!$F:$F,'ffp5cs 12V'!$A:$A,$A38,'ffp5cs 12V'!$G:$G,$D38) -> 6 | I38: =SUM(E38:H38) -> 13 | J38: 2 | K38: =IF(I38=0,0,I38+J38) -> 15 | L38: =INDEX(Prix!$E$5:$E$79,MATCH($A38,Prix!$A$5:$A$79,0)) -> 1 | M38: =IF(K38=0,0,ROUNDUP(K38/L38,0)) -> 15 | N38: =IF(INDEX(Prix!$D$5:$D$79,MATCH($A38,Prix!$A$5:$A$79,0))="","",INDEX(Prix!$D$5:$D$79,MATCH($A38,Prix!$A$5:$A$79,0))) -> 1 | O38: =IF(N38="","",M38*N38) -> 15 | P38: =INDEX(Prix!$C$5:$C$79,MATCH($A38,Prix!$A$5:$A$79,0)) -> Moussasoft | Q38: =INDEX(Prix!$H$5:$H$79,MATCH($A38,Prix!$A$5:$A$79,0)) -> Maroc | S38: lien
A39: LED_V | B39: 4. Semi-conducteurs | C39: LED 5 mm verte | D39: À acheter | E39: =SUMIFS(msp1!$F:$F,msp1!$A:$A,$A39,msp1!$G:$G,$D39) -> 0 | F39: =SUMIFS(n3pp!$F:$F,n3pp!$A:$A,$A39,n3pp!$G:$G,$D39) -> 0 | G39: =SUMIFS('ffp5cs 230V'!$F:$F,'ffp5cs 230V'!$A:$A,$A39,'ffp5cs 230V'!$G:$G,$D39) -> 1 | H39: =SUMIFS('ffp5cs 12V'!$F:$F,'ffp5cs 12V'!$A:$A,$A39,'ffp5cs 12V'!$G:$G,$D39) -> 1 | I39: =SUM(E39:H39) -> 2 | J39: 1 | K39: =IF(I39=0,0,I39+J39) -> 3 | L39: =INDEX(Prix!$E$5:$E$79,MATCH($A39,Prix!$A$5:$A$79,0)) -> 1 | M39: =IF(K39=0,0,ROUNDUP(K39/L39,0)) -> 3 | N39: =IF(INDEX(Prix!$D$5:$D$79,MATCH($A39,Prix!$A$5:$A$79,0))="","",INDEX(Prix!$D$5:$D$79,MATCH($A39,Prix!$A$5:$A$79,0))) -> 0.9 | O39: =IF(N39="","",M39*N39) -> 2.7 | P39: =INDEX(Prix!$C$5:$C$79,MATCH($A39,Prix!$A$5:$A$79,0)) -> Shop4Makers | Q39: =INDEX(Prix!$H$5:$H$79,MATCH($A39,Prix!$A$5:$A$79,0)) -> Maroc | S39: lien
A40: SRD05 | B40: 5. Relais et protection secteur | C40: Relais Songle SRD-05VDC-SL-C (composant seul, pas le module) | D40: À acheter | E40: =SUMIFS(msp1!$F:$F,msp1!$A:$A,$A40,msp1!$G:$G,$D40) -> 0 | F40: =SUMIFS(n3pp!$F:$F,n3pp!$A:$A,$A40,n3pp!$G:$G,$D40) -> 1 | G40: =SUMIFS('ffp5cs 230V'!$F:$F,'ffp5cs 230V'!$A:$A,$A40,'ffp5cs 230V'!$G:$G,$D40) -> 6 | H40: =SUMIFS('ffp5cs 12V'!$F:$F,'ffp5cs 12V'!$A:$A,$A40,'ffp5cs 12V'!$G:$G,$D40) -> 6 | I40: =SUM(E40:H40) -> 13 | J40: 1 | K40: =IF(I40=0,0,I40+J40) -> 14 | L40: =INDEX(Prix!$E$5:$E$79,MATCH($A40,Prix!$A$5:$A$79,0)) -> 1 | M40: =IF(K40=0,0,ROUNDUP(K40/L40,0)) -> 14 | N40: =IF(INDEX(Prix!$D$5:$D$79,MATCH($A40,Prix!$A$5:$A$79,0))="","",INDEX(Prix!$D$5:$D$79,MATCH($A40,Prix!$A$5:$A$79,0))) -> 18 | O40: =IF(N40="","",M40*N40) -> 252 | P40: =INDEX(Prix!$C$5:$C$79,MATCH($A40,Prix!$A$5:$A$79,0)) -> Moussasoft | Q40: =INDEX(Prix!$H$5:$H$79,MATCH($A40,Prix!$A$5:$A$79,0)) -> Maroc | R40: Composant seul 5 broches, pas un module relais. 324 en stock. | S40: lien
A41: VARISTANCE | B41: 5. Relais et protection secteur | C41: Varistance 14D471K (ou 10D471K), pas 7,5 mm | D41: À acheter | E41: =SUMIFS(msp1!$F:$F,msp1!$A:$A,$A41,msp1!$G:$G,$D41) -> 0 | F41: =SUMIFS(n3pp!$F:$F,n3pp!$A:$A,$A41,n3pp!$G:$G,$D41) -> 0 | G41: =SUMIFS('ffp5cs 230V'!$F:$F,'ffp5cs 230V'!$A:$A,$A41,'ffp5cs 230V'!$G:$G,$D41) -> 1 | H41: =SUMIFS('ffp5cs 12V'!$F:$F,'ffp5cs 12V'!$A:$A,$A41,'ffp5cs 12V'!$G:$G,$D41) -> 0 | I41: =SUM(E41:H41) -> 1 | J41: 1 | K41: =IF(I41=0,0,I41+J41) -> 2 | L41: =INDEX(Prix!$E$5:$E$79,MATCH($A41,Prix!$A$5:$A$79,0)) -> 1 | M41: =IF(K41=0,0,ROUNDUP(K41/L41,0)) -> 2 | N41: =IF(INDEX(Prix!$D$5:$D$79,MATCH($A41,Prix!$A$5:$A$79,0))="","",INDEX(Prix!$D$5:$D$79,MATCH($A41,Prix!$A$5:$A$79,0))) -> 4 | O41: =IF(N41="","",M41*N41) -> 8 | P41: =INDEX(Prix!$C$5:$C$79,MATCH($A41,Prix!$A$5:$A$79,0)) -> MicroPlanet | Q41: =INDEX(Prix!$H$5:$H$79,MATCH($A41,Prix!$A$5:$A$79,0)) -> Maroc | R41: Variante 470 V (471). | S41: lien
A42: PORTEFUS_5x20 | B42: 5. Relais et protection secteur | C42: Porte-fusible 5×20 pour circuit imprimé, à capot (pas 22–22,6 mm) | D42: À acheter | E42: =SUMIFS(msp1!$F:$F,msp1!$A:$A,$A42,msp1!$G:$G,$D42) -> 0 | F42: =SUMIFS(n3pp!$F:$F,n3pp!$A:$A,$A42,n3pp!$G:$G,$D42) -> 0 | G42: =SUMIFS('ffp5cs 230V'!$F:$F,'ffp5cs 230V'!$A:$A,$A42,'ffp5cs 230V'!$G:$G,$D42) -> 1 | H42: =SUMIFS('ffp5cs 12V'!$F:$F,'ffp5cs 12V'!$A:$A,$A42,'ffp5cs 12V'!$G:$G,$D42) -> 0 | I42: =SUM(E42:H42) -> 1 | J42: 0 | K42: =IF(I42=0,0,I42+J42) -> 1 | L42: =INDEX(Prix!$E$5:$E$79,MATCH($A42,Prix!$A$5:$A$79,0)) -> 1 | M42: =IF(K42=0,0,ROUNDUP(K42/L42,0)) -> 1 | N42: =IF(INDEX(Prix!$D$5:$D$79,MATCH($A42,Prix!$A$5:$A$79,0))="","",INDEX(Prix!$D$5:$D$79,MATCH($A42,Prix!$A$5:$A$79,0))) -> 4 | O42: =IF(N42="","",M42*N42) -> 4 | P42: =INDEX(Prix!$C$5:$C$79,MATCH($A42,Prix!$A$5:$A$79,0)) -> Moussasoft | Q42: =INDEX(Prix!$H$5:$H$79,MATCH($A42,Prix!$A$5:$A$79,0)) -> Maroc | R42: Mesurer l'entraxe des pattes AVANT achat : 22,0–22,6 mm. Sinon LCSC C3131. | S42: lien
A43: FUS_T1A | B43: 5. Relais et protection secteur | C43: Fusible verre 5×20 temporisé T1A | D43: À acheter | E43: =SUMIFS(msp1!$F:$F,msp1!$A:$A,$A43,msp1!$G:$G,$D43) -> 0 | F43: =SUMIFS(n3pp!$F:$F,n3pp!$A:$A,$A43,n3pp!$G:$G,$D43) -> 0 | G43: =SUMIFS('ffp5cs 230V'!$F:$F,'ffp5cs 230V'!$A:$A,$A43,'ffp5cs 230V'!$G:$G,$D43) -> 3 | H43: =SUMIFS('ffp5cs 12V'!$F:$F,'ffp5cs 12V'!$A:$A,$A43,'ffp5cs 12V'!$G:$G,$D43) -> 0 | I43: =SUM(E43:H43) -> 3 | J43: 0 | K43: =IF(I43=0,0,I43+J43) -> 3 | L43: =INDEX(Prix!$E$5:$E$79,MATCH($A43,Prix!$A$5:$A$79,0)) -> 1 | M43: =IF(K43=0,0,ROUNDUP(K43/L43,0)) -> 3 | N43: =IF(INDEX(Prix!$D$5:$D$79,MATCH($A43,Prix!$A$5:$A$79,0))="","",INDEX(Prix!$D$5:$D$79,MATCH($A43,Prix!$A$5:$A$79,0))) -> 0.5 | O43: =IF(N43="","",M43*N43) -> 1.5 | P43: =INDEX(Prix!$C$5:$C$79,MATCH($A43,Prix!$A$5:$A$79,0)) -> Megma | Q43: =INDEX(Prix!$H$5:$H$79,MATCH($A43,Prix!$A$5:$A$79,0)) -> Maroc | R43: Le type T (temporisé) n'est pas indiqué : demander « T1A » ; un fusible rapide F peut sauter au branchement. | S43: lien
A44: HLK20M05 | B44: 5. Relais et protection secteur | C44: Module Hi-Link HLK-20M05 (230 V → 5 V 3,6 A) | D44: À acheter | E44: =SUMIFS(msp1!$F:$F,msp1!$A:$A,$A44,msp1!$G:$G,$D44) -> 0 | F44: =SUMIFS(n3pp!$F:$F,n3pp!$A:$A,$A44,n3pp!$G:$G,$D44) -> 0 | G44: =SUMIFS('ffp5cs 230V'!$F:$F,'ffp5cs 230V'!$A:$A,$A44,'ffp5cs 230V'!$G:$G,$D44) -> 1 | H44: =SUMIFS('ffp5cs 12V'!$F:$F,'ffp5cs 12V'!$A:$A,$A44,'ffp5cs 12V'!$G:$G,$D44) -> 0 | I44: =SUM(E44:H44) -> 1 | J44: 0 | K44: =IF(I44=0,0,I44+J44) -> 1 | L44: =INDEX(Prix!$E$5:$E$79,MATCH($A44,Prix!$A$5:$A$79,0)) -> 1 | M44: =IF(K44=0,0,ROUNDUP(K44/L44,0)) -> 1 | N44: =IF(INDEX(Prix!$D$5:$D$79,MATCH($A44,Prix!$A$5:$A$79,0))="","",INDEX(Prix!$D$5:$D$79,MATCH($A44,Prix!$A$5:$A$79,0))) -> 90 | O44: =IF(N44="","",M44*N44) -> 90 | P44: =INDEX(Prix!$C$5:$C$79,MATCH($A44,Prix!$A$5:$A$79,0)) -> Shop4Makers | Q44: =INDEX(Prix!$H$5:$H$79,MATCH($A44,Prix!$A$5:$A$79,0)) -> Maroc | R44: Authenticité non garantie : mesurer les entraxes des broches (COMMANDE.md §0.3) avant de souder. | S44: lien
A45: BORNIER_2P | B45: 6. Connectique carte | C45: Bornier à vis 2 pôles pas 5,08 (KF301-2P) | D45: À acheter | E45: =SUMIFS(msp1!$F:$F,msp1!$A:$A,$A45,msp1!$G:$G,$D45) -> 5 | F45: =SUMIFS(n3pp!$F:$F,n3pp!$A:$A,$A45,n3pp!$G:$G,$D45) -> 5 | G45: =SUMIFS('ffp5cs 230V'!$F:$F,'ffp5cs 230V'!$A:$A,$A45,'ffp5cs 230V'!$G:$G,$D45) -> 5 | H45: =SUMIFS('ffp5cs 12V'!$F:$F,'ffp5cs 12V'!$A:$A,$A45,'ffp5cs 12V'!$G:$G,$D45) -> 8 | I45: =SUM(E45:H45) -> 23 | J45: 3 | K45: =IF(I45=0,0,I45+J45) -> 26 | L45: =INDEX(Prix!$E$5:$E$79,MATCH($A45,Prix!$A$5:$A$79,0)) -> 1 | M45: =IF(K45=0,0,ROUNDUP(K45/L45,0)) -> 26 | N45: =IF(INDEX(Prix!$D$5:$D$79,MATCH($A45,Prix!$A$5:$A$79,0))="","",INDEX(Prix!$D$5:$D$79,MATCH($A45,Prix!$A$5:$A$79,0))) -> 2 | O45: =IF(N45="","",M45*N45) -> 52 | P45: =INDEX(Prix!$C$5:$C$79,MATCH($A45,Prix!$A$5:$A$79,0)) -> MicroPlanet | Q45: =INDEX(Prix!$H$5:$H$79,MATCH($A45,Prix!$A$5:$A$79,0)) -> Maroc | R45: KF301 annoncé au pas de 5,0 mm : se monte sur les trous 5,08 (écart 0,08 mm). | S45: lien
A46: BORNIER_3P | B46: 6. Connectique carte | C46: Bornier à vis 3 pôles pas 5,08 (KF301-3P) | D46: À acheter | E46: =SUMIFS(msp1!$F:$F,msp1!$A:$A,$A46,msp1!$G:$G,$D46) -> 8 | F46: =SUMIFS(n3pp!$F:$F,n3pp!$A:$A,$A46,n3pp!$G:$G,$D46) -> 6 | G46: =SUMIFS('ffp5cs 230V'!$F:$F,'ffp5cs 230V'!$A:$A,$A46,'ffp5cs 230V'!$G:$G,$D46) -> 8 | H46: =SUMIFS('ffp5cs 12V'!$F:$F,'ffp5cs 12V'!$A:$A,$A46,'ffp5cs 12V'!$G:$G,$D46) -> 8 | I46: =SUM(E46:H46) -> 30 | J46: 3 | K46: =IF(I46=0,0,I46+J46) -> 33 | L46: =INDEX(Prix!$E$5:$E$79,MATCH($A46,Prix!$A$5:$A$79,0)) -> 1 | M46: =IF(K46=0,0,ROUNDUP(K46/L46,0)) -> 33 | N46: =IF(INDEX(Prix!$D$5:$D$79,MATCH($A46,Prix!$A$5:$A$79,0))="","",INDEX(Prix!$D$5:$D$79,MATCH($A46,Prix!$A$5:$A$79,0))) -> 3 | O46: =IF(N46="","",M46*N46) -> 99 | P46: =INDEX(Prix!$C$5:$C$79,MATCH($A46,Prix!$A$5:$A$79,0)) -> MicroPlanet | Q46: =INDEX(Prix!$H$5:$H$79,MATCH($A46,Prix!$A$5:$A$79,0)) -> Maroc | R46: KF301 pas 5,0 mm : se monte sur les trous 5,08. | S46: lien
A47: BORNIER_4P | B47: 6. Connectique carte | C47: Bornier à vis 4 pôles pas 5,08 (ou 2+2 emboîtés) | D47: À acheter | E47: =SUMIFS(msp1!$F:$F,msp1!$A:$A,$A47,msp1!$G:$G,$D47) -> 0 | F47: =SUMIFS(n3pp!$F:$F,n3pp!$A:$A,$A47,n3pp!$G:$G,$D47) -> 0 | G47: =SUMIFS('ffp5cs 230V'!$F:$F,'ffp5cs 230V'!$A:$A,$A47,'ffp5cs 230V'!$G:$G,$D47) -> 3 | H47: =SUMIFS('ffp5cs 12V'!$F:$F,'ffp5cs 12V'!$A:$A,$A47,'ffp5cs 12V'!$G:$G,$D47) -> 3 | I47: =SUM(E47:H47) -> 6 | J47: 1 | K47: =IF(I47=0,0,I47+J47) -> 7 | L47: =INDEX(Prix!$E$5:$E$79,MATCH($A47,Prix!$A$5:$A$79,0)) -> 1 | M47: =IF(K47=0,0,ROUNDUP(K47/L47,0)) -> 7 | N47: =IF(INDEX(Prix!$D$5:$D$79,MATCH($A47,Prix!$A$5:$A$79,0))="","",INDEX(Prix!$D$5:$D$79,MATCH($A47,Prix!$A$5:$A$79,0))) -> 5 | O47: =IF(N47="","",M47*N47) -> 35 | P47: =INDEX(Prix!$C$5:$C$79,MATCH($A47,Prix!$A$5:$A$79,0)) -> MicroPlanet | Q47: =INDEX(Prix!$H$5:$H$79,MATCH($A47,Prix!$A$5:$A$79,0)) -> Maroc | R47: KF128-4P. Sur 4 pôles, l'écart 5,0/5,08 cumule 0,24 mm : présenter avant de souder, ou 2 × KF301-2P emboîtés. | S47: lien
A48: BARRETTE_F | B48: 6. Connectique carte | C48: Barrette femelle sécable 1×40 pas 2,54 | D48: À acheter | E48: =SUMIFS(msp1!$F:$F,msp1!$A:$A,$A48,msp1!$G:$G,$D48) -> 2 | F48: =SUMIFS(n3pp!$F:$F,n3pp!$A:$A,$A48,n3pp!$G:$G,$D48) -> 2 | G48: =SUMIFS('ffp5cs 230V'!$F:$F,'ffp5cs 230V'!$A:$A,$A48,'ffp5cs 230V'!$G:$G,$D48) -> 2 | H48: =SUMIFS('ffp5cs 12V'!$F:$F,'ffp5cs 12V'!$A:$A,$A48,'ffp5cs 12V'!$G:$G,$D48) -> 2 | I48: =SUM(E48:H48) -> 8 | J48: 1 | K48: =IF(I48=0,0,I48+J48) -> 9 | L48: =INDEX(Prix!$E$5:$E$79,MATCH($A48,Prix!$A$5:$A$79,0)) -> 1 | M48: =IF(K48=0,0,ROUNDUP(K48/L48,0)) -> 9 | N48: =IF(INDEX(Prix!$D$5:$D$79,MATCH($A48,Prix!$A$5:$A$79,0))="","",INDEX(Prix!$D$5:$D$79,MATCH($A48,Prix!$A$5:$A$79,0))) -> 5 | O48: =IF(N48="","",M48*N48) -> 45 | P48: =INDEX(Prix!$C$5:$C$79,MATCH($A48,Prix!$A$5:$A$79,0)) -> Moussasoft | Q48: =INDEX(Prix!$H$5:$H$79,MATCH($A48,Prix!$A$5:$A$79,0)) -> Maroc | R48: Une broche perdue à chaque coupe (compté). | S48: lien
A49: BARRETTE_M | B49: 6. Connectique carte | C49: Barrette mâle sécable 1×40 pas 2,54 | D49: À acheter | E49: =SUMIFS(msp1!$F:$F,msp1!$A:$A,$A49,msp1!$G:$G,$D49) -> 2 | F49: =SUMIFS(n3pp!$F:$F,n3pp!$A:$A,$A49,n3pp!$G:$G,$D49) -> 2 | G49: =SUMIFS('ffp5cs 230V'!$F:$F,'ffp5cs 230V'!$A:$A,$A49,'ffp5cs 230V'!$G:$G,$D49) -> 2 | H49: =SUMIFS('ffp5cs 12V'!$F:$F,'ffp5cs 12V'!$A:$A,$A49,'ffp5cs 12V'!$G:$G,$D49) -> 2 | I49: =SUM(E49:H49) -> 8 | J49: 1 | K49: =IF(I49=0,0,I49+J49) -> 9 | L49: =INDEX(Prix!$E$5:$E$79,MATCH($A49,Prix!$A$5:$A$79,0)) -> 1 | M49: =IF(K49=0,0,ROUNDUP(K49/L49,0)) -> 9 | N49: =IF(INDEX(Prix!$D$5:$D$79,MATCH($A49,Prix!$A$5:$A$79,0))="","",INDEX(Prix!$D$5:$D$79,MATCH($A49,Prix!$A$5:$A$79,0))) -> 4 | O49: =IF(N49="","",M49*N49) -> 36 | P49: =INDEX(Prix!$C$5:$C$79,MATCH($A49,Prix!$A$5:$A$79,0)) -> Moussasoft | Q49: =INDEX(Prix!$H$5:$H$79,MATCH($A49,Prix!$A$5:$A$79,0)) -> Maroc | S49: lien
A50: CAVALIER | B50: 6. Connectique carte | C50: Cavalier (jumper) 2,54 mm | D50: À acheter | E50: =SUMIFS(msp1!$F:$F,msp1!$A:$A,$A50,msp1!$G:$G,$D50) -> 9 | F50: =SUMIFS(n3pp!$F:$F,n3pp!$A:$A,$A50,n3pp!$G:$G,$D50) -> 5 | G50: =SUMIFS('ffp5cs 230V'!$F:$F,'ffp5cs 230V'!$A:$A,$A50,'ffp5cs 230V'!$G:$G,$D50) -> 7 | H50: =SUMIFS('ffp5cs 12V'!$F:$F,'ffp5cs 12V'!$A:$A,$A50,'ffp5cs 12V'!$G:$G,$D50) -> 8 | I50: =SUM(E50:H50) -> 29 | J50: 5 | K50: =IF(I50=0,0,I50+J50) -> 34 | L50: =INDEX(Prix!$E$5:$E$79,MATCH($A50,Prix!$A$5:$A$79,0)) -> 10 | M50: =IF(K50=0,0,ROUNDUP(K50/L50,0)) -> 4 | N50: =IF(INDEX(Prix!$D$5:$D$79,MATCH($A50,Prix!$A$5:$A$79,0))="","",INDEX(Prix!$D$5:$D$79,MATCH($A50,Prix!$A$5:$A$79,0))) -> 5 | O50: =IF(N50="","",M50*N50) -> 20 | P50: =INDEX(Prix!$C$5:$C$79,MATCH($A50,Prix!$A$5:$A$79,0)) -> Shop4Makers | Q50: =INDEX(Prix!$H$5:$H$79,MATCH($A50,Prix!$A$5:$A$79,0)) -> Maroc | R50: Prix du plus petit lot (bas de la fourchette affichée). | S50: lien
A51: JACK_DC | B51: 6. Connectique carte | C51: Jack DC femelle 5,5×2,1 pour circuit imprimé (DC-005) | D51: À acheter | E51: =SUMIFS(msp1!$F:$F,msp1!$A:$A,$A51,msp1!$G:$G,$D51) -> 0 | F51: =SUMIFS(n3pp!$F:$F,n3pp!$A:$A,$A51,n3pp!$G:$G,$D51) -> 1 | G51: =SUMIFS('ffp5cs 230V'!$F:$F,'ffp5cs 230V'!$A:$A,$A51,'ffp5cs 230V'!$G:$G,$D51) -> 0 | H51: =SUMIFS('ffp5cs 12V'!$F:$F,'ffp5cs 12V'!$A:$A,$A51,'ffp5cs 12V'!$G:$G,$D51) -> 0 | I51: =SUM(E51:H51) -> 1 | J51: 0 | K51: =IF(I51=0,0,I51+J51) -> 1 | L51: =INDEX(Prix!$E$5:$E$79,MATCH($A51,Prix!$A$5:$A$79,0)) -> 1 | M51: =IF(K51=0,0,ROUNDUP(K51/L51,0)) -> 1 | N51: =IF(INDEX(Prix!$D$5:$D$79,MATCH($A51,Prix!$A$5:$A$79,0))="","",INDEX(Prix!$D$5:$D$79,MATCH($A51,Prix!$A$5:$A$79,0))) -> 4 | O51: =IF(N51="","",M51*N51) -> 4 | P51: =INDEX(Prix!$C$5:$C$79,MATCH($A51,Prix!$A$5:$A$79,0)) -> ShoppingMaroc | Q51: =INDEX(Prix!$H$5:$H$79,MATCH($A51,Prix!$A$5:$A$79,0)) -> Maroc | R51: DC-005 traversant 3 broches. | S51: lien
A52: FIL | B52: 6. Connectique carte | C52: Pont de fil à la place de D5 (chute de patte de résistance) | D52: À acheter | E52: =SUMIFS(msp1!$F:$F,msp1!$A:$A,$A52,msp1!$G:$G,$D52) -> 1 | F52: =SUMIFS(n3pp!$F:$F,n3pp!$A:$A,$A52,n3pp!$G:$G,$D52) -> 1 | G52: =SUMIFS('ffp5cs 230V'!$F:$F,'ffp5cs 230V'!$A:$A,$A52,'ffp5cs 230V'!$G:$G,$D52) -> 1 | H52: =SUMIFS('ffp5cs 12V'!$F:$F,'ffp5cs 12V'!$A:$A,$A52,'ffp5cs 12V'!$G:$G,$D52) -> 1 | I52: =SUM(E52:H52) -> 4 | J52: 0 | K52: =IF(I52=0,0,I52+J52) -> 4 | L52: =INDEX(Prix!$E$5:$E$79,MATCH($A52,Prix!$A$5:$A$79,0)) -> 1 | M52: =IF(K52=0,0,ROUNDUP(K52/L52,0)) -> 4 | N52: =IF(INDEX(Prix!$D$5:$D$79,MATCH($A52,Prix!$A$5:$A$79,0))="","",INDEX(Prix!$D$5:$D$79,MATCH($A52,Prix!$A$5:$A$79,0))) -> 0 | O52: =IF(N52="","",M52*N52) -> 0 | P52: =INDEX(Prix!$C$5:$C$79,MATCH($A52,Prix!$A$5:$A$79,0)) -> — | Q52: =INDEX(Prix!$H$5:$H$79,MATCH($A52,Prix!$A$5:$A$79,0)) -> Maroc | R52: Chute de patte de résistance : gratuit.
A53: TP_FIL | B53: 6. Connectique carte | C53: Points de test TP1-TP4 : boucle de fil (chute de patte) | D53: À acheter | E53: =SUMIFS(msp1!$F:$F,msp1!$A:$A,$A53,msp1!$G:$G,$D53) -> 4 | F53: =SUMIFS(n3pp!$F:$F,n3pp!$A:$A,$A53,n3pp!$G:$G,$D53) -> 4 | G53: =SUMIFS('ffp5cs 230V'!$F:$F,'ffp5cs 230V'!$A:$A,$A53,'ffp5cs 230V'!$G:$G,$D53) -> 4 | H53: =SUMIFS('ffp5cs 12V'!$F:$F,'ffp5cs 12V'!$A:$A,$A53,'ffp5cs 12V'!$G:$G,$D53) -> 4 | I53: =SUM(E53:H53) -> 16 | J53: 0 | K53: =IF(I53=0,0,I53+J53) -> 16 | L53: =INDEX(Prix!$E$5:$E$79,MATCH($A53,Prix!$A$5:$A$79,0)) -> 1 | M53: =IF(K53=0,0,ROUNDUP(K53/L53,0)) -> 16 | N53: =IF(INDEX(Prix!$D$5:$D$79,MATCH($A53,Prix!$A$5:$A$79,0))="","",INDEX(Prix!$D$5:$D$79,MATCH($A53,Prix!$A$5:$A$79,0))) -> 0 | O53: =IF(N53="","",M53*N53) -> 0 | P53: =INDEX(Prix!$C$5:$C$79,MATCH($A53,Prix!$A$5:$A$79,0)) -> — | Q53: =INDEX(Prix!$H$5:$H$79,MATCH($A53,Prix!$A$5:$A$79,0)) -> Maroc | R53: Chute de patte : gratuit.
A54: DHT11 | B54: 7. Capteurs et actionneurs | C54: Capteur température/humidité DHT11 | D54: À acheter | E54: =SUMIFS(msp1!$F:$F,msp1!$A:$A,$A54,msp1!$G:$G,$D54) -> 2 | F54: =SUMIFS(n3pp!$F:$F,n3pp!$A:$A,$A54,n3pp!$G:$G,$D54) -> 1 | G54: =SUMIFS('ffp5cs 230V'!$F:$F,'ffp5cs 230V'!$A:$A,$A54,'ffp5cs 230V'!$G:$G,$D54) -> 1 | H54: =SUMIFS('ffp5cs 12V'!$F:$F,'ffp5cs 12V'!$A:$A,$A54,'ffp5cs 12V'!$G:$G,$D54) -> 1 | I54: =SUM(E54:H54) -> 5 | J54: 1 | K54: =IF(I54=0,0,I54+J54) -> 6 | L54: =INDEX(Prix!$E$5:$E$79,MATCH($A54,Prix!$A$5:$A$79,0)) -> 1 | M54: =IF(K54=0,0,ROUNDUP(K54/L54,0)) -> 6 | N54: =IF(INDEX(Prix!$D$5:$D$79,MATCH($A54,Prix!$A$5:$A$79,0))="","",INDEX(Prix!$D$5:$D$79,MATCH($A54,Prix!$A$5:$A$79,0))) -> 16.2 | O54: =IF(N54="","",M54*N54) -> 97.2 | P54: =INDEX(Prix!$C$5:$C$79,MATCH($A54,Prix!$A$5:$A$79,0)) -> Shop4Makers | Q54: =INDEX(Prix!$H$5:$H$79,MATCH($A54,Prix!$A$5:$A$79,0)) -> Maroc | R54: Capteur nu 4 broches : 1=VCC 2=DATA 3=libre 4=GND (pull-up déjà sur la carte). DHT22 : 49,50 DH. | S54: lien
A55: BME280 | B55: 7. Capteurs et actionneurs | C55: Module BME280 I2C (température, humidité, pression) | D55: Option | E55: =SUMIFS(msp1!$F:$F,msp1!$A:$A,$A55,msp1!$G:$G,$D55) -> 2 | F55: =SUMIFS(n3pp!$F:$F,n3pp!$A:$A,$A55,n3pp!$G:$G,$D55) -> 1 | G55: =SUMIFS('ffp5cs 230V'!$F:$F,'ffp5cs 230V'!$A:$A,$A55,'ffp5cs 230V'!$G:$G,$D55) -> 0 | H55: =SUMIFS('ffp5cs 12V'!$F:$F,'ffp5cs 12V'!$A:$A,$A55,'ffp5cs 12V'!$G:$G,$D55) -> 0 | I55: =SUM(E55:H55) -> 3 | J55: 0 | K55: =IF(I55=0,0,I55+J55) -> 3 | L55: =INDEX(Prix!$E$5:$E$79,MATCH($A55,Prix!$A$5:$A$79,0)) -> 1 | M55: =IF(K55=0,0,ROUNDUP(K55/L55,0)) -> 3 | N55: =IF(INDEX(Prix!$D$5:$D$79,MATCH($A55,Prix!$A$5:$A$79,0))="","",INDEX(Prix!$D$5:$D$79,MATCH($A55,Prix!$A$5:$A$79,0))) -> 85 | O55: =IF(N55="","",M55*N55) -> 255 | P55: =INDEX(Prix!$C$5:$C$79,MATCH($A55,Prix!$A$5:$A$79,0)) -> Shop4Makers | Q55: =INDEX(Prix!$H$5:$H$79,MATCH($A55,Prix!$A$5:$A$79,0)) -> Maroc | R55: Prendre la version 3,3 V (pas un BMP280, sans humidité). Raccorder par fils Dupont. | S55: lien
A56: DS18B20 | B56: 7. Capteurs et actionneurs | C56: Sonde DS18B20 étanche (câble 1 m) | D56: À acheter | E56: =SUMIFS(msp1!$F:$F,msp1!$A:$A,$A56,msp1!$G:$G,$D56) -> 1 | F56: =SUMIFS(n3pp!$F:$F,n3pp!$A:$A,$A56,n3pp!$G:$G,$D56) -> 0 | G56: =SUMIFS('ffp5cs 230V'!$F:$F,'ffp5cs 230V'!$A:$A,$A56,'ffp5cs 230V'!$G:$G,$D56) -> 1 | H56: =SUMIFS('ffp5cs 12V'!$F:$F,'ffp5cs 12V'!$A:$A,$A56,'ffp5cs 12V'!$G:$G,$D56) -> 1 | I56: =SUM(E56:H56) -> 3 | J56: 0 | K56: =IF(I56=0,0,I56+J56) -> 3 | L56: =INDEX(Prix!$E$5:$E$79,MATCH($A56,Prix!$A$5:$A$79,0)) -> 1 | M56: =IF(K56=0,0,ROUNDUP(K56/L56,0)) -> 3 | N56: =IF(INDEX(Prix!$D$5:$D$79,MATCH($A56,Prix!$A$5:$A$79,0))="","",INDEX(Prix!$D$5:$D$79,MATCH($A56,Prix!$A$5:$A$79,0))) -> 50 | O56: =IF(N56="","",M56*N56) -> 150 | P56: =INDEX(Prix!$C$5:$C$79,MATCH($A56,Prix!$A$5:$A$79,0)) -> A2itronic | Q56: =INDEX(Prix!$H$5:$H$79,MATCH($A56,Prix!$A$5:$A$79,0)) -> Maroc | R56: Étanche ~1 m. Shop4Makers 36 DH mais en rupture. | S56: lien
A57: LDR | B57: 7. Capteurs et actionneurs | C57: Photorésistance LDR GL5528 | D57: À acheter | E57: =SUMIFS(msp1!$F:$F,msp1!$A:$A,$A57,msp1!$G:$G,$D57) -> 4 | F57: =SUMIFS(n3pp!$F:$F,n3pp!$A:$A,$A57,n3pp!$G:$G,$D57) -> 1 | G57: =SUMIFS('ffp5cs 230V'!$F:$F,'ffp5cs 230V'!$A:$A,$A57,'ffp5cs 230V'!$G:$G,$D57) -> 1 | H57: =SUMIFS('ffp5cs 12V'!$F:$F,'ffp5cs 12V'!$A:$A,$A57,'ffp5cs 12V'!$G:$G,$D57) -> 1 | I57: =SUM(E57:H57) -> 7 | J57: 2 | K57: =IF(I57=0,0,I57+J57) -> 9 | L57: =INDEX(Prix!$E$5:$E$79,MATCH($A57,Prix!$A$5:$A$79,0)) -> 1 | M57: =IF(K57=0,0,ROUNDUP(K57/L57,0)) -> 9 | N57: =IF(INDEX(Prix!$D$5:$D$79,MATCH($A57,Prix!$A$5:$A$79,0))="","",INDEX(Prix!$D$5:$D$79,MATCH($A57,Prix!$A$5:$A$79,0))) -> 2 | O57: =IF(N57="","",M57*N57) -> 18 | P57: =INDEX(Prix!$C$5:$C$79,MATCH($A57,Prix!$A$5:$A$79,0)) -> Moussasoft | Q57: =INDEX(Prix!$H$5:$H$79,MATCH($A57,Prix!$A$5:$A$79,0)) -> Maroc | R57: GL5528 introuvable à l'unité : GM5539 (plus résistante dans le noir, sans effet en plein jour). Les 4 LDR du tracker du même lot. | S57: lien
A58: PLUIE | B58: 7. Capteurs et actionneurs | C58: Module capteur de pluie FC-37 / YL-83 (sortie DO) | D58: À acheter | E58: =SUMIFS(msp1!$F:$F,msp1!$A:$A,$A58,msp1!$G:$G,$D58) -> 1 | F58: =SUMIFS(n3pp!$F:$F,n3pp!$A:$A,$A58,n3pp!$G:$G,$D58) -> 0 | G58: =SUMIFS('ffp5cs 230V'!$F:$F,'ffp5cs 230V'!$A:$A,$A58,'ffp5cs 230V'!$G:$G,$D58) -> 0 | H58: =SUMIFS('ffp5cs 12V'!$F:$F,'ffp5cs 12V'!$A:$A,$A58,'ffp5cs 12V'!$G:$G,$D58) -> 0 | I58: =SUM(E58:H58) -> 1 | J58: 0 | K58: =IF(I58=0,0,I58+J58) -> 1 | L58: =INDEX(Prix!$E$5:$E$79,MATCH($A58,Prix!$A$5:$A$79,0)) -> 1 | M58: =IF(K58=0,0,ROUNDUP(K58/L58,0)) -> 1 | N58: =IF(INDEX(Prix!$D$5:$D$79,MATCH($A58,Prix!$A$5:$A$79,0))="","",INDEX(Prix!$D$5:$D$79,MATCH($A58,Prix!$A$5:$A$79,0))) -> 25 | O58: =IF(N58="","",M58*N58) -> 25 | P58: =INDEX(Prix!$C$5:$C$79,MATCH($A58,Prix!$A$5:$A$79,0)) -> Moussasoft | Q58: =INDEX(Prix!$H$5:$H$79,MATCH($A58,Prix!$A$5:$A$79,0)) -> Maroc | R58: Plaque + module comparateur ; utiliser la sortie DO. | S58: lien
A59: SOL_CAPA | B59: 7. Capteurs et actionneurs | C59: Capteur d'humidité du sol capacitif v1.2 (sortie AO) | D59: À acheter | E59: =SUMIFS(msp1!$F:$F,msp1!$A:$A,$A59,msp1!$G:$G,$D59) -> 1 | F59: =SUMIFS(n3pp!$F:$F,n3pp!$A:$A,$A59,n3pp!$G:$G,$D59) -> 4 | G59: =SUMIFS('ffp5cs 230V'!$F:$F,'ffp5cs 230V'!$A:$A,$A59,'ffp5cs 230V'!$G:$G,$D59) -> 0 | H59: =SUMIFS('ffp5cs 12V'!$F:$F,'ffp5cs 12V'!$A:$A,$A59,'ffp5cs 12V'!$G:$G,$D59) -> 0 | I59: =SUM(E59:H59) -> 5 | J59: 1 | K59: =IF(I59=0,0,I59+J59) -> 6 | L59: =INDEX(Prix!$E$5:$E$79,MATCH($A59,Prix!$A$5:$A$79,0)) -> 1 | M59: =IF(K59=0,0,ROUNDUP(K59/L59,0)) -> 6 | N59: =IF(INDEX(Prix!$D$5:$D$79,MATCH($A59,Prix!$A$5:$A$79,0))="","",INDEX(Prix!$D$5:$D$79,MATCH($A59,Prix!$A$5:$A$79,0))) -> 35 | O59: =IF(N59="","",M59*N59) -> 210 | P59: =INDEX(Prix!$C$5:$C$79,MATCH($A59,Prix!$A$5:$A$79,0)) -> Shop4Makers | Q59: =INDEX(Prix!$H$5:$H$79,MATCH($A59,Prix!$A$5:$A$79,0)) -> Maroc | R59: Étalonner sec / dans l'eau sous 3,3 V. Vernir le bord de la carte du capteur (électronique exposée). | S59: lien
A60: HCSR04 | B60: 7. Capteurs et actionneurs | C60: Capteur ultrason HC-SR04 | D60: À acheter | E60: =SUMIFS(msp1!$F:$F,msp1!$A:$A,$A60,msp1!$G:$G,$D60) -> 0 | F60: =SUMIFS(n3pp!$F:$F,n3pp!$A:$A,$A60,n3pp!$G:$G,$D60) -> 0 | G60: =SUMIFS('ffp5cs 230V'!$F:$F,'ffp5cs 230V'!$A:$A,$A60,'ffp5cs 230V'!$G:$G,$D60) -> 3 | H60: =SUMIFS('ffp5cs 12V'!$F:$F,'ffp5cs 12V'!$A:$A,$A60,'ffp5cs 12V'!$G:$G,$D60) -> 3 | I60: =SUM(E60:H60) -> 6 | J60: 1 | K60: =IF(I60=0,0,I60+J60) -> 7 | L60: =INDEX(Prix!$E$5:$E$79,MATCH($A60,Prix!$A$5:$A$79,0)) -> 1 | M60: =IF(K60=0,0,ROUNDUP(K60/L60,0)) -> 7 | N60: =IF(INDEX(Prix!$D$5:$D$79,MATCH($A60,Prix!$A$5:$A$79,0))="","",INDEX(Prix!$D$5:$D$79,MATCH($A60,Prix!$A$5:$A$79,0))) -> 25 | O60: =IF(N60="","",M60*N60) -> 175 | P60: =INDEX(Prix!$C$5:$C$79,MATCH($A60,Prix!$A$5:$A$79,0)) -> Moussasoft | Q60: =INDEX(Prix!$H$5:$H$79,MATCH($A60,Prix!$A$5:$A$79,0)) -> Maroc | S60: lien
A61: SG90 | B61: 7. Capteurs et actionneurs | C61: Servomoteur SG90 | D61: À acheter | E61: =SUMIFS(msp1!$F:$F,msp1!$A:$A,$A61,msp1!$G:$G,$D61) -> 2 | F61: =SUMIFS(n3pp!$F:$F,n3pp!$A:$A,$A61,n3pp!$G:$G,$D61) -> 0 | G61: =SUMIFS('ffp5cs 230V'!$F:$F,'ffp5cs 230V'!$A:$A,$A61,'ffp5cs 230V'!$G:$G,$D61) -> 2 | H61: =SUMIFS('ffp5cs 12V'!$F:$F,'ffp5cs 12V'!$A:$A,$A61,'ffp5cs 12V'!$G:$G,$D61) -> 2 | I61: =SUM(E61:H61) -> 6 | J61: 1 | K61: =IF(I61=0,0,I61+J61) -> 7 | L61: =INDEX(Prix!$E$5:$E$79,MATCH($A61,Prix!$A$5:$A$79,0)) -> 1 | M61: =IF(K61=0,0,ROUNDUP(K61/L61,0)) -> 7 | N61: =IF(INDEX(Prix!$D$5:$D$79,MATCH($A61,Prix!$A$5:$A$79,0))="","",INDEX(Prix!$D$5:$D$79,MATCH($A61,Prix!$A$5:$A$79,0))) -> 30 | O61: =IF(N61="","",M61*N61) -> 210 | P61: =INDEX(Prix!$C$5:$C$79,MATCH($A61,Prix!$A$5:$A$79,0)) -> Moussasoft | Q61: =INDEX(Prix!$H$5:$H$79,MATCH($A61,Prix!$A$5:$A$79,0)) -> Maroc | R61: Version 180° (pas 360° « rotation continue »). | S61: lien
A62: OLED | B62: 7. Capteurs et actionneurs | C62: Écran OLED 0,96" SSD1306 I2C 128×64 | D62: À acheter | E62: =SUMIFS(msp1!$F:$F,msp1!$A:$A,$A62,msp1!$G:$G,$D62) -> 1 | F62: =SUMIFS(n3pp!$F:$F,n3pp!$A:$A,$A62,n3pp!$G:$G,$D62) -> 1 | G62: =SUMIFS('ffp5cs 230V'!$F:$F,'ffp5cs 230V'!$A:$A,$A62,'ffp5cs 230V'!$G:$G,$D62) -> 1 | H62: =SUMIFS('ffp5cs 12V'!$F:$F,'ffp5cs 12V'!$A:$A,$A62,'ffp5cs 12V'!$G:$G,$D62) -> 1 | I62: =SUM(E62:H62) -> 4 | J62: 0 | K62: =IF(I62=0,0,I62+J62) -> 4 | L62: =INDEX(Prix!$E$5:$E$79,MATCH($A62,Prix!$A$5:$A$79,0)) -> 1 | M62: =IF(K62=0,0,ROUNDUP(K62/L62,0)) -> 4 | N62: =IF(INDEX(Prix!$D$5:$D$79,MATCH($A62,Prix!$A$5:$A$79,0))="","",INDEX(Prix!$D$5:$D$79,MATCH($A62,Prix!$A$5:$A$79,0))) -> 70 | O62: =IF(N62="","",M62*N62) -> 280 | P62: =INDEX(Prix!$C$5:$C$79,MATCH($A62,Prix!$A$5:$A$79,0)) -> Shop4Makers | Q62: =INDEX(Prix!$H$5:$H$79,MATCH($A62,Prix!$A$5:$A$79,0)) -> Maroc | R62: Vérifier l'ordre des broches : J13 = GND-VCC-SCL-SDA. Si le module est VCC-GND-…, NE PAS l'enficher : fils Dupont. | S62: lien
A63: DS3231 | B63: 7. Capteurs et actionneurs | C63: Module horloge RTC DS3231 (ZS-042) | D63: À acheter | E63: =SUMIFS(msp1!$F:$F,msp1!$A:$A,$A63,msp1!$G:$G,$D63) -> 0 | F63: =SUMIFS(n3pp!$F:$F,n3pp!$A:$A,$A63,n3pp!$G:$G,$D63) -> 0 | G63: =SUMIFS('ffp5cs 230V'!$F:$F,'ffp5cs 230V'!$A:$A,$A63,'ffp5cs 230V'!$G:$G,$D63) -> 1 | H63: =SUMIFS('ffp5cs 12V'!$F:$F,'ffp5cs 12V'!$A:$A,$A63,'ffp5cs 12V'!$G:$G,$D63) -> 1 | I63: =SUM(E63:H63) -> 2 | J63: 0 | K63: =IF(I63=0,0,I63+J63) -> 2 | L63: =INDEX(Prix!$E$5:$E$79,MATCH($A63,Prix!$A$5:$A$79,0)) -> 1 | M63: =IF(K63=0,0,ROUNDUP(K63/L63,0)) -> 2 | N63: =IF(INDEX(Prix!$D$5:$D$79,MATCH($A63,Prix!$A$5:$A$79,0))="","",INDEX(Prix!$D$5:$D$79,MATCH($A63,Prix!$A$5:$A$79,0))) -> 29 | O63: =IF(N63="","",M63*N63) -> 58 | P63: =INDEX(Prix!$C$5:$C$79,MATCH($A63,Prix!$A$5:$A$79,0)) -> A2itronic | Q63: =INDEX(Prix!$H$5:$H$79,MATCH($A63,Prix!$A$5:$A$79,0)) -> Maroc | R63: Brochage ZS-042 ≠ J14 : raccorder par fils Dupont (GND, VCC, SCL, SDA). | S63: lien
A64: CR2032 | B64: 7. Capteurs et actionneurs | C64: Pile bouton CR2032 | D64: À acheter | E64: =SUMIFS(msp1!$F:$F,msp1!$A:$A,$A64,msp1!$G:$G,$D64) -> 0 | F64: =SUMIFS(n3pp!$F:$F,n3pp!$A:$A,$A64,n3pp!$G:$G,$D64) -> 0 | G64: =SUMIFS('ffp5cs 230V'!$F:$F,'ffp5cs 230V'!$A:$A,$A64,'ffp5cs 230V'!$G:$G,$D64) -> 1 | H64: =SUMIFS('ffp5cs 12V'!$F:$F,'ffp5cs 12V'!$A:$A,$A64,'ffp5cs 12V'!$G:$G,$D64) -> 1 | I64: =SUM(E64:H64) -> 2 | J64: 0 | K64: =IF(I64=0,0,I64+J64) -> 2 | L64: =INDEX(Prix!$E$5:$E$79,MATCH($A64,Prix!$A$5:$A$79,0)) -> 1 | M64: =IF(K64=0,0,ROUNDUP(K64/L64,0)) -> 2 | N64: =IF(INDEX(Prix!$D$5:$D$79,MATCH($A64,Prix!$A$5:$A$79,0))="","",INDEX(Prix!$D$5:$D$79,MATCH($A64,Prix!$A$5:$A$79,0))) -> 3 | O64: =IF(N64="","",M64*N64) -> 6 | P64: =INDEX(Prix!$C$5:$C$79,MATCH($A64,Prix!$A$5:$A$79,0)) -> Shop4Makers | Q64: =INDEX(Prix!$H$5:$H$79,MATCH($A64,Prix!$A$5:$A$79,0)) -> Maroc | S64: lien
A65: INA226 | B65: 7. Capteurs et actionneurs | C65: Module INA226 (mesure tension/courant I2C) | D65: À acheter | E65: =SUMIFS(msp1!$F:$F,msp1!$A:$A,$A65,msp1!$G:$G,$D65) -> 0 | F65: =SUMIFS(n3pp!$F:$F,n3pp!$A:$A,$A65,n3pp!$G:$G,$D65) -> 0 | G65: =SUMIFS('ffp5cs 230V'!$F:$F,'ffp5cs 230V'!$A:$A,$A65,'ffp5cs 230V'!$G:$G,$D65) -> 0 | H65: =SUMIFS('ffp5cs 12V'!$F:$F,'ffp5cs 12V'!$A:$A,$A65,'ffp5cs 12V'!$G:$G,$D65) -> 1 | I65: =SUM(E65:H65) -> 1 | J65: 0 | K65: =IF(I65=0,0,I65+J65) -> 1 | L65: =INDEX(Prix!$E$5:$E$79,MATCH($A65,Prix!$A$5:$A$79,0)) -> 1 | M65: =IF(K65=0,0,ROUNDUP(K65/L65,0)) -> 1 | N65: =IF(INDEX(Prix!$D$5:$D$79,MATCH($A65,Prix!$A$5:$A$79,0))="","",INDEX(Prix!$D$5:$D$79,MATCH($A65,Prix!$A$5:$A$79,0))) -> 50 | O65: =IF(N65="","",M65*N65) -> 50 | P65: =INDEX(Prix!$C$5:$C$79,MATCH($A65,Prix!$A$5:$A$79,0)) -> Shop4Makers | Q65: =INDEX(Prix!$H$5:$H$79,MATCH($A65,Prix!$A$5:$A$79,0)) -> Maroc | R65: Seul INA226 trouvé au Maroc. Raccorder par fils Dupont selon le brochage du module. | S65: lien
A66: INA226 | B66: 7. Capteurs et actionneurs | C66: Module INA226 (mesure tension/courant I2C) | D66: Option | E66: =SUMIFS(msp1!$F:$F,msp1!$A:$A,$A66,msp1!$G:$G,$D66) -> 0 | F66: =SUMIFS(n3pp!$F:$F,n3pp!$A:$A,$A66,n3pp!$G:$G,$D66) -> 0 | G66: =SUMIFS('ffp5cs 230V'!$F:$F,'ffp5cs 230V'!$A:$A,$A66,'ffp5cs 230V'!$G:$G,$D66) -> 0 | H66: =SUMIFS('ffp5cs 12V'!$F:$F,'ffp5cs 12V'!$A:$A,$A66,'ffp5cs 12V'!$G:$G,$D66) -> 2 | I66: =SUM(E66:H66) -> 2 | J66: 0 | K66: =IF(I66=0,0,I66+J66) -> 2 | L66: =INDEX(Prix!$E$5:$E$79,MATCH($A66,Prix!$A$5:$A$79,0)) -> 1 | M66: =IF(K66=0,0,ROUNDUP(K66/L66,0)) -> 2 | N66: =IF(INDEX(Prix!$D$5:$D$79,MATCH($A66,Prix!$A$5:$A$79,0))="","",INDEX(Prix!$D$5:$D$79,MATCH($A66,Prix!$A$5:$A$79,0))) -> 50 | O66: =IF(N66="","",M66*N66) -> 100 | P66: =INDEX(Prix!$C$5:$C$79,MATCH($A66,Prix!$A$5:$A$79,0)) -> Shop4Makers | Q66: =INDEX(Prix!$H$5:$H$79,MATCH($A66,Prix!$A$5:$A$79,0)) -> Maroc | R66: Seul INA226 trouvé au Maroc. Raccorder par fils Dupont selon le brochage du module. | S66: lien
A67: MICROSD | B67: 7. Capteurs et actionneurs | C67: Module lecteur microSD SPI 3,3 V direct | D67: Option | E67: =SUMIFS(msp1!$F:$F,msp1!$A:$A,$A67,msp1!$G:$G,$D67) -> 0 | F67: =SUMIFS(n3pp!$F:$F,n3pp!$A:$A,$A67,n3pp!$G:$G,$D67) -> 0 | G67: =SUMIFS('ffp5cs 230V'!$F:$F,'ffp5cs 230V'!$A:$A,$A67,'ffp5cs 230V'!$G:$G,$D67) -> 1 | H67: =SUMIFS('ffp5cs 12V'!$F:$F,'ffp5cs 12V'!$A:$A,$A67,'ffp5cs 12V'!$G:$G,$D67) -> 0 | I67: =SUM(E67:H67) -> 1 | J67: 0 | K67: =IF(I67=0,0,I67+J67) -> 1 | L67: =INDEX(Prix!$E$5:$E$79,MATCH($A67,Prix!$A$5:$A$79,0)) -> 1 | M67: =IF(K67=0,0,ROUNDUP(K67/L67,0)) -> 1 | N67: =IF(INDEX(Prix!$D$5:$D$79,MATCH($A67,Prix!$A$5:$A$79,0))="","",INDEX(Prix!$D$5:$D$79,MATCH($A67,Prix!$A$5:$A$79,0))) -> 18 | O67: =IF(N67="","",M67*N67) -> 18 | P67: =INDEX(Prix!$C$5:$C$79,MATCH($A67,Prix!$A$5:$A$79,0)) -> Moussasoft | Q67: =INDEX(Prix!$H$5:$H$79,MATCH($A67,Prix!$A$5:$A$79,0)) -> Maroc | R67: ATTENTION : le module « pour Arduino » courant a un régulateur + tampon (type Catalex) : NE CONVIENT PAS. Chercher un module 3,3 V direct. | S67: lien
A68: 1N4007_EXT | B68: 7. Capteurs et actionneurs | C68: Diode 1N4007 aux bornes d'une pompe DC (roue libre) | D68: À acheter | E68: =SUMIFS(msp1!$F:$F,msp1!$A:$A,$A68,msp1!$G:$G,$D68) -> 0 | F68: =SUMIFS(n3pp!$F:$F,n3pp!$A:$A,$A68,n3pp!$G:$G,$D68) -> 1 | G68: =SUMIFS('ffp5cs 230V'!$F:$F,'ffp5cs 230V'!$A:$A,$A68,'ffp5cs 230V'!$G:$G,$D68) -> 0 | H68: =SUMIFS('ffp5cs 12V'!$F:$F,'ffp5cs 12V'!$A:$A,$A68,'ffp5cs 12V'!$G:$G,$D68) -> 2 | I68: =SUM(E68:H68) -> 3 | J68: 0 | K68: =IF(I68=0,0,I68+J68) -> 3 | L68: =INDEX(Prix!$E$5:$E$79,MATCH($A68,Prix!$A$5:$A$79,0)) -> 1 | M68: =IF(K68=0,0,ROUNDUP(K68/L68,0)) -> 3 | N68: =IF(INDEX(Prix!$D$5:$D$79,MATCH($A68,Prix!$A$5:$A$79,0))="","",INDEX(Prix!$D$5:$D$79,MATCH($A68,Prix!$A$5:$A$79,0))) -> 0.9 | O68: =IF(N68="","",M68*N68) -> 2.7 | P68: =INDEX(Prix!$C$5:$C$79,MATCH($A68,Prix!$A$5:$A$79,0)) -> Shop4Makers | Q68: =INDEX(Prix!$H$5:$H$79,MATCH($A68,Prix!$A$5:$A$79,0)) -> Maroc | S68: lien
A69: TP4056 | B69: 8. Alimentation hors carte | C69: Module chargeur TP4056 avec protection (DW01) | D69: Déjà possédé | E69: =SUMIFS(msp1!$F:$F,msp1!$A:$A,$A69,msp1!$G:$G,$D69) -> 1 | F69: =SUMIFS(n3pp!$F:$F,n3pp!$A:$A,$A69,n3pp!$G:$G,$D69) -> 0 | G69: =SUMIFS('ffp5cs 230V'!$F:$F,'ffp5cs 230V'!$A:$A,$A69,'ffp5cs 230V'!$G:$G,$D69) -> 0 | H69: =SUMIFS('ffp5cs 12V'!$F:$F,'ffp5cs 12V'!$A:$A,$A69,'ffp5cs 12V'!$G:$G,$D69) -> 0 | I69: =SUM(E69:H69) -> 1 | J69: 0 | K69: =IF(I69=0,0,I69+J69) -> 1 | L69: =INDEX(Prix!$E$5:$E$79,MATCH($A69,Prix!$A$5:$A$79,0)) -> 1 | M69: =IF(K69=0,0,ROUNDUP(K69/L69,0)) -> 1 | N69: =IF(INDEX(Prix!$D$5:$D$79,MATCH($A69,Prix!$A$5:$A$79,0))="","",INDEX(Prix!$D$5:$D$79,MATCH($A69,Prix!$A$5:$A$79,0))) -> 15 | O69: =IF(N69="","",M69*N69) -> 15 | P69: =INDEX(Prix!$C$5:$C$79,MATCH($A69,Prix!$A$5:$A$79,0)) -> Shop4Makers | Q69: =INDEX(Prix!$H$5:$H$79,MATCH($A69,Prix!$A$5:$A$79,0)) -> Maroc | R69: Version avec protection DW01A + FS8205A, entrée USB-C. | S69: lien
A70: BOOST | B70: 8. Alimentation hors carte | C70: Module boost MT3608 (réglé 5,1 V) | D70: À acheter | E70: =SUMIFS(msp1!$F:$F,msp1!$A:$A,$A70,msp1!$G:$G,$D70) -> 1 | F70: =SUMIFS(n3pp!$F:$F,n3pp!$A:$A,$A70,n3pp!$G:$G,$D70) -> 0 | G70: =SUMIFS('ffp5cs 230V'!$F:$F,'ffp5cs 230V'!$A:$A,$A70,'ffp5cs 230V'!$G:$G,$D70) -> 0 | H70: =SUMIFS('ffp5cs 12V'!$F:$F,'ffp5cs 12V'!$A:$A,$A70,'ffp5cs 12V'!$G:$G,$D70) -> 0 | I70: =SUM(E70:H70) -> 1 | J70: 0 | K70: =IF(I70=0,0,I70+J70) -> 1 | L70: =INDEX(Prix!$E$5:$E$79,MATCH($A70,Prix!$A$5:$A$79,0)) -> 1 | M70: =IF(K70=0,0,ROUNDUP(K70/L70,0)) -> 1 | N70: =IF(INDEX(Prix!$D$5:$D$79,MATCH($A70,Prix!$A$5:$A$79,0))="","",INDEX(Prix!$D$5:$D$79,MATCH($A70,Prix!$A$5:$A$79,0))) -> 16 | O70: =IF(N70="","",M70*N70) -> 16 | P70: =INDEX(Prix!$C$5:$C$79,MATCH($A70,Prix!$A$5:$A$79,0)) -> Shop4Makers | Q70: =INDEX(Prix!$H$5:$H$79,MATCH($A70,Prix!$A$5:$A$79,0)) -> Maroc | S70: lien
A71: CELL_18650 | B71: 8. Alimentation hors carte | C71: Pile Li-ion 18650 de marque (≥ 2 500 mAh) | D71: À acheter | E71: =SUMIFS(msp1!$F:$F,msp1!$A:$A,$A71,msp1!$G:$G,$D71) -> 1 | F71: =SUMIFS(n3pp!$F:$F,n3pp!$A:$A,$A71,n3pp!$G:$G,$D71) -> 0 | G71: =SUMIFS('ffp5cs 230V'!$F:$F,'ffp5cs 230V'!$A:$A,$A71,'ffp5cs 230V'!$G:$G,$D71) -> 0 | H71: =SUMIFS('ffp5cs 12V'!$F:$F,'ffp5cs 12V'!$A:$A,$A71,'ffp5cs 12V'!$G:$G,$D71) -> 0 | I71: =SUM(E71:H71) -> 1 | J71: 0 | K71: =IF(I71=0,0,I71+J71) -> 1 | L71: =INDEX(Prix!$E$5:$E$79,MATCH($A71,Prix!$A$5:$A$79,0)) -> 1 | M71: =IF(K71=0,0,ROUNDUP(K71/L71,0)) -> 1 | N71: =IF(INDEX(Prix!$D$5:$D$79,MATCH($A71,Prix!$A$5:$A$79,0))="","",INDEX(Prix!$D$5:$D$79,MATCH($A71,Prix!$A$5:$A$79,0))) -> 55 | O71: =IF(N71="","",M71*N71) -> 55 | P71: =INDEX(Prix!$C$5:$C$79,MATCH($A71,Prix!$A$5:$A$79,0)) -> Shop4Makers | Q71: =INDEX(Prix!$H$5:$H$79,MATCH($A71,Prix!$A$5:$A$79,0)) -> Maroc | R71: LG INR18650MH1 3 200 mAh, cellule nue flat-top. | S71: lien
A72: SUPPORT_18650 | B72: 8. Alimentation hors carte | C72: Support de pile 18650 (1 cellule) | D72: À acheter | E72: =SUMIFS(msp1!$F:$F,msp1!$A:$A,$A72,msp1!$G:$G,$D72) -> 1 | F72: =SUMIFS(n3pp!$F:$F,n3pp!$A:$A,$A72,n3pp!$G:$G,$D72) -> 0 | G72: =SUMIFS('ffp5cs 230V'!$F:$F,'ffp5cs 230V'!$A:$A,$A72,'ffp5cs 230V'!$G:$G,$D72) -> 0 | H72: =SUMIFS('ffp5cs 12V'!$F:$F,'ffp5cs 12V'!$A:$A,$A72,'ffp5cs 12V'!$G:$G,$D72) -> 0 | I72: =SUM(E72:H72) -> 1 | J72: 0 | K72: =IF(I72=0,0,I72+J72) -> 1 | L72: =INDEX(Prix!$E$5:$E$79,MATCH($A72,Prix!$A$5:$A$79,0)) -> 1 | M72: =IF(K72=0,0,ROUNDUP(K72/L72,0)) -> 1 | N72: =IF(INDEX(Prix!$D$5:$D$79,MATCH($A72,Prix!$A$5:$A$79,0))="","",INDEX(Prix!$D$5:$D$79,MATCH($A72,Prix!$A$5:$A$79,0))) -> 9 | O72: =IF(N72="","",M72*N72) -> 9 | P72: =INDEX(Prix!$C$5:$C$79,MATCH($A72,Prix!$A$5:$A$79,0)) -> MicroPlanet | Q72: =INDEX(Prix!$H$5:$H$79,MATCH($A72,Prix!$A$5:$A$79,0)) -> Maroc | S72: lien
A73: PANNEAU_6V | B73: 8. Alimentation hors carte | C73: Panneau solaire 6 V 5–6 W | D73: À acheter | E73: =SUMIFS(msp1!$F:$F,msp1!$A:$A,$A73,msp1!$G:$G,$D73) -> 1 | F73: =SUMIFS(n3pp!$F:$F,n3pp!$A:$A,$A73,n3pp!$G:$G,$D73) -> 0 | G73: =SUMIFS('ffp5cs 230V'!$F:$F,'ffp5cs 230V'!$A:$A,$A73,'ffp5cs 230V'!$G:$G,$D73) -> 0 | H73: =SUMIFS('ffp5cs 12V'!$F:$F,'ffp5cs 12V'!$A:$A,$A73,'ffp5cs 12V'!$G:$G,$D73) -> 0 | I73: =SUM(E73:H73) -> 1 | J73: 0 | K73: =IF(I73=0,0,I73+J73) -> 1 | L73: =INDEX(Prix!$E$5:$E$79,MATCH($A73,Prix!$A$5:$A$79,0)) -> 1 | M73: =IF(K73=0,0,ROUNDUP(K73/L73,0)) -> 1 | N73: =IF(INDEX(Prix!$D$5:$D$79,MATCH($A73,Prix!$A$5:$A$79,0))="","",INDEX(Prix!$D$5:$D$79,MATCH($A73,Prix!$A$5:$A$79,0))) -> 110 | O73: =IF(N73="","",M73*N73) -> 110 | P73: =INDEX(Prix!$C$5:$C$79,MATCH($A73,Prix!$A$5:$A$79,0)) -> Jumia.ma (Safe Buys) | Q73: =INDEX(Prix!$H$5:$H$79,MATCH($A73,Prix!$A$5:$A$79,0)) -> Maroc | R73: 6 V 3,8 W (pas de 5 W au Maroc) : ~7 Wh/j en hiver pour ~2,3 consommés, marge ×3. Sortie USB = se branche sur l'USB-C du TP4056. | S73: lien
A74: CHARGEUR_5V | B74: 8. Alimentation hors carte | C74: Chargeur 5 V 2 A (ou 3 A) de marque | D74: À acheter | E74: =SUMIFS(msp1!$F:$F,msp1!$A:$A,$A74,msp1!$G:$G,$D74) -> 0 | F74: =SUMIFS(n3pp!$F:$F,n3pp!$A:$A,$A74,n3pp!$G:$G,$D74) -> 1 | G74: =SUMIFS('ffp5cs 230V'!$F:$F,'ffp5cs 230V'!$A:$A,$A74,'ffp5cs 230V'!$G:$G,$D74) -> 0 | H74: =SUMIFS('ffp5cs 12V'!$F:$F,'ffp5cs 12V'!$A:$A,$A74,'ffp5cs 12V'!$G:$G,$D74) -> 0 | I74: =SUM(E74:H74) -> 1 | J74: 0 | K74: =IF(I74=0,0,I74+J74) -> 1 | L74: =INDEX(Prix!$E$5:$E$79,MATCH($A74,Prix!$A$5:$A$79,0)) -> 1 | M74: =IF(K74=0,0,ROUNDUP(K74/L74,0)) -> 1 | N74: =IF(INDEX(Prix!$D$5:$D$79,MATCH($A74,Prix!$A$5:$A$79,0))="","",INDEX(Prix!$D$5:$D$79,MATCH($A74,Prix!$A$5:$A$79,0))) -> 50 | O74: =IF(N74="","",M74*N74) -> 50 | P74: =INDEX(Prix!$C$5:$C$79,MATCH($A74,Prix!$A$5:$A$79,0)) -> Megma | Q74: =INDEX(Prix!$H$5:$H$79,MATCH($A74,Prix!$A$5:$A$79,0)) -> Maroc | R74: Seul 5 V 2 A en stock avec un vrai jack 5,5×2,1 (sans marque). Mieux : chargeur de téléphone de marque + cordon USB→jack. | S74: lien
A75: CABLE_USB_JACK | B75: 8. Alimentation hors carte | C75: Cordon USB-A → jack 5,5×2,1 court | D75: À acheter | E75: =SUMIFS(msp1!$F:$F,msp1!$A:$A,$A75,msp1!$G:$G,$D75) -> 0 | F75: =SUMIFS(n3pp!$F:$F,n3pp!$A:$A,$A75,n3pp!$G:$G,$D75) -> 1 | G75: =SUMIFS('ffp5cs 230V'!$F:$F,'ffp5cs 230V'!$A:$A,$A75,'ffp5cs 230V'!$G:$G,$D75) -> 0 | H75: =SUMIFS('ffp5cs 12V'!$F:$F,'ffp5cs 12V'!$A:$A,$A75,'ffp5cs 12V'!$G:$G,$D75) -> 0 | I75: =SUM(E75:H75) -> 1 | J75: 0 | K75: =IF(I75=0,0,I75+J75) -> 1 | L75: =INDEX(Prix!$E$5:$E$79,MATCH($A75,Prix!$A$5:$A$79,0)) -> 1 | M75: =IF(K75=0,0,ROUNDUP(K75/L75,0)) -> 1 | N75: =IF(INDEX(Prix!$D$5:$D$79,MATCH($A75,Prix!$A$5:$A$79,0))="","",INDEX(Prix!$D$5:$D$79,MATCH($A75,Prix!$A$5:$A$79,0))) -> 35 | O75: =IF(N75="","",M75*N75) -> 35 | P75: =INDEX(Prix!$C$5:$C$79,MATCH($A75,Prix!$A$5:$A$79,0)) -> Moussasoft | Q75: =INDEX(Prix!$H$5:$H$79,MATCH($A75,Prix!$A$5:$A$79,0)) -> Maroc | R75: En rupture lors du relevé (A2itronic idem, 35 DH). | S75: lien
A76: BUCK | B76: 8. Alimentation hors carte | C76: Module buck MP1584EN (12 V → 5,1 V) | D76: À acheter | E76: =SUMIFS(msp1!$F:$F,msp1!$A:$A,$A76,msp1!$G:$G,$D76) -> 0 | F76: =SUMIFS(n3pp!$F:$F,n3pp!$A:$A,$A76,n3pp!$G:$G,$D76) -> 0 | G76: =SUMIFS('ffp5cs 230V'!$F:$F,'ffp5cs 230V'!$A:$A,$A76,'ffp5cs 230V'!$G:$G,$D76) -> 0 | H76: =SUMIFS('ffp5cs 12V'!$F:$F,'ffp5cs 12V'!$A:$A,$A76,'ffp5cs 12V'!$G:$G,$D76) -> 1 | I76: =SUM(E76:H76) -> 1 | J76: 0 | K76: =IF(I76=0,0,I76+J76) -> 1 | L76: =INDEX(Prix!$E$5:$E$79,MATCH($A76,Prix!$A$5:$A$79,0)) -> 1 | M76: =IF(K76=0,0,ROUNDUP(K76/L76,0)) -> 1 | N76: =IF(INDEX(Prix!$D$5:$D$79,MATCH($A76,Prix!$A$5:$A$79,0))="","",INDEX(Prix!$D$5:$D$79,MATCH($A76,Prix!$A$5:$A$79,0))) -> 25 | O76: =IF(N76="","",M76*N76) -> 25 | P76: =INDEX(Prix!$C$5:$C$79,MATCH($A76,Prix!$A$5:$A$79,0)) -> Shop4Makers | Q76: =INDEX(Prix!$H$5:$H$79,MATCH($A76,Prix!$A$5:$A$79,0)) -> Maroc | R76: Entrée 28 V max : convient au bus AGM. | S76: lien
A77: FUSIBLE_LAME | B77: 8. Alimentation hors carte | C77: Porte-fusible lame en ligne + fusible 10 A | D77: À acheter | E77: =SUMIFS(msp1!$F:$F,msp1!$A:$A,$A77,msp1!$G:$G,$D77) -> 0 | F77: =SUMIFS(n3pp!$F:$F,n3pp!$A:$A,$A77,n3pp!$G:$G,$D77) -> 0 | G77: =SUMIFS('ffp5cs 230V'!$F:$F,'ffp5cs 230V'!$A:$A,$A77,'ffp5cs 230V'!$G:$G,$D77) -> 0 | H77: =SUMIFS('ffp5cs 12V'!$F:$F,'ffp5cs 12V'!$A:$A,$A77,'ffp5cs 12V'!$G:$G,$D77) -> 1 | I77: =SUM(E77:H77) -> 1 | J77: 1 | K77: =IF(I77=0,0,I77+J77) -> 2 | L77: =INDEX(Prix!$E$5:$E$79,MATCH($A77,Prix!$A$5:$A$79,0)) -> 1 | M77: =IF(K77=0,0,ROUNDUP(K77/L77,0)) -> 2 | N77: =IF(INDEX(Prix!$D$5:$D$79,MATCH($A77,Prix!$A$5:$A$79,0))="","",INDEX(Prix!$D$5:$D$79,MATCH($A77,Prix!$A$5:$A$79,0))) | O77: =IF(N77="","",M77*N77) | P77: =INDEX(Prix!$C$5:$C$79,MATCH($A77,Prix!$A$5:$A$79,0)) -> Accessoires auto | Q77: =INDEX(Prix!$H$5:$H$79,MATCH($A77,Prix!$A$5:$A$79,0)) -> Maroc | R77: Porte-fusible lame en ligne non trouvé en ligne : magasin d'accessoires auto (fusible ATO/mini 10 A).
A78: AGM_12V | B78: 8. Alimentation hors carte | C78: Batterie AGM 12 V (12 Ah) | D78: Déjà possédé | E78: =SUMIFS(msp1!$F:$F,msp1!$A:$A,$A78,msp1!$G:$G,$D78) -> 0 | F78: =SUMIFS(n3pp!$F:$F,n3pp!$A:$A,$A78,n3pp!$G:$G,$D78) -> 0 | G78: =SUMIFS('ffp5cs 230V'!$F:$F,'ffp5cs 230V'!$A:$A,$A78,'ffp5cs 230V'!$G:$G,$D78) -> 0 | H78: =SUMIFS('ffp5cs 12V'!$F:$F,'ffp5cs 12V'!$A:$A,$A78,'ffp5cs 12V'!$G:$G,$D78) -> 1 | I78: =SUM(E78:H78) -> 1 | J78: 0 | K78: =IF(I78=0,0,I78+J78) -> 1 | L78: =INDEX(Prix!$E$5:$E$79,MATCH($A78,Prix!$A$5:$A$79,0)) -> 1 | M78: =IF(K78=0,0,ROUNDUP(K78/L78,0)) -> 1 | N78: =IF(INDEX(Prix!$D$5:$D$79,MATCH($A78,Prix!$A$5:$A$79,0))="","",INDEX(Prix!$D$5:$D$79,MATCH($A78,Prix!$A$5:$A$79,0))) -> 490 | O78: =IF(N78="","",M78*N78) -> 490 | P78: =INDEX(Prix!$C$5:$C$79,MATCH($A78,Prix!$A$5:$A$79,0)) -> Jumia.ma | Q78: =INDEX(Prix!$H$5:$H$79,MATCH($A78,Prix!$A$5:$A$79,0)) -> Maroc | R78: Prix de référence (Sunlight 12 Ah AGM, en rupture ; 9 Ah générique 249 DH). | S78: lien
A79: PWM_SOLAIRE | B79: 8. Alimentation hors carte | C79: Régulateur de charge solaire PWM 12 V 10 A | D79: Déjà possédé | E79: =SUMIFS(msp1!$F:$F,msp1!$A:$A,$A79,msp1!$G:$G,$D79) -> 0 | F79: =SUMIFS(n3pp!$F:$F,n3pp!$A:$A,$A79,n3pp!$G:$G,$D79) -> 0 | G79: =SUMIFS('ffp5cs 230V'!$F:$F,'ffp5cs 230V'!$A:$A,$A79,'ffp5cs 230V'!$G:$G,$D79) -> 0 | H79: =SUMIFS('ffp5cs 12V'!$F:$F,'ffp5cs 12V'!$A:$A,$A79,'ffp5cs 12V'!$G:$G,$D79) -> 1 | I79: =SUM(E79:H79) -> 1 | J79: 0 | K79: =IF(I79=0,0,I79+J79) -> 1 | L79: =INDEX(Prix!$E$5:$E$79,MATCH($A79,Prix!$A$5:$A$79,0)) -> 1 | M79: =IF(K79=0,0,ROUNDUP(K79/L79,0)) -> 1 | N79: =IF(INDEX(Prix!$D$5:$D$79,MATCH($A79,Prix!$A$5:$A$79,0))="","",INDEX(Prix!$D$5:$D$79,MATCH($A79,Prix!$A$5:$A$79,0))) -> 299 | O79: =IF(N79="","",M79*N79) -> 299 | P79: =INDEX(Prix!$C$5:$C$79,MATCH($A79,Prix!$A$5:$A$79,0)) -> Jumia.ma (AM NEWS) | Q79: =INDEX(Prix!$H$5:$H$79,MATCH($A79,Prix!$A$5:$A$79,0)) -> Maroc | R79: Prix de référence. | S79: lien
A80: PANNEAU_12V | B80: 8. Alimentation hors carte | C80: Panneau solaire 12 V | D80: Déjà possédé | E80: =SUMIFS(msp1!$F:$F,msp1!$A:$A,$A80,msp1!$G:$G,$D80) -> 0 | F80: =SUMIFS(n3pp!$F:$F,n3pp!$A:$A,$A80,n3pp!$G:$G,$D80) -> 0 | G80: =SUMIFS('ffp5cs 230V'!$F:$F,'ffp5cs 230V'!$A:$A,$A80,'ffp5cs 230V'!$G:$G,$D80) -> 0 | H80: =SUMIFS('ffp5cs 12V'!$F:$F,'ffp5cs 12V'!$A:$A,$A80,'ffp5cs 12V'!$G:$G,$D80) -> 1 | I80: =SUM(E80:H80) -> 1 | J80: 0 | K80: =IF(I80=0,0,I80+J80) -> 1 | L80: =INDEX(Prix!$E$5:$E$79,MATCH($A80,Prix!$A$5:$A$79,0)) -> 1 | M80: =IF(K80=0,0,ROUNDUP(K80/L80,0)) -> 1 | N80: =IF(INDEX(Prix!$D$5:$D$79,MATCH($A80,Prix!$A$5:$A$79,0))="","",INDEX(Prix!$D$5:$D$79,MATCH($A80,Prix!$A$5:$A$79,0))) -> 179 | O80: =IF(N80="","",M80*N80) -> 179 | P80: =INDEX(Prix!$C$5:$C$79,MATCH($A80,Prix!$A$5:$A$79,0)) -> Jumia.ma (XARIUM TECH) | Q80: =INDEX(Prix!$H$5:$H$79,MATCH($A80,Prix!$A$5:$A$79,0)) -> Maroc | R80: Prix de référence (20 W). | S80: lien
A81: CORDON_SECTEUR | B81: 8. Alimentation hors carte | C81: Cordon secteur 2 fils avec fiche | D81: À acheter | E81: =SUMIFS(msp1!$F:$F,msp1!$A:$A,$A81,msp1!$G:$G,$D81) -> 0 | F81: =SUMIFS(n3pp!$F:$F,n3pp!$A:$A,$A81,n3pp!$G:$G,$D81) -> 0 | G81: =SUMIFS('ffp5cs 230V'!$F:$F,'ffp5cs 230V'!$A:$A,$A81,'ffp5cs 230V'!$G:$G,$D81) -> 1 | H81: =SUMIFS('ffp5cs 12V'!$F:$F,'ffp5cs 12V'!$A:$A,$A81,'ffp5cs 12V'!$G:$G,$D81) -> 0 | I81: =SUM(E81:H81) -> 1 | J81: 0 | K81: =IF(I81=0,0,I81+J81) -> 1 | L81: =INDEX(Prix!$E$5:$E$79,MATCH($A81,Prix!$A$5:$A$79,0)) -> 1 | M81: =IF(K81=0,0,ROUNDUP(K81/L81,0)) -> 1 | N81: =IF(INDEX(Prix!$D$5:$D$79,MATCH($A81,Prix!$A$5:$A$79,0))="","",INDEX(Prix!$D$5:$D$79,MATCH($A81,Prix!$A$5:$A$79,0))) -> 12 | O81: =IF(N81="","",M81*N81) -> 12 | P81: =INDEX(Prix!$C$5:$C$79,MATCH($A81,Prix!$A$5:$A$79,0)) -> La-Librairie.ma | Q81: =INDEX(Prix!$H$5:$H$79,MATCH($A81,Prix!$A$5:$A$79,0)) -> Maroc | R81: Probablement à embase C7 : couper l'embase, dénuder, embouts. Ou cordon d'électricien. | S81: lien
A82: VIS_M3 | B82: 9. Mécanique et câblage | C82: Vis M3 nylon + écrou (H1-H7 ; nylon OBLIGATOIRE en H1/H5) | D82: À acheter | E82: =SUMIFS(msp1!$F:$F,msp1!$A:$A,$A82,msp1!$G:$G,$D82) -> 7 | F82: =SUMIFS(n3pp!$F:$F,n3pp!$A:$A,$A82,n3pp!$G:$G,$D82) -> 7 | G82: =SUMIFS('ffp5cs 230V'!$F:$F,'ffp5cs 230V'!$A:$A,$A82,'ffp5cs 230V'!$G:$G,$D82) -> 7 | H82: =SUMIFS('ffp5cs 12V'!$F:$F,'ffp5cs 12V'!$A:$A,$A82,'ffp5cs 12V'!$G:$G,$D82) -> 7 | I82: =SUM(E82:H82) -> 28 | J82: 4 | K82: =IF(I82=0,0,I82+J82) -> 32 | L82: =INDEX(Prix!$E$5:$E$79,MATCH($A82,Prix!$A$5:$A$79,0)) -> 60 | M82: =IF(K82=0,0,ROUNDUP(K82/L82,0)) -> 1 | N82: =IF(INDEX(Prix!$D$5:$D$79,MATCH($A82,Prix!$A$5:$A$79,0))="","",INDEX(Prix!$D$5:$D$79,MATCH($A82,Prix!$A$5:$A$79,0))) -> 120 | O82: =IF(N82="","",M82*N82) -> 120 | P82: =INDEX(Prix!$C$5:$C$79,MATCH($A82,Prix!$A$5:$A$79,0)) -> Dsindustrie | Q82: =INDEX(Prix!$H$5:$H$79,MATCH($A82,Prix!$A$5:$A$79,0)) -> Maroc | R82: Kit nylon : 60 vis, 60 écrous, 80 entretoises 6–12 mm ; un kit suffit pour les 4 cartes. | S82: lien
A83: ENTRETOISE_M3 | B83: 9. Mécanique et câblage | C83: Entretoise M3 nylon ~10 mm | D83: À acheter | E83: =SUMIFS(msp1!$F:$F,msp1!$A:$A,$A83,msp1!$G:$G,$D83) -> 7 | F83: =SUMIFS(n3pp!$F:$F,n3pp!$A:$A,$A83,n3pp!$G:$G,$D83) -> 7 | G83: =SUMIFS('ffp5cs 230V'!$F:$F,'ffp5cs 230V'!$A:$A,$A83,'ffp5cs 230V'!$G:$G,$D83) -> 7 | H83: =SUMIFS('ffp5cs 12V'!$F:$F,'ffp5cs 12V'!$A:$A,$A83,'ffp5cs 12V'!$G:$G,$D83) -> 7 | I83: =SUM(E83:H83) -> 28 | J83: 4 | K83: =IF(I83=0,0,I83+J83) -> 32 | L83: =INDEX(Prix!$E$5:$E$79,MATCH($A83,Prix!$A$5:$A$79,0)) -> 1 | M83: =IF(K83=0,0,ROUNDUP(K83/L83,0)) -> 32 | N83: =IF(INDEX(Prix!$D$5:$D$79,MATCH($A83,Prix!$A$5:$A$79,0))="","",INDEX(Prix!$D$5:$D$79,MATCH($A83,Prix!$A$5:$A$79,0))) -> 0 | O83: =IF(N83="","",M83*N83) -> 0 | P83: =INDEX(Prix!$C$5:$C$79,MATCH($A83,Prix!$A$5:$A$79,0)) -> Dsindustrie | Q83: =INDEX(Prix!$H$5:$H$79,MATCH($A83,Prix!$A$5:$A$79,0)) -> Maroc | R83: Incluses dans le kit nylon M3.
A84: BOITIER | B84: 9. Mécanique et câblage | C84: Boîtier étanche IP65 (~200×150 mm ou plus) | D84: À acheter | E84: =SUMIFS(msp1!$F:$F,msp1!$A:$A,$A84,msp1!$G:$G,$D84) -> 1 | F84: =SUMIFS(n3pp!$F:$F,n3pp!$A:$A,$A84,n3pp!$G:$G,$D84) -> 1 | G84: =SUMIFS('ffp5cs 230V'!$F:$F,'ffp5cs 230V'!$A:$A,$A84,'ffp5cs 230V'!$G:$G,$D84) -> 1 | H84: =SUMIFS('ffp5cs 12V'!$F:$F,'ffp5cs 12V'!$A:$A,$A84,'ffp5cs 12V'!$G:$G,$D84) -> 1 | I84: =SUM(E84:H84) -> 4 | J84: 0 | K84: =IF(I84=0,0,I84+J84) -> 4 | L84: =INDEX(Prix!$E$5:$E$79,MATCH($A84,Prix!$A$5:$A$79,0)) -> 1 | M84: =IF(K84=0,0,ROUNDUP(K84/L84,0)) -> 4 | N84: =IF(INDEX(Prix!$D$5:$D$79,MATCH($A84,Prix!$A$5:$A$79,0))="","",INDEX(Prix!$D$5:$D$79,MATCH($A84,Prix!$A$5:$A$79,0))) -> 352 | O84: =IF(N84="","",M84*N84) -> 1408 | P84: =INDEX(Prix!$C$5:$C$79,MATCH($A84,Prix!$A$5:$A$79,0)) -> EnergyMarket | Q84: =INDEX(Prix!$H$5:$H$79,MATCH($A84,Prix!$A$5:$A$79,0)) -> Maroc | R84: La carte fait 278 × 135 mm : coffret ≥ 300 × 200 mm. Prix affiché, taille à confirmer avec le vendeur. | S84: lien
A85: PRESSE_ETOUPE | B85: 9. Mécanique et câblage | C85: Presse-étoupe PG7 / PG9 | D85: À acheter | E85: =SUMIFS(msp1!$F:$F,msp1!$A:$A,$A85,msp1!$G:$G,$D85) -> 6 | F85: =SUMIFS(n3pp!$F:$F,n3pp!$A:$A,$A85,n3pp!$G:$G,$D85) -> 6 | G85: =SUMIFS('ffp5cs 230V'!$F:$F,'ffp5cs 230V'!$A:$A,$A85,'ffp5cs 230V'!$G:$G,$D85) -> 8 | H85: =SUMIFS('ffp5cs 12V'!$F:$F,'ffp5cs 12V'!$A:$A,$A85,'ffp5cs 12V'!$G:$G,$D85) -> 8 | I85: =SUM(E85:H85) -> 28 | J85: 2 | K85: =IF(I85=0,0,I85+J85) -> 30 | L85: =INDEX(Prix!$E$5:$E$79,MATCH($A85,Prix!$A$5:$A$79,0)) -> 1 | M85: =IF(K85=0,0,ROUNDUP(K85/L85,0)) -> 30 | N85: =IF(INDEX(Prix!$D$5:$D$79,MATCH($A85,Prix!$A$5:$A$79,0))="","",INDEX(Prix!$D$5:$D$79,MATCH($A85,Prix!$A$5:$A$79,0))) | O85: =IF(N85="","",M85*N85) | P85: =INDEX(Prix!$C$5:$C$79,MATCH($A85,Prix!$A$5:$A$79,0)) -> Quincaillerie | Q85: =INDEX(Prix!$H$5:$H$79,MATCH($A85,Prix!$A$5:$A$79,0)) -> Maroc | R85: Non trouvé en ligne au Maroc : électricien / quincaillerie.
A86: FIL_05 | B86: 9. Mécanique et câblage | C86: Fil souple 0,5 mm² (mètre) | D86: À acheter | E86: =SUMIFS(msp1!$F:$F,msp1!$A:$A,$A86,msp1!$G:$G,$D86) -> 5 | F86: =SUMIFS(n3pp!$F:$F,n3pp!$A:$A,$A86,n3pp!$G:$G,$D86) -> 5 | G86: =SUMIFS('ffp5cs 230V'!$F:$F,'ffp5cs 230V'!$A:$A,$A86,'ffp5cs 230V'!$G:$G,$D86) -> 5 | H86: =SUMIFS('ffp5cs 12V'!$F:$F,'ffp5cs 12V'!$A:$A,$A86,'ffp5cs 12V'!$G:$G,$D86) -> 5 | I86: =SUM(E86:H86) -> 20 | J86: 0 | K86: =IF(I86=0,0,I86+J86) -> 20 | L86: =INDEX(Prix!$E$5:$E$79,MATCH($A86,Prix!$A$5:$A$79,0)) -> 1 | M86: =IF(K86=0,0,ROUNDUP(K86/L86,0)) -> 20 | N86: =IF(INDEX(Prix!$D$5:$D$79,MATCH($A86,Prix!$A$5:$A$79,0))="","",INDEX(Prix!$D$5:$D$79,MATCH($A86,Prix!$A$5:$A$79,0))) -> 3.5 | O86: =IF(N86="","",M86*N86) -> 70 | P86: =INDEX(Prix!$C$5:$C$79,MATCH($A86,Prix!$A$5:$A$79,0)) -> ElectroDelivery | Q86: =INDEX(Prix!$H$5:$H$79,MATCH($A86,Prix!$A$5:$A$79,0)) -> Maroc | R86: Câble souple 0,75 mm² (pas de 0,5 mm² en ligne). | S86: lien
A87: FIL_15 | B87: 9. Mécanique et câblage | C87: Fil souple 1,5 mm² (mètre) | D87: À acheter | E87: =SUMIFS(msp1!$F:$F,msp1!$A:$A,$A87,msp1!$G:$G,$D87) -> 0 | F87: =SUMIFS(n3pp!$F:$F,n3pp!$A:$A,$A87,n3pp!$G:$G,$D87) -> 0 | G87: =SUMIFS('ffp5cs 230V'!$F:$F,'ffp5cs 230V'!$A:$A,$A87,'ffp5cs 230V'!$G:$G,$D87) -> 5 | H87: =SUMIFS('ffp5cs 12V'!$F:$F,'ffp5cs 12V'!$A:$A,$A87,'ffp5cs 12V'!$G:$G,$D87) -> 5 | I87: =SUM(E87:H87) -> 10 | J87: 0 | K87: =IF(I87=0,0,I87+J87) -> 10 | L87: =INDEX(Prix!$E$5:$E$79,MATCH($A87,Prix!$A$5:$A$79,0)) -> 1 | M87: =IF(K87=0,0,ROUNDUP(K87/L87,0)) -> 10 | N87: =IF(INDEX(Prix!$D$5:$D$79,MATCH($A87,Prix!$A$5:$A$79,0))="","",INDEX(Prix!$D$5:$D$79,MATCH($A87,Prix!$A$5:$A$79,0))) -> 8 | O87: =IF(N87="","",M87*N87) -> 80 | P87: =INDEX(Prix!$C$5:$C$79,MATCH($A87,Prix!$A$5:$A$79,0)) -> ElectroDelivery | Q87: =INDEX(Prix!$H$5:$H$79,MATCH($A87,Prix!$A$5:$A$79,0)) -> Maroc | R87: Câble souple 2 × 1,5 mm² (aller + retour d'une charge). | S87: lien
A89: Outillage et consommables partagés (une fois pour les 4 unités)
A90: ID | B90: Catégorie | C90: Article | D90: Statut | E90: msp1 | F90: n3pp | G90: ffp5cs 230V | H90: ffp5cs 12V | I90: Total 4 unités | J90: Rechange | K90: Qté à acheter | L90: Taille du lot | M90: Nb de lots | N90: Prix du lot (DH) | O90: Coût (DH) | P90: Fournisseur | Q90: Source | R90: Remarque achat | S90: Lien
A91: KIT_EMBOUTS | B91: Outillage partagé | C91: Pince à sertir + kit d'embouts de câblage (ferrules) | D91: À acheter | I91: 1 | J91: 0 | K91: =I91+J91 -> 1 | L91: =INDEX(Prix!$E$5:$E$79,MATCH($A91,Prix!$A$5:$A$79,0)) -> 1 | M91: =ROUNDUP(K91/L91,0) -> 1 | N91: =IF(INDEX(Prix!$D$5:$D$79,MATCH($A91,Prix!$A$5:$A$79,0))="","",INDEX(Prix!$D$5:$D$79,MATCH($A91,Prix!$A$5:$A$79,0))) -> 250 | O91: =IF(N91="","",M91*N91) -> 250 | P91: =INDEX(Prix!$C$5:$C$79,MATCH($A91,Prix!$A$5:$A$79,0)) -> Moussasoft | Q91: =INDEX(Prix!$H$5:$H$79,MATCH($A91,Prix!$A$5:$A$79,0)) -> Maroc | R91: Tout fil souple vissé dans un bornier reçoit un embout serti. Pince à cliquet + 1 200 embouts 0,25–10 mm². | S91: lien
A92: VERNIS | B92: Outillage partagé | C92: Vernis de tropicalisation (Plastik 70 / Relife 70) | D92: À acheter | I92: 1 | J92: 0 | K92: =I92+J92 -> 1 | L92: =INDEX(Prix!$E$5:$E$79,MATCH($A92,Prix!$A$5:$A$79,0)) -> 1 | M92: =ROUNDUP(K92/L92,0) -> 1 | N92: =IF(INDEX(Prix!$D$5:$D$79,MATCH($A92,Prix!$A$5:$A$79,0))="","",INDEX(Prix!$D$5:$D$79,MATCH($A92,Prix!$A$5:$A$79,0))) -> 400 | O92: =IF(N92="","",M92*N92) -> 400 | P92: =INDEX(Prix!$C$5:$C$79,MATCH($A92,Prix!$A$5:$A$79,0)) -> A2itronic | Q92: =INDEX(Prix!$H$5:$H$79,MATCH($A92,Prix!$A$5:$A$79,0)) -> Maroc | R92: Après montage et test ; masquer borniers, supports et cavaliers. Tropicoat, en rupture lors du relevé. | S92: lien
A93: DUPONT | B93: Outillage partagé | C93: Fils Dupont mâle-femelle 20 cm | D93: À acheter | I93: 4 | J93: 0 | K93: =I93+J93 -> 4 | L93: =INDEX(Prix!$E$5:$E$79,MATCH($A93,Prix!$A$5:$A$79,0)) -> 1 | M93: =ROUNDUP(K93/L93,0) -> 4 | N93: =IF(INDEX(Prix!$D$5:$D$79,MATCH($A93,Prix!$A$5:$A$79,0))="","",INDEX(Prix!$D$5:$D$79,MATCH($A93,Prix!$A$5:$A$79,0))) -> 6 | O93: =IF(N93="","",M93*N93) -> 24 | P93: =INDEX(Prix!$C$5:$C$79,MATCH($A93,Prix!$A$5:$A$79,0)) -> MicroPlanet | Q93: =INDEX(Prix!$H$5:$H$79,MATCH($A93,Prix!$A$5:$A$79,0)) -> Maroc | R93: Raccordement des modules I2C dont le brochage diffère des supports, essais sur table. Lot de 10 fils 20 cm. | S93: lien

Sheet Prix
A1: Catalogue des prix — fournisseurs marocains
A2: Relevé le 18/10/2026 sur les pages produits, prix en DH tels qu'affichés (TTC). Cellules bleues = à mettre à jour ; toutes les autres feuilles se recalculent depuis celle-ci.
A4: ID | B4: Article | C4: Fournisseur | D4: Prix du lot (DH) | E4: Taille du lot | F4: Unité de vente | G4: Prix unitaire (DH) | H4: Source | I4: Lien | J4: Remarque achat | K4: Relevé le
A5: PCB | B5: Circuit imprimé n3-universal rev 0.2.2 (JLCPCB, 2 oz) | C5: JLCPCB | E5: 1 | F5: carte | G5: =IF(D5="","",D5/E5) | H5: Import | I5: lien | J5: Commande unique de 10 cartes : ≈ 55–85 $ les 5 + port (COMMANDE.md) ; prix réel au devis JLCPCB. | K5: 18/10/2026
A6: ESP32_DEVKIT | B6: ESP32 DevKit V1 30 broches (WROOM-32) | C6: Shop4Makers | D6: 113 | E6: 1 | F6: pièce | G6: =IF(D6="","",D6/E6) -> 113 | H6: Maroc | I6: lien | J6: ESP32 WROOM CP2102 30 broches. Ne pas importer (ANRT). Repli A2itronic 120 DH. | K6: 18/10/2026
A7: R_220 | B7: Résistance 220 Ω 1/4 W | C7: MicroPlanet | D7: 1.5 | E7: 5 | F7: lot de 5 | G7: =IF(D7="","",D7/E7) -> 0.3 | H7: Maroc | I7: lien | J7: 1/4 W 1 %, vendues par 5. | K7: 18/10/2026
A8: R_1k | B8: Résistance 1 kΩ 1/4 W | C8: MicroPlanet | D8: 1.5 | E8: 5 | F8: lot de 5 | G8: =IF(D8="","",D8/E8) -> 0.3 | H8: Maroc | I8: lien | J8: 1/4 W 1 %, vendues par 5. | K8: 18/10/2026
A9: R_2k | B9: Résistance 2 kΩ 1/4 W (2,2 kΩ convient) | C9: MicroPlanet | D9: 1.5 | E9: 5 | F9: lot de 5 | G9: =IF(D9="","",D9/E9) -> 0.3 | H9: Maroc | I9: lien | J9: 1/4 W 1 %, vendues par 5. | K9: 18/10/2026
A10: R_4.7k | B10: Résistance 4,7 kΩ 1/4 W | C10: MicroPlanet | D10: 1.5 | E10: 5 | F10: lot de 5 | G10: =IF(D10="","",D10/E10) -> 0.3 | H10: Maroc | I10: lien | J10: 1/4 W 1 %, vendues par 5. | K10: 18/10/2026
A11: R_10k | B11: Résistance 10 kΩ 1/4 W | C11: MicroPlanet | D11: 1.5 | E11: 5 | F11: lot de 5 | G11: =IF(D11="","",D11/E11) -> 0.3 | H11: Maroc | I11: lien | J11: 1/4 W 1 %, vendues par 5. | K11: 18/10/2026
A12: R_18k | B12: Résistance 18 kΩ 1/4 W | C12: MicroPlanet | D12: 1.5 | E12: 5 | F12: lot de 5 | G12: =IF(D12="","",D12/E12) -> 0.3 | H12: Maroc | I12: lien | J12: 1/4 W 1 %, vendues par 5. | K12: 18/10/2026
A13: R_100k | B13: Résistance 100 kΩ 1/4 W | C13: MicroPlanet | D13: 1.5 | E13: 5 | F13: lot de 5 | G13: =IF(D13="","",D13/E13) -> 0.3 | H13: Maroc | I13: lien | J13: 1/4 W 1 %, vendues par 5. | K13: 18/10/2026
A14: C_100n | B14: Condensateur céramique 100 nF (pas 5 mm) | C14: A2itronic | D14: 0.5 | E14: 1 | F14: pièce | G14: =IF(D14="","",D14/E14) -> 0.5 | H14: Maroc | I14: lien | J14: Céramique 50 V. | K14: 18/10/2026
A15: C_10u25 | B15: Condensateur électrolytique 10 µF 25 V | C15: A2itronic | D15: 1 | E15: 1 | F15: pièce | G15: =IF(D15="","",D15/E15) -> 1 | H15: Maroc | I15: lien | J15: Proposé en 50 V (mieux que 25 V). | K15: 18/10/2026
A16: C_100u16 | B16: Condensateur électrolytique 100 µF 16 V | C16: A2itronic | D16: 1 | E16: 1 | F16: pièce | G16: =IF(D16="","",D16/E16) -> 1 | H16: Maroc | I16: lien | J16: 5×7 mm. | K16: 18/10/2026
A17: C_470u16 | B17: Condensateur électrolytique 470 µF 16 V (25 V convient) | C17: A2itronic | D17: 2 | E17: 1 | F17: pièce | G17: =IF(D17="","",D17/E17) -> 2 | H17: Maroc | I17: lien | J17: Proposé en 25 V, 8×12 mm (empreinte 8 mm) : convient. | K17: 18/10/2026
... A19: C_1000u16 | B19: Condensateur électrolytique 1000 µF 16 V (diam. 10 mm) | C19: A2itronic | D19: 3 | E19: 1 | F19: pièce | G19: =IF(D19="","",D19/E19) -> 3 | H19: Maroc | I19: lien | J19: Page ambiguë 16/25 V : les deux conviennent, mais diamètre ≤ 10 mm et pas 5 mm. | K19: 18/10/2026
A20: 1N4007 | B20: Diode 1N4007 (roue libre des bobines de relais) | C20: Shop4Makers | D20: 0.9 | E20: 1 | F20: pièce | G20: =IF(D20="","",D20/E20) -> 0.9 | H20: Maroc | I20: lien | K20: 18/10/2026
A21: BAT85 | B21: Diode Schottky BAT85 / BAT43 / BAT42 (DO-35) | C21: Moussasoft | D21: 2 | E21: 1 | F21: pièce | G21: =IF(D21="","",D21/E21) -> 2 | H21: Maroc | I21: lien | J21: Boîtier DO-34, se pose sur les trous DO-35. BAT43/42/54 introuvables au Maroc. | K21: 18/10/2026
A22: TVS_6V8 | B22: Diode TVS 1.5KE6.8A (ou P6KE6.8A) | C22: LCSC | E22: 1 | F22: pièce | G22: =IF(D22="","",D22/E22) | H22: Import LCSC | I22: lien | J22: Introuvable au Maroc : LCSC C412500 (repli P6KE6.8A C409413), colis combiné JLCPCB. | K22: 18/10/2026
A23: TVS_18 | B23: Diode TVS 1.5KE18A (ou P6KE18A) — PAS 15 V | C23: LCSC | E23: 1 | F23: pièce | G23: =IF(D23="","",D23/E23) | H23: Import LCSC | I23: lien | J23: Introuvable au Maroc : LCSC C1666858. Ne pas remplacer par une 15 V. | K23: 18/10/2026
A24: Z15 | B24: Diode Zener 15 V 1 W 1N4744A | C24: MicroPlanet | D24: 2 | E24: 1 | F24: pièce | G24: =IF(D24="","",D24/E24) -> 2 | H24: Maroc | I24: lien | J24: Zener 1 W, variante 15 V (équivalent 1N4744A). | K24: 18/10/2026
A25: BC337 | B25: Transistor NPN BC337-40 (TO-92) | C25: A2itronic | D25: 1 | E25: 1 | F25: pièce | G25: =IF(D25="","",D25/E25) -> 1 | H25: Maroc | I25: lien | J25: Annoncé BC337B/-40 : tout BC337 convient (brochage C-B-E). | K25: 18/10/2026
A26: IRF4905 | B26: MOSFET P IRF4905 (TO-220) | C26: A2itronic | D26: 10 | E26: 1 | F26: pièce | G26: =IF(D26="","",D26/E26) -> 10 | H26: Maroc | I26: lien | J26: Stock non vérifié : appeler avant. Repli LCSC C2564. | K26: 18/10/2026
A27: LD1117 | B27: Régulateur LD1117V33 TO-220 (1=GND 2=OUT 3=IN) | C27: Megma | D27: 7.5 | E27: 1 | F27: pièce | G27: =IF(D27="","",D27/E27) -> 7.5 | H27: Maroc | I27: lien | J27: LM1117T-3.3 TO-220, même brochage que le LD1117V33. Pas de version SOT-223 (CMS). | K27: 18/10/2026
A28: LED_R | B28: LED 5 mm rouge | C28: Moussasoft | D28: 1 | E28: 1 | F28: pièce | G28: =IF(D28="","",D28/E28) -> 1 | H28: Maroc | I28: lien | K28: 18/10/2026
A29: LED_V | B29: LED 5 mm verte | C29: Shop4Makers | D29: 0.9 | E29: 1 | F29: pièce | G29: =IF(D29="","",D29/E29) -> 0.9 | H29: Maroc | I29: lien | K29: 18/10/2026
A30: SRD05 | B30: Relais Songle SRD-05VDC-SL-C (composant seul, pas le module) | C30: Moussasoft | D30: 18 | E30: 1 | F30: pièce | G30: =IF(D30="","",D30/E30) -> 18 | H30: Maroc | I30: lien | J30: Composant seul 5 broches, pas un module relais. 324 en stock. | K30: 18/10/2026
A31: VARISTANCE | B31: Varistance 14D471K (ou 10D471K), pas 7,5 mm | C31: MicroPlanet | D31: 4 | E31: 1 | F31: pièce | G31: =IF(D31="","",D31/E31) -> 4 | H31: Maroc | I31: lien | J31: Variante 470 V (471). | K31: 18/10/2026
A32: PORTEFUS_5x20 | B32: Porte-fusible 5×20 pour circuit imprimé, à capot (pas 22–22,6 mm) | C32: Moussasoft | D32: 4 | E32: 1 | F32: pièce | G32: =IF(D32="","",D32/E32) -> 4 | H32: Maroc | I32: lien | J32: Mesurer l'entraxe des pattes AVANT achat : 22,0–22,6 mm. Sinon LCSC C3131. | K32: 18/10/2026
A33: FUS_T1A | B33: Fusible verre 5×20 temporisé T1A | C33: Megma | D33: 0.5 | E33: 1 | F33: pièce | G33: =IF(D33="","",D33/E33) -> 0.5 | H33: Maroc | I33: lien | J33: Le type T (temporisé) n'est pas indiqué : demander « T1A » ; un fusible rapide F peut sauter au branchement. | K33: 18/10/2026
A34: HLK20M05 | B34: Module Hi-Link HLK-20M05 (230 V → 5 V 3,6 A) | C34: Shop4Makers | D34: 90 | E34: 1 | F34: pièce | G34: =IF(D34="","",D34/E34) -> 90 | H34: Maroc | I34: lien | J34: Authenticité non garantie : mesurer les entraxes des broches (COMMANDE.md §0.3) avant de souder. | K34: 18/10/2026
A35: BORNIER_2P | B35: Bornier à vis 2 pôles pas 5,08 (KF301-2P) | C35: MicroPlanet | D35: 2 | E35: 1 | F35: pièce | G35: =IF(D35="","",D35/E35) -> 2 | H35: Maroc | I35: lien | J35: KF301 annoncé au pas de 5,0 mm : se monte sur les trous 5,08 (écart 0,08 mm). | K35: 18/10/2026
A36: BORNIER_3P | B36: Bornier à vis 3 pôles pas 5,08 (KF301-3P) | C36: MicroPlanet | D36: 3 | E36: 1 | F36: pièce | G36: =IF(D36="","",D36/E36) -> 3 | H36: Maroc | I36: lien | J36: KF301 pas 5,0 mm : se monte sur les trous 5,08. | K36: 18/10/2026
A37: BORNIER_4P | B37: Bornier à vis 4 pôles pas 5,08 (ou 2+2 emboîtés) | C37: MicroPlanet | D37: 5 | E37: 1 | F37: pièce | G37: =IF(D37="","",D37/E37) -> 5 | H37: Maroc | I37: lien | J37: KF128-4P. Sur 4 pôles, l'écart 5,0/5,08 cumule 0,24 mm : présenter avant de souder, ou 2 × KF301-2P emboîtés. | K37: 18/10/2026
A38: BARRETTE_F | B38: Barrette femelle sécable 1×40 pas 2,54 | C38: Moussasoft | D38: 5 | E38: 1 | F38: barrette 1×40 | G38: =IF(D38="","",D38/E38) -> 5 | H38: Maroc | I38: lien | J38: Une broche perdue à chaque coupe (compté). | K38: 18/10/2026
A39: BARRETTE_M | B39: Barrette mâle sécable 1×40 pas 2,54 | C39: Moussasoft | D39: 4 | E39: 1 | F39: barrette 1×40 | G39: =IF(D39="","",D39/E39) -> 4 | H39: Maroc | I39: lien | K39: 18/10/2026
A40: CAVALIER | B40: Cavalier (jumper) 2,54 mm | C40: Shop4Makers | D40: 5 | E40: 10 | F40: lot de 10 | G40: =IF(D40="","",D40/E40) -> 0.5 | H40: Maroc | I40: lien | J40: Prix du plus petit lot (bas de la fourchette affichée). | K40: 18/10/2026
A41: JACK_DC | B41: Jack DC femelle 5,5×2,1 pour circuit imprimé (DC-005) | C41: ShoppingMaroc | D41: 4 | E41: 1 | F41: pièce | G41: =IF(D41="","",D41/E41) -> 4 | H41: Maroc | I41: lien | J41: DC-005 traversant 3 broches. | K41: 18/10/2026
A42: FIL | B42: Pont de fil à la place de D5 (chute de patte de résistance) | C42: — | D42: 0 | E42: 1 | F42: — | G42: =IF(D42="","",D42/E42) -> 0 | H42: Maroc | J42: Chute de patte de résistance : gratuit. | K42: 18/10/2026
A43: TP_FIL | B43: Points de test TP1-TP4 : boucle de fil (chute de patte) | C43: — | D43: 0 | E43: 1 | F43: — | G43: =IF(D43="","",D43/E43) -> 0 | H43: Maroc | J43: Chute de patte : gratuit. | K43: 18/10/2026
A44: DHT11 | B44: Capteur température/humidité DHT11 | C44: Shop4Makers | D44: 16.2 | E44: 1 | F44: pièce | G44: =IF(D44="","",D44/E44) -> 16.2 | H44: Maroc | I44: lien | J44: Capteur nu 4 broches : 1=VCC 2=DATA 3=libre 4=GND (pull-up déjà sur la carte). DHT22 : 49,50 DH. | K44: 18/10/2026
A45: BME280 | B45: Module BME280 I2C (température, humidité, pression) | C45: Shop4Makers | D45: 85 | E45: 1 | F45: pièce | G45: =IF(D45="","",D45/E45) -> 85 | H45: Maroc | I45: lien | J45: Prendre la version 3,3 V (pas un BMP280, sans humidité). Raccorder par fils Dupont. | K45: 18/10/2026
A46: DS18B20 | B46: Sonde DS18B20 étanche (câble 1 m) | C46: A2itronic | D46: 50 | E46: 1 | F46: pièce | G46: =IF(D46="","",D46/E46) -> 50 | H46: Maroc | I46: lien | J46: Étanche ~1 m. Shop4Makers 36 DH mais en rupture. | K46: 18/10/2026
A47: LDR | B47: Photorésistance LDR GL5528 | C47: Moussasoft | D47: 2 | E47: 1 | F47: pièce | G47: =IF(D47="","",D47/E47) -> 2 | H47: Maroc | I47: lien | J47: GL5528 introuvable à l'unité : GM5539 (plus résistante dans le noir, sans effet en plein jour). Les 4 LDR du tracker du même lot. | K47: 18/10/2026
A48: PLUIE | B48: Module capteur de pluie FC-37 / YL-83 (sortie DO) | C48: Moussasoft | D48: 25 | E48: 1 | F48: pièce | G48: =IF(D48="","",D48/E48) -> 25 | H48: Maroc | I48: lien | J48: Plaque + module comparateur ; utiliser la sortie DO. | K48: 18/10/2026
A49: SOL_CAPA | B49: Capteur d'humidité du sol capacitif v1.2 (sortie AO) | C49: Shop4Makers | D49: 35 | E49: 1 | F49: pièce | G49: =IF(D49="","",D49/E49) -> 35 | H49: Maroc | I49: lien | J49: Étalonner sec / dans l'eau sous 3,3 V. Vernir le bord de la carte du capteur (électronique exposée). | K49: 18/10/2026
A50: HCSR04 | B50: Capteur ultrason HC-SR04 | C50: Moussasoft | D50: 25 | E50: 1 | F50: pièce | G50: =IF(D50="","",D50/E50) -> 25 | H50: Maroc | I50: lien | K50: 18/10/2026
A51: SG90 | B51: Servomoteur SG90 | C51: Moussasoft | D51: 30 | E51: 1 | F51: pièce | G51: =IF(D51="","",D51/E51) -> 30 | H51: Maroc | I51: lien | J51: Version 180° (pas 360° « rotation continue »). | K51: 18/10/2026
A52: OLED | B52: Écran OLED 0,96" SSD1306 I2C 128×64 | C52: Shop4Makers | D52: 70 | E52: 1 | F52: pièce | G52: =IF(D52="","",D52/E52) -> 70 | H52: Maroc | I52: lien | J52: Vérifier l'ordre des broches : J13 = GND-VCC-SCL-SDA. Si le module est VCC-GND-…, NE PAS l'enficher : fils Dupont. | K52: 18/10/2026
A53: DS3231 | B53: Module horloge RTC DS3231 (ZS-042) | C53: A2itronic | D53: 29 | E53: 1 | F53: pièce | G53: =IF(D53="","",D53/E53) -> 29 | H53: Maroc | I53: lien | J53: Brochage ZS-042 ≠ J14 : raccorder par fils Dupont (GND, VCC, SCL, SDA). | K53: 18/10/2026
A54: CR2032 | B54: Pile bouton CR2032 | C54: Shop4Makers | D54: 3 | E54: 1 | F54: pièce | G54: =IF(D54="","",D54/E54) -> 3 | H54: Maroc | I54: lien | K54: 18/10/2026
A55: INA226 | B55: Module INA226 (mesure tension/courant I2C) | C55: Shop4Makers | D55: 50 | E55: 1 | F55: pièce | G55: =IF(D55="","",D55/E55) -> 50 | H55: Maroc | I55: lien | J55: Seul INA226 trouvé au Maroc. Raccorder par fils Dupont selon le brochage du module. | K55: 18/10/2026
A56: MICROSD | B56: Module lecteur microSD SPI 3,3 V direct | C56: Moussasoft | D56: 18 | E56: 1 | F56: pièce | G56: =IF(D56="","",D56/E56) -> 18 | H56: Maroc | I56: lien | J56: ATTENTION : le module « pour Arduino » courant a un régulateur + tampon (type Catalex) : NE CONVIENT PAS. Chercher un module 3,3 V direct. | K56: 18/10/2026
A57: 1N4007_EXT | B57: Diode 1N4007 aux bornes d'une pompe DC (roue libre) | C57: Shop4Makers | D57: 0.9 | E57: 1 | F57: pièce | G57: =IF(D57="","",D57/E57) -> 0.9 | H57: Maroc | I57: lien | K57: 18/10/2026
A58: TP4056 | B58: Module chargeur TP4056 avec protection (DW01) | C58: Shop4Makers | D58: 15 | E58: 1 | F58: pièce | G58: =IF(D58="","",D58/E58) -> 15 | H58: Maroc | I58: lien | J58: Version avec protection DW01A + FS8205A, entrée USB-C. | K58: 18/10/2026
A59: BOOST | B59: Module boost MT3608 (réglé 5,1 V) | C59: Shop4Makers | D59: 16 | E59: 1 | F59: pièce | G59: =IF(D59="","",D59/E59) -> 16 | H59: Maroc | I59: lien | K59: 18/10/2026
A60: CELL_18650 | B60: Pile Li-ion 18650 de marque (≥ 2 500 mAh) | C60: Shop4Makers | D60: 55 | E60: 1 | F60: pièce | G60: =IF(D60="","",D60/E60) -> 55 | H60: Maroc | I60: lien | J60: LG INR18650MH1 3 200 mAh, cellule nue flat-top. | K60: 18/10/2026
A61: SUPPORT_18650 | B61: Support de pile 18650 (1 cellule) | C61: MicroPlanet | D61: 9 | E61: 1 | F61: pièce | G61: =IF(D61="","",D61/E61) -> 9 | H61: Maroc | I61: lien | K61: 18/10/2026
A62: PANNEAU_6V | B62: Panneau solaire 6 V 5–6 W | C62: Jumia.ma (Safe Buys) | D62: 110 | E62: 1 | F62: pièce | G62: =IF(D62="","",D62/E62) -> 110 | H62: Maroc | I62: lien | J62: 6 V 3,8 W (pas de 5 W au Maroc) : ~7 Wh/j en hiver pour ~2,3 consommés, marge ×3. Sortie USB = se branche sur l'USB-C du TP4056. | K62: 18/10/2026
A63: CHARGEUR_5V | B63: Chargeur 5 V 2 A (ou 3 A) de marque | C63: Megma | D63: 50 | E63: 1 | F63: pièce | G63: =IF(D63="","",D63/E63) -> 50 | H63: Maroc | I63: lien | J63: Seul 5 V 2 A en stock avec un vrai jack 5,5×2,1 (sans marque). Mieux : chargeur de téléphone de marque + cordon USB→jack. | K63: 18/10/2026
A64: CABLE_USB_JACK | B64: Cordon USB-A → jack 5,5×2,1 court | C64: Moussasoft | D64: 35 | E64: 1 | F64: pièce | G64: =IF(D64="","",D64/E64) -> 35 | H64: Maroc | I64: lien | J64: En rupture lors du relevé (A2itronic idem, 35 DH). | K64: 18/10/2026
A65: BUCK | B65: Module buck MP1584EN (12 V → 5,1 V) | C65: Shop4Makers | D65: 25 | E65: 1 | F65: pièce | G65: =IF(D65="","",D65/E65) -> 25 | H65: Maroc | I65: lien | J65: Entrée 28 V max : convient au bus AGM. | K65: 18/10/2026
A66: FUSIBLE_LAME | B66: Porte-fusible lame en ligne + fusible 10 A | C66: Accessoires auto | E66: 1 | F66: pièce | G66: =IF(D66="","",D66/E66) | H66: Maroc | J66: Porte-fusible lame en ligne non trouvé en ligne : magasin d'accessoires auto (fusible ATO/mini 10 A). | K66: 18/10/2026
A67: AGM_12V | B67: Batterie AGM 12 V (12 Ah) | C67: Jumia.ma | D67: 490 | E67: 1 | F67: pièce | G67: =IF(D67="","",D67/E67) -> 490 | H67: Maroc | I67: lien | J67: Prix de référence (Sunlight 12 Ah AGM, en rupture ; 9 Ah générique 249 DH). | K67: 18/10/2026
A68: PWM_SOLAIRE | B68: Régulateur de charge solaire PWM 12 V 10 A | C68: Jumia.ma (AM NEWS) | D68: 299 | E68: 1 | F68: pièce | G68: =IF(D68="","",D68/E68) -> 299 | H68: Maroc | I68: lien | J68: Prix de référence. | K68: 18/10/2026
A69: PANNEAU_12V | B69: Panneau solaire 12 V | C69: Jumia.ma (XARIUM TECH) | D69: 179 | E69: 1 | F69: pièce | G69: =IF(D69="","",D69/E69) -> 179 | H69: Maroc | I69: lien | J69: Prix de référence (20 W). | K69: 18/10/2026
A70: CORDON_SECTEUR | B70: Cordon secteur 2 fils avec fiche | C70: La-Librairie.ma | D70: 12 | E70: 1 | F70: pièce | G70: =IF(D70="","",D70/E70) -> 12 | H70: Maroc | I70: lien | J70: Probablement à embase C7 : couper l'embase, dénuder, embouts. Ou cordon d'électricien. | K70: 18/10/2026
A71: VIS_M3 | B71: Vis M3 nylon + écrou (H1-H7 ; nylon OBLIGATOIRE en H1/H5) | C71: Dsindustrie | D71: 120 | E71: 60 | F71: kit 200 pièces (60 vis) | G71: =IF(D71="","",D71/E71) -> 2 | H71: Maroc | I71: lien | J71: Kit nylon : 60 vis, 60 écrous, 80 entretoises 6–12 mm ; un kit suffit pour les 4 cartes. | K71: 18/10/2026
A72: ENTRETOISE_M3 | B72: Entretoise M3 nylon ~10 mm | C72: Dsindustrie | D72: 0 | E72: 1 | F72: inclus dans le kit | G72: =IF(D72="","",D72/E72) -> 0 | H72: Maroc | J72: Incluses dans le kit nylon M3. | K72: 18/10/2026
A73: BOITIER | B73: Boîtier étanche IP65 (~200×150 mm ou plus) | C73: EnergyMarket | D73: 352 | E73: 1 | F73: pièce | G73: =IF(D73="","",D73/E73) -> 352 | H73: Maroc | I73: lien | J73: La carte fait 278 × 135 mm : coffret ≥ 300 × 200 mm. Prix affiché, taille à confirmer avec le vendeur. | K73: 18/10/2026
A74: PRESSE_ETOUPE | B74: Presse-étoupe PG7 / PG9 | C74: Quincaillerie | E74: 1 | F74: pièce | G74: =IF(D74="","",D74/E74) | H74: Maroc | J74: Non trouvé en ligne au Maroc : électricien / quincaillerie. | K74: 18/10/2026
A75: FIL_05 | B75: Fil souple 0,5 mm² (mètre) | C75: ElectroDelivery | D75: 3.5 | E75: 1 | F75: mètre | G75: =IF(D75="","",D75/E75) -> 3.5 | H75: Maroc | I75: lien | J75: Câble souple 0,75 mm² (pas de 0,5 mm² en ligne). | K75: 18/10/2026
A76: FIL_15 | B76: Fil souple 1,5 mm² (mètre) | C76: ElectroDelivery | D76: 8 | E76: 1 | F76: mètre | G76: =IF(D76="","",D76/E76) -> 8 | H76: Maroc | I76: lien | J76: Câble souple 2 × 1,5 mm² (aller + retour d'une charge). | K76: 18/10/2026
A77: KIT_EMBOUTS | B77: Pince à sertir + kit d'embouts de câblage (ferrules) | C77: Moussasoft | D77: 250 | E77: 1 | F77: kit | G77: =IF(D77="","",D77/E77) -> 250 | H77: Maroc | I77: lien | J77: Pince à cliquet + 1 200 embouts 0,25–10 mm². | K77: 18/10/2026
A78: VERNIS | B78: Vernis de tropicalisation (Plastik 70 / Relife 70) | C78: A2itronic | D78: 400 | E78: 1 | F78: bombe 650 ml | G78: =IF(D78="","",D78/E78) -> 400 | H78: Maroc | I78: lien | J78: Tropicoat, en rupture lors du relevé. | K78: 18/10/2026
A79: DUPONT | B79: Fils Dupont mâle-femelle 20 cm | C79: MicroPlanet | D79: 6 | E79: 1 | F79: lot de 10 | G79: =IF(D79="","",D79/E79) -> 6 | H79: Maroc | I79: lien | J79: Lot de 10 fils 20 cm. | K79: 18/10/2026

Sheet msp1
A1: msp1 — station météo + tracker (18650 + solaire)
A2: Carte n3-universal rev 0.2.2 — composants à poser et à acheter pour UNE unité. Prix du 18/10/2026 (feuille Prix). Les quantités (bleu) sont modifiables ; l'achat groupé arrondi aux lots est dans « Global ».
A4: Consignes de pose de ce profil
B5: • Chaîne d'alimentation : panneau 6 V → TP4056 → 18650 → boost réglé à 5,1 V → J1 (bornier).
B6: • JP1 ôté (parqué en 2-3) : capteurs, OLED et servos coupés pendant le sommeil.
B7: • JP12 en 2-3 (pont 1S 100k/100k) ; JP16-JP19 FERMÉS (LDR tracker) ; JP21 FERMÉ (DHT extérieur) ; JP13-JP15 et JP20 OUVERTS.
B8: • NE PAS poser : LED5/R13, R17-R19, R27, tout l'étage relais (K1-K6…), Hi-Link, section 12 V.
B9: • Firmware : seuil de veille d'urgence à régler pour ≥ 3,3 V cellule. Cellule à l'ombre.
C11: Total à acheter, une unité (DH) | J11: =SUMIFS(J18:J60,G18:G60,"À acheter") -> 1072.1
C12: Options (DH) | J12: =SUMIFS(J18:J60,G18:G60,"Option") -> 170
C13: Déjà possédé — valeur indicative (DH) | J13: =SUMIFS(J18:J60,G18:G60,"Déjà possédé") -> 15
C14: Articles à acheter sans prix en ligne (import LCSC, quincaillerie, PCB) | J14: =SUMPRODUCT((G18:G60="À acheter")*(I18:I60="")) -> 3
A17: ID | B17: Catégorie | C17: Article | D17: Réf. carte | E17: Rôle | F17: Qté | G17: Statut | H17: Fournisseur | I17: Prix unitaire (DH) | J17: Coût (DH) | K17: Remarques | L17: Lien
A18: PCB | B18: 1. Carte et cerveau | C18: Circuit imprimé n3-universal rev 0.2.2 (JLCPCB, 2 oz) | D18: — | E18: Circuit imprimé n3-universal rev 0.2.2 | F18: 1 | G18: À acheter | H18: =INDEX(Prix!$C$5:$C$79,MATCH($A18,Prix!$A$5:$A$79,0)) -> JLCPCB | I18: =IFERROR(INDEX(Prix!$G$5:$G$79,MATCH($A18,Prix!$A$5:$A$79,0)),"") | J18: =IF(I18="","",F18*I18) | L18: lien
A19: ESP32_DEVKIT | B19: 1. Carte et cerveau | C19: ESP32 DevKit V1 30 broches (WROOM-32) | D19: A1 | E19: Module ESP32-WROOM-32 DevKit V1 30 broches, sur 2 supports 1x15 | F19: 1 | G19: À acheter | H19: =INDEX(Prix!$C$5:$C$79,MATCH($A19,Prix!$A$5:$A$79,0)) -> Shop4Makers | I19: =IFERROR(INDEX(Prix!$G$5:$G$79,MATCH($A19,Prix!$A$5:$A$79,0)),"") -> 113 | J19: =IF(I19="","",F19*I19) -> 113 | K19: Enfiché sur ses supports, jamais soudé. Vérifier l'écart des rangées (25,4 ou 27,94 mm : support droit sur A ou A'). | L19: lien
A20: R_220 | B20: 2. Résistances | C20: Résistance 220 Ω 1/4 W | D20: R20, R21 | E20: Série signal servo gros; Série signal servo petits | F20: 2 | G20: À acheter | H20: =INDEX(Prix!$C$5:$C$79,MATCH($A20,Prix!$A$5:$A$79,0)) -> MicroPlanet | I20: =IFERROR(INDEX(Prix!$G$5:$G$79,MATCH($A20,Prix!$A$5:$A$79,0)),"") -> 0.3 | J20: =IF(I20="","",F20*I20) -> 0.6 | L20: lien
A21: R_1k | B21: 2. Résistances | C21: Résistance 1 kΩ 1/4 W | D21: R34, R49, R50, R51, R52, R53, R54 | E21: Base commande gate; Série ADC_VBAT; Série ADC_A; Série ADC_B ; … | F21: 7 | G21: À acheter | H21: =INDEX(Prix!$C$5:$C$79,MATCH($A21,Prix!$A$5:$A$79,0)) -> MicroPlanet | I21: =IFERROR(INDEX(Prix!$G$5:$G$79,MATCH($A21,Prix!$A$5:$A$79,0)),"") -> 0.3 | J21: =IF(I21="","",F21*I21) -> 2.1 | L21: lien
A22: R_4.7k | B22: 2. Résistances | C22: Résistance 4,7 kΩ 1/4 W | D22: R24, R25, R26 | E22: Pull-up bus 1-Wire DS18B20; Pull-up I2C SDA; Pull-up I2C SCL | F22: 3 | G22: À acheter | H22: =INDEX(Prix!$C$5:$C$79,MATCH($A22,Prix!$A$5:$A$79,0)) -> MicroPlanet | I22: =IFERROR(INDEX(Prix!$G$5:$G$79,MATCH($A22,Prix!$A$5:$A$79,0)),"") -> 0.3 | J22: =IF(I22="","",F22*I22) -> 0.9 | L22: lien
A23: R_10k | B23: 2. Résistances | C23: Résistance 10 kΩ 1/4 W | D23: R23, R43, R44, R45, R46, R47, R48 | E23: Pull-up data DHT11; Bas de pont ADC_A (en circuit si JP16 FERMÉ : LDR msp; Bas de pont ADC_B (en circuit si JP17 FERMÉ : LDR msp; Bas de pont ADC_C (en circuit si JP18 FERMÉ : LDR msp ; … | F23: 7 | G23: À acheter | H23: =INDEX(Prix!$C$5:$C$79,MATCH($A23,Prix!$A$5:$A$79,0)) -> MicroPlanet | I23: =IFERROR(INDEX(Prix!$G$5:$G$79,MATCH($A23,Prix!$A$5:$A$79,0)),"") -> 0.3 | J23: =IF(I23="","",F23*I23) -> 2.1 | L23: lien
A24: R_18k | B24: 2. Résistances | C24: Résistance 18 kΩ 1/4 W | D24: R39 | E24: Bas du pont VBAT profil bus 12V : 100k/18k | F24: 1 | G24: À acheter | H24: =INDEX(Prix!$C$5:$C$79,MATCH($A24,Prix!$A$5:$A$79,0)) -> MicroPlanet | I24: =IFERROR(INDEX(Prix!$G$5:$G$79,MATCH($A24,Prix!$A$5:$A$79,0)),"") -> 0.3 | J24: =IF(I24="","",F24*I24) -> 0.3 | L24: lien
A25: R_100k | B25: 2. Résistances | C25: Résistance 100 kΩ 1/4 W | D25: R35, R38, R57, R58 | E25: Pull-up grille P-MOSFET vers +5V; Haut du pont VBAT; Grille de Q12 vers GND; Bas du pont VBAT profil 1S : 100k/100k | F25: 4 | G25: À acheter | H25: =INDEX(Prix!$C$5:$C$79,MATCH($A25,Prix!$A$5:$A$79,0)) -> MicroPlanet | I25: =IFERROR(INDEX(Prix!$G$5:$G$79,MATCH($A25,Prix!$A$5:$A$79,0)),"") -> 0.3 | J25: =IF(I25="","",F25*I25) -> 1.2 | L25: lien
A26: C_100n | B26: 3. Condensateurs | C26: Condensateur céramique 100 nF (pas 5 mm) | D26: C3, C4, C6, C7, C8, C9, C10, C13 | E26: Découplage 3V3 capteurs; Découplage 3V3 I2C; Filtre ADC ADC_A; Filtre ADC ADC_B ; … | F26: 8 | G26: À acheter | H26: =INDEX(Prix!$C$5:$C$79,MATCH($A26,Prix!$A$5:$A$79,0)) -> A2itronic | I26: =IFERROR(INDEX(Prix!$G$5:$G$79,MATCH($A26,Prix!$A$5:$A$79,0)),"") -> 0.5 | J26: =IF(I26="","",F26*I26) -> 4 | L26: lien
A27: C_10u25 | B27: 3. Condensateurs | C27: Condensateur électrolytique 10 µF 25 V | D27: C11 | E27: Entrée LDO | F27: 1 | G27: À acheter | H27: =INDEX(Prix!$C$5:$C$79,MATCH($A27,Prix!$A$5:$A$79,0)) -> A2itronic | I27: =IFERROR(INDEX(Prix!$G$5:$G$79,MATCH($A27,Prix!$A$5:$A$79,0)),"") -> 1 | J27: =IF(I27="","",F27*I27) -> 1 | L27: lien
A28: C_100u16 | B28: 3. Condensateurs | C28: Condensateur électrolytique 100 µF 16 V | D28: C12 | E28: Sortie LDO | F28: 1 | G28: À acheter | H28: =INDEX(Prix!$C$5:$C$79,MATCH($A28,Prix!$A$5:$A$79,0)) -> A2itronic | I28: =IFERROR(INDEX(Prix!$G$5:$G$79,MATCH($A28,Prix!$A$5:$A$79,0)),"") -> 1 | J28: =IF(I28="","",F28*I28) -> 1 | L28: lien
A29: C_470u16 | B29: 3. Condensateurs | C29: Condensateur électrolytique 470 µF 16 V (25 V convient) | D29: C2 | E29: Réservoir du rail 5 V commuté LDO_IN côté servos | F29: 1 | G29: À acheter | H29: =INDEX(Prix!$C$5:$C$79,MATCH($A29,Prix!$A$5:$A$79,0)) -> A2itronic | I29: =IFERROR(INDEX(Prix!$G$5:$G$79,MATCH($A29,Prix!$A$5:$A$79,0)),"") -> 2 | J29: =IF(I29="","",F29*I29) -> 2 | L29: lien
A30: C_1000u16 | B30: 3. Condensateurs | C30: Condensateur électrolytique 1000 µF 16 V (diam. 10 mm) | D30: C1 | E30: Réservoir rail 5V | F30: 1 | G30: À acheter | H30: =INDEX(Prix!$C$5:$C$79,MATCH($A30,Prix!$A$5:$A$79,0)) -> A2itronic | I30: =IFERROR(INDEX(Prix!$G$5:$G$79,MATCH($A30,Prix!$A$5:$A$79,0)),"") -> 3 | J30: =IF(I30="","",F30*I30) -> 3 | L30: lien
A31: BAT85 | B31: 4. Semi-conducteurs | C31: Diode Schottky BAT85 / BAT43 / BAT42 (DO-35) | D31: D11 | E31: Clamp ADC_VBAT sur +3V3 | F31: 1 | G31: À acheter | H31: =INDEX(Prix!$C$5:$C$79,MATCH($A31,Prix!$A$5:$A$79,0)) -> Moussasoft | I31: =IFERROR(INDEX(Prix!$G$5:$G$79,MATCH($A31,Prix!$A$5:$A$79,0)),"") -> 2 | J31: =IF(I31="","",F31*I31) -> 2 | L31: lien
A32: TVS_6V8 | B32: 4. Semi-conducteurs | C32: Diode TVS 1.5KE6.8A (ou P6KE6.8A) | D32: D12 | E32: TVS 6,8V sur le rail +5V : surtension / inversion résiduelle | F32: 1 | G32: À acheter | H32: =INDEX(Prix!$C$5:$C$79,MATCH($A32,Prix!$A$5:$A$79,0)) -> LCSC | I32: =IFERROR(INDEX(Prix!$G$5:$G$79,MATCH($A32,Prix!$A$5:$A$79,0)),"") | J32: =IF(I32="","",F32*I32) | K32: Protège le rail 5 V. Commander tôt chez LCSC (stock faible). | L32: lien
A33: BC337 | B33: 4. Semi-conducteurs | C33: Transistor NPN BC337-40 (TO-92) | D33: Q8 | E33: Driver gate | F33: 1 | G33: À acheter | H33: =INDEX(Prix!$C$5:$C$79,MATCH($A33,Prix!$A$5:$A$79,0)) -> A2itronic | I33: =IFERROR(INDEX(Prix!$G$5:$G$79,MATCH($A33,Prix!$A$5:$A$79,0)),"") -> 1 | J33: =IF(I33="","",F33*I33) -> 1 | K33: Brochage C-B-E sérigraphié. | L33: lien
A34: IRF4905 | B34: 4. Semi-conducteurs | C34: MOSFET P IRF4905 (TO-220) | D34: Q7, Q12 | E34: P-MOSFET commutation 5V du LDO capteurs; Anti-inversion entrée 5V (P-MOSFET 55V, VGS = -5V | F34: 2 | G34: À acheter | H34: =INDEX(Prix!$C$5:$C$79,MATCH($A34,Prix!$A$5:$A$79,0)) -> A2itronic | I34: =IFERROR(INDEX(Prix!$G$5:$G$79,MATCH($A34,Prix!$A$5:$A$79,0)),"") -> 10 | J34: =IF(I34="","",F34*I34) -> 20 | K34: Respecter la sérigraphie G-D-S de chaque MOSFET. | L34: lien
A35: LD1117 | B35: 4. Semi-conducteurs | C35: Régulateur LD1117V33 TO-220 (1=GND 2=OUT 3=IN) | D35: U1 | E35: Régulateur 3,3V 800mA du rail capteurs (1=GND 2=OUT 3=IN | F35: 1 | G35: À acheter | H35: =INDEX(Prix!$C$5:$C$79,MATCH($A35,Prix!$A$5:$A$79,0)) -> Megma | I35: =IFERROR(INDEX(Prix!$G$5:$G$79,MATCH($A35,Prix!$A$5:$A$79,0)),"") -> 7.5 | J35: =IF(I35="","",F35*I35) -> 7.5 | K35: Ce n'est pas un 78xx : 1=GND 2=OUT 3=IN (sérigraphié). | L35: lien
A36: BORNIER_2P | B36: 6. Connectique carte | C36: Bornier à vis 2 pôles pas 5,08 (KF301-2P) | D36: J1, J12, J18, J19, J25 | E36: Entrée 5V alternative; LDR déportée entre 3V3 et l'ADC; Distribution 5V; Distribution 3V3 capteurs ; … | F36: 5 | G36: À acheter | H36: =INDEX(Prix!$C$5:$C$79,MATCH($A36,Prix!$A$5:$A$79,0)) -> MicroPlanet | I36: =IFERROR(INDEX(Prix!$G$5:$G$79,MATCH($A36,Prix!$A$5:$A$79,0)),"") -> 2 | J36: =IF(I36="","",F36*I36) -> 10 | K36: Entrée du boost 5,1 V. Pont batterie 1S : J25 sur le + de la 18650, JP12 en 2-3. Veille d'urgence firmware ≥ 3,3 V. | L36: lien
A37: BORNIER_3P | B37: 6. Connectique carte | C37: Bornier à vis 3 pôles pas 5,08 (KF301-3P) | D37: J10, J11, J29, J30, J31, J32, J33, J34 | E37: DHT11/DHT22; Sonde DS18B20 étanche; Module pluie DO msp; DHT externe msp ; … | F37: 8 | G37: À acheter | H37: =INDEX(Prix!$C$5:$C$79,MATCH($A37,Prix!$A$5:$A$79,0)) -> MicroPlanet | I37: =IFERROR(INDEX(Prix!$G$5:$G$79,MATCH($A37,Prix!$A$5:$A$79,0)),"") -> 3 | J37: =IF(I37="","",F37*I37) -> 24 | L37: lien
A38: BARRETTE_F | B38: 6. Connectique carte | C38: Barrette femelle sécable 1×40 pas 2,54 | D38: A1 (2×15), J13, J21 | E38: Supports du DevKit (jamais soudé); OLED SSD1306 128x64 I2C 0x3C; Port I2C libre 2 | F38: 2 | G38: À acheter | H38: =INDEX(Prix!$C$5:$C$79,MATCH($A38,Prix!$A$5:$A$79,0)) -> Moussasoft | I38: =IFERROR(INDEX(Prix!$G$5:$G$79,MATCH($A38,Prix!$A$5:$A$79,0)),"") -> 5 | J38: =IF(I38="","",F38*I38) -> 10 | K38: 38 broches femelles utilisées (+ pertes de coupe). | L38: lien
A39: BARRETTE_M | B39: 6. Connectique carte | C39: Barrette mâle sécable 1×40 pas 2,54 | D39: J15, J16, J17, J20, JP1, JP12, JP13, JP14, JP15, JP16, JP17, JP18, JP19, JP20, … | E39: Servo GROS; Servo PETITS; Header service; Rail Dupont ; … | F39: 2 | G39: À acheter | H39: =INDEX(Prix!$C$5:$C$79,MATCH($A39,Prix!$A$5:$A$79,0)) -> Moussasoft | I39: =IFERROR(INDEX(Prix!$G$5:$G$79,MATCH($A39,Prix!$A$5:$A$79,0)),"") -> 4 | J39: =IF(I39="","",F39*I39) -> 8 | K39: 42 broches mâles utilisées (+ pertes de coupe). | L39: lien
A40: CAVALIER | B40: 6. Connectique carte | C40: Cavalier (jumper) 2,54 mm | D40: JP… | E40: Cavaliers de configuration du profil (+2 de rechange) | F40: 9 | G40: À acheter | H40: =INDEX(Prix!$C$5:$C$79,MATCH($A40,Prix!$A$5:$A$79,0)) -> Shop4Makers | I40: =IFERROR(INDEX(Prix!$G$5:$G$79,MATCH($A40,Prix!$A$5:$A$79,0)),"") -> 0.5 | J40: =IF(I40="","",F40*I40) -> 4.5 | K40: Cavaliers posés : JP1 parqué (rail commuté), JP12 en 2-3 (1S), JP16-JP19 et JP21 FERMÉS. | L40: lien
A41: FIL | B41: 6. Connectique carte | C41: Pont de fil à la place de D5 (chute de patte de résistance) | D41: D5 | E41: PONT DE FIL vers VIN DevKit | F41: 1 | G41: À acheter | H41: =INDEX(Prix!$C$5:$C$79,MATCH($A41,Prix!$A$5:$A$79,0)) -> — | I41: =IFERROR(INDEX(Prix!$G$5:$G$79,MATCH($A41,Prix!$A$5:$A$79,0)),"") -> 0 | J41: =IF(I41="","",F41*I41) -> 0 | K41: D5 = pont de fil (rev 0.2.2). Règle absolue : ne JAMAIS brancher l'USB du DevKit quand la carte est alimentée.
A42: TP_FIL | B42: 6. Connectique carte | C42: Points de test TP1-TP4 : boucle de fil (chute de patte) | D42: TP1, TP2, TP3, TP4 | E42: Point de test GND; Point de test +5V; Point de test +3V3_SW; Point de test +3V3 | F42: 4 | G42: À acheter | H42: =INDEX(Prix!$C$5:$C$79,MATCH($A42,Prix!$A$5:$A$79,0)) -> — | I42: =IFERROR(INDEX(Prix!$G$5:$G$79,MATCH($A42,Prix!$A$5:$A$79,0)),"") -> 0 | J42: =IF(I42="","",F42*I42) -> 0
A43: DHT11 | B43: 7. Capteurs et actionneurs | C43: Capteur température/humidité DHT11 | D43: hors carte | E43: Température/humidité air intérieure (J10) et extérieure (J30) | F43: 2 | G43: À acheter | H43: =INDEX(Prix!$C$5:$C$79,MATCH($A43,Prix!$A$5:$A$79,0)) -> Shop4Makers | I43: =IFERROR(INDEX(Prix!$G$5:$G$79,MATCH($A43,Prix!$A$5:$A$79,0)),"") -> 16.2 | J43: =IF(I43="","",F43*I43) -> 32.4 | K43: J30 exige JP21 FERMÉ (pull-up R47). Un BME280 détecté remplace le DHT (option ci-dessous). | L43: lien
A44: BME280 | B44: 7. Capteurs et actionneurs | C44: Module BME280 I2C (température, humidité, pression) | D44: hors carte | E44: Remplace les DHT11 : 0x76 = intérieur, 0x77 = extérieur (I2C J21 / J14) | F44: 2 | G44: Option | H44: =INDEX(Prix!$C$5:$C$79,MATCH($A44,Prix!$A$5:$A$79,0)) -> Shop4Makers | I44: =IFERROR(INDEX(Prix!$G$5:$G$79,MATCH($A44,Prix!$A$5:$A$79,0)),"") -> 85 | J44: =IF(I44="","",F44*I44) -> 170 | K44: Le firmware le détecte au démarrage. Adresse 0x77 : pont SDO à souder sur le module. | L44: lien
A45: DS18B20 | B45: 7. Capteurs et actionneurs | C45: Sonde DS18B20 étanche (câble 1 m) | D45: hors carte | E45: Température du sol (« TempEau » côté serveur) sur J11 | F45: 1 | G45: À acheter | H45: =INDEX(Prix!$C$5:$C$79,MATCH($A45,Prix!$A$5:$A$79,0)) -> A2itronic | I45: =IFERROR(INDEX(Prix!$G$5:$G$79,MATCH($A45,Prix!$A$5:$A$79,0)),"") -> 50 | J45: =IF(I45="","",F45*I45) -> 50 | K45: Version étanche, câble 1 m. | L45: lien
A46: LDR | B46: 7. Capteurs et actionneurs | C46: Photorésistance LDR GL5528 | D46: hors carte | E46: Tracker solaire : 4 photorésistances sur J31-J34 | F46: 4 | G46: À acheter | H46: =INDEX(Prix!$C$5:$C$79,MATCH($A46,Prix!$A$5:$A$79,0)) -> Moussasoft | I46: =IFERROR(INDEX(Prix!$G$5:$G$79,MATCH($A46,Prix!$A$5:$A$79,0)),"") -> 2 | J46: =IF(I46="","",F46*I46) -> 8 | K46: JP16-JP19 FERMÉS (bas de pont R43-R46 10k). Prévoir un séparateur en croix entre les 4 LDR. | L46: lien
A47: PLUIE | B47: 7. Capteurs et actionneurs | C47: Module capteur de pluie FC-37 / YL-83 (sortie DO) | D47: hors carte | E47: Détection de pluie (sortie DO) sur J29 | F47: 1 | G47: À acheter | H47: =INDEX(Prix!$C$5:$C$79,MATCH($A47,Prix!$A$5:$A$79,0)) -> Moussasoft | I47: =IFERROR(INDEX(Prix!$G$5:$G$79,MATCH($A47,Prix!$A$5:$A$79,0)),"") -> 25 | J47: =IF(I47="","",F47*I47) -> 25 | K47: Ne PAS poser R17 (sinon « mouillé » permanent). Alimenté par +3V3_SW. | L47: lien
A48: SOL_CAPA | B48: 7. Capteurs et actionneurs | C48: Capteur d'humidité du sol capacitif v1.2 (sortie AO) | D48: hors carte | E48: Humidité du sol (« HumiditeSol », sortie AO) sur J12 | F48: 1 | G48: À acheter | H48: =INDEX(Prix!$C$5:$C$79,MATCH($A48,Prix!$A$5:$A$79,0)) -> Shop4Makers | I48: =IFERROR(INDEX(Prix!$G$5:$G$79,MATCH($A48,Prix!$A$5:$A$79,0)),"") -> 35 | J48: =IF(I48="","",F48*I48) -> 35 | K48: R27 NON posé, JP20 OUVERT. Module 3 fils : prendre le GND sur un bornier voisin (J12 n'a que 3V3/ADC). | L48: lien
A49: SG90 | B49: 7. Capteurs et actionneurs | C49: Servomoteur SG90 | D49: hors carte | E49: Tracker : servo gauche-droite (J15) et haut-bas (J16) | F49: 2 | G49: À acheter | H49: =INDEX(Prix!$C$5:$C$79,MATCH($A49,Prix!$A$5:$A$79,0)) -> Moussasoft | I49: =IFERROR(INDEX(Prix!$G$5:$G$79,MATCH($A49,Prix!$A$5:$A$79,0)),"") -> 30 | J49: =IF(I49="","",F49*I49) -> 60 | K49: Coupés pendant le sommeil (JP1 ôté). Gros servo plus tard : fil +5V en étoile, voir ALIMENTATION.md. | L49: lien
A50: OLED | B50: 7. Capteurs et actionneurs | C50: Écran OLED 0,96" SSD1306 I2C 128×64 | D50: hors carte | E50: Affichage local sur J13 | F50: 1 | G50: À acheter | H50: =INDEX(Prix!$C$5:$C$79,MATCH($A50,Prix!$A$5:$A$79,0)) -> Shop4Makers | I50: =IFERROR(INDEX(Prix!$G$5:$G$79,MATCH($A50,Prix!$A$5:$A$79,0)),"") -> 70 | J50: =IF(I50="","",F50*I50) -> 70 | K50: Alimenté par le rail commuté : éteint en sommeil, 0 fuite. | L50: lien
A51: TP4056 | B51: 8. Alimentation hors carte | C51: Module chargeur TP4056 avec protection (DW01) | D51: hors carte | E51: Chargeur 1S entre panneau et 18650 | F51: 1 | G51: Déjà possédé | H51: =INDEX(Prix!$C$5:$C$79,MATCH($A51,Prix!$A$5:$A$79,0)) -> Shop4Makers | I51: =IFERROR(INDEX(Prix!$G$5:$G$79,MATCH($A51,Prix!$A$5:$A$79,0)),"") -> 15 | J51: =IF(I51="","",F51*I51) -> 15 | K51: Décision N5 : conservé (déjà en stock). Modèle AVEC protection (DW01). | L51: lien
A52: BOOST | B52: 8. Alimentation hors carte | C52: Module boost MT3608 (réglé 5,1 V) | D52: hors carte | E52: Élève 3,0–4,2 V de la 18650 à 5,1 V vers J1 | F52: 1 | G52: À acheter | H52: =INDEX(Prix!$C$5:$C$79,MATCH($A52,Prix!$A$5:$A$79,0)) -> Shop4Makers | I52: =IFERROR(INDEX(Prix!$G$5:$G$79,MATCH($A52,Prix!$A$5:$A$79,0)),"") -> 16 | J52: =IF(I52="","",F52*I52) -> 16 | K52: RÉGLER À 5,1 V au multimètre AVANT de brancher la carte. MT3608 : ~1,5 mA à vide, acceptable. | L52: lien
A53: CELL_18650 | B53: 8. Alimentation hors carte | C53: Pile Li-ion 18650 de marque (≥ 2 500 mAh) | D53: hors carte | E53: Stockage d'énergie (~2,3 Wh/jour consommés) | F53: 1 | G53: À acheter | H53: =INDEX(Prix!$C$5:$C$79,MATCH($A53,Prix!$A$5:$A$79,0)) -> Shop4Makers | I53: =IFERROR(INDEX(Prix!$G$5:$G$79,MATCH($A53,Prix!$A$5:$A$79,0)),"") -> 55 | J53: =IF(I53="","",F53*I53) -> 55 | K53: Cellule de marque (Samsung/LG/Panasonic/Molicel), pas de « 9900 mAh ». 2e cellule en parallèle = option. | L53: lien
A54: SUPPORT_18650 | B54: 8. Alimentation hors carte | C54: Support de pile 18650 (1 cellule) | D54: hors carte | E54: Logement de la cellule | F54: 1 | G54: À acheter | H54: =INDEX(Prix!$C$5:$C$79,MATCH($A54,Prix!$A$5:$A$79,0)) -> MicroPlanet | I54: =IFERROR(INDEX(Prix!$G$5:$G$79,MATCH($A54,Prix!$A$5:$A$79,0)),"") -> 9 | J54: =IF(I54="","",F54*I54) -> 9 | K54: À l'ombre, sous le panneau : jamais au soleil (> 45 °C). | L54: lien
A55: PANNEAU_6V | B55: 8. Alimentation hors carte | C55: Panneau solaire 6 V 5–6 W | D55: hors carte | E55: Recharge solaire | F55: 1 | G55: À acheter | H55: =INDEX(Prix!$C$5:$C$79,MATCH($A55,Prix!$A$5:$A$79,0)) -> Jumia.ma (Safe Buys) | I55: =IFERROR(INDEX(Prix!$G$5:$G$79,MATCH($A55,Prix!$A$5:$A$79,0)),"") -> 110 | J55: =IF(I55="","",F55*I55) -> 110 | K55: 5–6 W / 6 V : un 2 W est déficitaire en hiver (ALIMENTATION.md §3). | L55: lien
A56: VIS_M3 | B56: 9. Mécanique et câblage | C56: Vis M3 nylon + écrou (H1-H7 ; nylon OBLIGATOIRE en H1/H5) | D56: H1, H2, H3, H4, H5, H6, H7 | E56: Trou de fixation M3 | F56: 7 | G56: À acheter | H56: =INDEX(Prix!$C$5:$C$79,MATCH($A56,Prix!$A$5:$A$79,0)) -> Dsindustrie | I56: =IFERROR(INDEX(Prix!$G$5:$G$79,MATCH($A56,Prix!$A$5:$A$79,0)),"") -> 2 | J56: =IF(I56="","",F56*I56) -> 14 | L56: lien
A57: ENTRETOISE_M3 | B57: 9. Mécanique et câblage | C57: Entretoise M3 nylon ~10 mm | D57: H1-H7 | E57: Entretoises de fixation de la carte | F57: 7 | G57: À acheter | H57: =INDEX(Prix!$C$5:$C$79,MATCH($A57,Prix!$A$5:$A$79,0)) -> Dsindustrie | I57: =IFERROR(INDEX(Prix!$G$5:$G$79,MATCH($A57,Prix!$A$5:$A$79,0)),"") -> 0 | J57: =IF(I57="","",F57*I57) -> 0
A58: BOITIER | B58: 9. Mécanique et câblage | C58: Boîtier étanche IP65 (~200×150 mm ou plus) | D58: hors carte | E58: Boîtier étanche extérieur | F58: 1 | G58: À acheter | H58: =INDEX(Prix!$C$5:$C$79,MATCH($A58,Prix!$A$5:$A$79,0)) -> EnergyMarket | I58: =IFERROR(INDEX(Prix!$G$5:$G$79,MATCH($A58,Prix!$A$5:$A$79,0)),"") -> 352 | J58: =IF(I58="","",F58*I58) -> 352 | K58: Ventilé par le bas / à l'ombre. | L58: lien
A59: PRESSE_ETOUPE | B59: 9. Mécanique et câblage | C59: Presse-étoupe PG7 / PG9 | D59: hors carte | E59: Passage des câbles capteurs/servos/alim | F59: 6 | G59: À acheter | H59: =INDEX(Prix!$C$5:$C$79,MATCH($A59,Prix!$A$5:$A$79,0)) -> Quincaillerie | I59: =IFERROR(INDEX(Prix!$G$5:$G$79,MATCH($A59,Prix!$A$5:$A$79,0)),"") | J59: =IF(I59="","",F59*I59) | K59: PG7 pour les sondes, PG9 pour l'alim.
A60: FIL_05 | B60: 9. Mécanique et câblage | C60: Fil souple 0,5 mm² (mètre) | D60: hors carte | E60: Câblage des capteurs (au mètre) | F60: 5 | G60: À acheter | H60: =INDEX(Prix!$C$5:$C$79,MATCH($A60,Prix!$A$5:$A$79,0)) -> ElectroDelivery | I60: =IFERROR(INDEX(Prix!$G$5:$G$79,MATCH($A60,Prix!$A$5:$A$79,0)),"") -> 3.5 | J60: =IF(I60="","",F60*I60) -> 17.5 | K60: Souple 0,25–0,5 mm² ; embouts sur chaque fil. | L60: lien

Sheet n3pp
A1: n3pp — serre (chargeur 5 V)
A2: Carte n3-universal rev 0.2.2 — composants à poser et à acheter pour UNE unité. Prix du 18/10/2026 (feuille Prix). Les quantités (bleu) sont modifiables ; l'achat groupé arrondi aux lots est dans « Global ».
A4: Consignes de pose de ce profil
B5: • Chargeur 5 V 2 A → cordon court et épais → J2 (jack). Jamais par le micro-USB du DevKit.
B6: • JP1 ôté (parqué en 2-3) ; JP12 en 2-3 ; JP20 FERMÉ (LDR) ; JP16-JP19 OUVERTS (sondes de sol) ; JP5 sans cavalier (AUTO).
B7: • Un seul relais : K1 = pompe d'arrosage (et ses pièces Q1, D1, R1, R5, LED1, R9, J3, JP5, R61).
B8: • NE PAS poser : LED5/R13, R43-R46, R17-R19, K2-K6, servos, Hi-Link, section 12 V.
B9: • J25 : relier J25-1 au +5V (J18-1) par un fil, sinon la mesure « batterie » lit 0 et le firmware se met en veille d'urgence (ou clé serveur 112 = 0). À vérifier au premier allumage.
C11: Total à acheter, une unité (DH) | J11: =SUMIFS(J18:J57,G18:G57,"À acheter") -> 929.8
C12: Options (DH) | J12: =SUMIFS(J18:J57,G18:G57,"Option") -> 85
C13: Déjà possédé — valeur indicative (DH) | J13: =SUMIFS(J18:J57,G18:G57,"Déjà possédé") -> 0
C14: Articles à acheter sans prix en ligne (import LCSC, quincaillerie, PCB) | J14: =SUMPRODUCT((G18:G57="À acheter")*(I18:I57="")) -> 3
A17: ID | B17: Catégorie | C17: Article | D17: Réf. carte | E17: Rôle | F17: Qté | G17: Statut | H17: Fournisseur | I17: Prix unitaire (DH) | J17: Coût (DH) | K17: Remarques | L17: Lien
A18: PCB | B18: 1. Carte et cerveau | C18: Circuit imprimé n3-universal rev 0.2.2 (JLCPCB, 2 oz) | D18: — | E18: Circuit imprimé n3-universal rev 0.2.2 | F18: 1 | G18: À acheter | H18: =INDEX(Prix!$C$5:$C$79,MATCH($A18,Prix!$A$5:$A$79,0)) -> JLCPCB | I18: =IFERROR(INDEX(Prix!$G$5:$G$79,MATCH($A18,Prix!$A$5:$A$79,0)),"") | J18: =IF(I18="","",F18*I18) | L18: lien
A19: ESP32_DEVKIT | B19: 1. Carte et cerveau | C19: ESP32 DevKit V1 30 broches (WROOM-32) | D19: A1 | E19: Module ESP32-WROOM-32 DevKit V1 30 broches, sur 2 supports 1x15 | F19: 1 | G19: À acheter | H19: =INDEX(Prix!$C$5:$C$79,MATCH($A19,Prix!$A$5:$A$79,0)) -> Shop4Makers | I19: =IFERROR(INDEX(Prix!$G$5:$G$79,MATCH($A19,Prix!$A$5:$A$79,0)),"") -> 113 | J19: =IF(I19="","",F19*I19) -> 113 | K19: Enfiché sur ses supports, jamais soudé. Vérifier l'écart des rangées (25,4 ou 27,94 mm : support droit sur A ou A'). | L19: lien
A20: R_1k | B20: 2. Résistances | C20: Résistance 1 kΩ 1/4 W | D20: R1, R9, R34, R49, R50, R51, R52, R53, R54, R61 | E20: Résistance base transistor; Résistance LED témoin; Base commande gate; Série ADC_VBAT ; … | F20: 10 | G20: À acheter | H20: =INDEX(Prix!$C$5:$C$79,MATCH($A20,Prix!$A$5:$A$79,0)) -> MicroPlanet | I20: =IFERROR(INDEX(Prix!$G$5:$G$79,MATCH($A20,Prix!$A$5:$A$79,0)),"") -> 0.3 | J20: =IF(I20="","",F20*I20) -> 3 | L20: lien
A21: R_4.7k | B21: 2. Résistances | C21: Résistance 4,7 kΩ 1/4 W | D21: R25, R26 | E21: Pull-up I2C SDA; Pull-up I2C SCL | F21: 2 | G21: À acheter | H21: =INDEX(Prix!$C$5:$C$79,MATCH($A21,Prix!$A$5:$A$79,0)) -> MicroPlanet | I21: =IFERROR(INDEX(Prix!$G$5:$G$79,MATCH($A21,Prix!$A$5:$A$79,0)),"") -> 0.3 | J21: =IF(I21="","",F21*I21) -> 0.6 | L21: lien
A22: R_10k | B22: 2. Résistances | C22: Résistance 10 kΩ 1/4 W | D22: R5, R23, R27, R48 | E22: Pull-down base; Pull-up data DHT11; Bas de pont LDR sur ADC_E; Pull-down base Q8 | F22: 4 | G22: À acheter | H22: =INDEX(Prix!$C$5:$C$79,MATCH($A22,Prix!$A$5:$A$79,0)) -> MicroPlanet | I22: =IFERROR(INDEX(Prix!$G$5:$G$79,MATCH($A22,Prix!$A$5:$A$79,0)),"") -> 0.3 | J22: =IF(I22="","",F22*I22) -> 1.2 | L22: lien
A23: R_18k | B23: 2. Résistances | C23: Résistance 18 kΩ 1/4 W | D23: R39 | E23: Bas du pont VBAT profil bus 12V : 100k/18k | F23: 1 | G23: À acheter | H23: =INDEX(Prix!$C$5:$C$79,MATCH($A23,Prix!$A$5:$A$79,0)) -> MicroPlanet | I23: =IFERROR(INDEX(Prix!$G$5:$G$79,MATCH($A23,Prix!$A$5:$A$79,0)),"") -> 0.3 | J23: =IF(I23="","",F23*I23) -> 0.3 | L23: lien
A24: R_100k | B24: 2. Résistances | C24: Résistance 100 kΩ 1/4 W | D24: R35, R38, R57, R58 | E24: Pull-up grille P-MOSFET vers +5V; Haut du pont VBAT; Grille de Q12 vers GND; Bas du pont VBAT profil 1S : 100k/100k | F24: 4 | G24: À acheter | H24: =INDEX(Prix!$C$5:$C$79,MATCH($A24,Prix!$A$5:$A$79,0)) -> MicroPlanet | I24: =IFERROR(INDEX(Prix!$G$5:$G$79,MATCH($A24,Prix!$A$5:$A$79,0)),"") -> 0.3 | J24: =IF(I24="","",F24*I24) -> 1.2 | L24: lien
A25: C_100n | B25: 3. Condensateurs | C25: Condensateur céramique 100 nF (pas 5 mm) | D25: C3, C4, C6, C7, C8, C9, C10, C13 | E25: Découplage 3V3 capteurs; Découplage 3V3 I2C; Filtre ADC ADC_A; Filtre ADC ADC_B ; … | F25: 8 | G25: À acheter | H25: =INDEX(Prix!$C$5:$C$79,MATCH($A25,Prix!$A$5:$A$79,0)) -> A2itronic | I25: =IFERROR(INDEX(Prix!$G$5:$G$79,MATCH($A25,Prix!$A$5:$A$79,0)),"") -> 0.5 | J25: =IF(I25="","",F25*I25) -> 4 | L25: lien
A26: C_10u25 | B26: 3. Condensateurs | C26: Condensateur électrolytique 10 µF 25 V | D26: C11 | E26: Entrée LDO | F26: 1 | G26: À acheter | H26: =INDEX(Prix!$C$5:$C$79,MATCH($A26,Prix!$A$5:$A$79,0)) -> A2itronic | I26: =IFERROR(INDEX(Prix!$G$5:$G$79,MATCH($A26,Prix!$A$5:$A$79,0)),"") -> 1 | J26: =IF(I26="","",F26*I26) -> 1 | L26: lien
A27: C_100u16 | B27: 3. Condensateurs | C27: Condensateur électrolytique 100 µF 16 V | D27: C12 | E27: Sortie LDO | F27: 1 | G27: À acheter | H27: =INDEX(Prix!$C$5:$C$79,MATCH($A27,Prix!$A$5:$A$79,0)) -> A2itronic | I27: =IFERROR(INDEX(Prix!$G$5:$G$79,MATCH($A27,Prix!$A$5:$A$79,0)),"") -> 1 | J27: =IF(I27="","",F27*I27) -> 1 | L27: lien
A28: C_1000u16 | B28: 3. Condensateurs | C28: Condensateur électrolytique 1000 µF 16 V (diam. 10 mm) | D28: C1 | E28: Réservoir rail 5V | F28: 1 | G28: À acheter | H28: =INDEX(Prix!$C$5:$C$79,MATCH($A28,Prix!$A$5:$A$79,0)) -> A2itronic | I28: =IFERROR(INDEX(Prix!$G$5:$G$79,MATCH($A28,Prix!$A$5:$A$79,0)),"") -> 3 | J28: =IF(I28="","",F28*I28) -> 3 | L28: lien
A29: 1N4007 | B29: 4. Semi-conducteurs | C29: Diode 1N4007 (roue libre des bobines de relais) | D29: D1 | E29: Diode de roue libre bobine | F29: 1 | G29: À acheter | H29: =INDEX(Prix!$C$5:$C$79,MATCH($A29,Prix!$A$5:$A$79,0)) -> Shop4Makers | I29: =IFERROR(INDEX(Prix!$G$5:$G$79,MATCH($A29,Prix!$A$5:$A$79,0)),"") -> 0.9 | J29: =IF(I29="","",F29*I29) -> 0.9 | L29: lien
A30: BAT85 | B30: 4. Semi-conducteurs | C30: Diode Schottky BAT85 / BAT43 / BAT42 (DO-35) | D30: D11 | E30: Clamp ADC_VBAT sur +3V3 | F30: 1 | G30: À acheter | H30: =INDEX(Prix!$C$5:$C$79,MATCH($A30,Prix!$A$5:$A$79,0)) -> Moussasoft | I30: =IFERROR(INDEX(Prix!$G$5:$G$79,MATCH($A30,Prix!$A$5:$A$79,0)),"") -> 2 | J30: =IF(I30="","",F30*I30) -> 2 | L30: lien
A31: TVS_6V8 | B31: 4. Semi-conducteurs | C31: Diode TVS 1.5KE6.8A (ou P6KE6.8A) | D31: D12 | E31: TVS 6,8V sur le rail +5V : surtension / inversion résiduelle | F31: 1 | G31: À acheter | H31: =INDEX(Prix!$C$5:$C$79,MATCH($A31,Prix!$A$5:$A$79,0)) -> LCSC | I31: =IFERROR(INDEX(Prix!$G$5:$G$79,MATCH($A31,Prix!$A$5:$A$79,0)),"") | J31: =IF(I31="","",F31*I31) | K31: Protège le rail 5 V. Commander tôt chez LCSC (stock faible). | L31: lien
A32: BC337 | B32: 4. Semi-conducteurs | C32: Transistor NPN BC337-40 (TO-92) | D32: Q1, Q8 | E32: Transistor NPN commande relais; Driver gate | F32: 2 | G32: À acheter | H32: =INDEX(Prix!$C$5:$C$79,MATCH($A32,Prix!$A$5:$A$79,0)) -> A2itronic | I32: =IFERROR(INDEX(Prix!$G$5:$G$79,MATCH($A32,Prix!$A$5:$A$79,0)),"") -> 1 | J32: =IF(I32="","",F32*I32) -> 2 | K32: Brochage C-B-E sérigraphié. | L32: lien
A33: IRF4905 | B33: 4. Semi-conducteurs | C33: MOSFET P IRF4905 (TO-220) | D33: Q7, Q12 | E33: P-MOSFET commutation 5V du LDO capteurs; Anti-inversion entrée 5V (P-MOSFET 55V, VGS = -5V | F33: 2 | G33: À acheter | H33: =INDEX(Prix!$C$5:$C$79,MATCH($A33,Prix!$A$5:$A$79,0)) -> A2itronic | I33: =IFERROR(INDEX(Prix!$G$5:$G$79,MATCH($A33,Prix!$A$5:$A$79,0)),"") -> 10 | J33: =IF(I33="","",F33*I33) -> 20 | K33: Respecter la sérigraphie G-D-S de chaque MOSFET. | L33: lien
A34: LD1117 | B34: 4. Semi-conducteurs | C34: Régulateur LD1117V33 TO-220 (1=GND 2=OUT 3=IN) | D34: U1 | E34: Régulateur 3,3V 800mA du rail capteurs (1=GND 2=OUT 3=IN | F34: 1 | G34: À acheter | H34: =INDEX(Prix!$C$5:$C$79,MATCH($A34,Prix!$A$5:$A$79,0)) -> Megma | I34: =IFERROR(INDEX(Prix!$G$5:$G$79,MATCH($A34,Prix!$A$5:$A$79,0)),"") -> 7.5 | J34: =IF(I34="","",F34*I34) -> 7.5 | K34: Ce n'est pas un 78xx : 1=GND 2=OUT 3=IN (sérigraphié). | L34: lien
A35: LED_R | B35: 4. Semi-conducteurs | C35: LED 5 mm rouge | D35: LED1 | E35: LED témoin relais ON | F35: 1 | G35: À acheter | H35: =INDEX(Prix!$C$5:$C$79,MATCH($A35,Prix!$A$5:$A$79,0)) -> Moussasoft | I35: =IFERROR(INDEX(Prix!$G$5:$G$79,MATCH($A35,Prix!$A$5:$A$79,0)),"") -> 1 | J35: =IF(I35="","",F35*I35) -> 1 | L35: lien
A36: SRD05 | B36: 5. Relais et protection secteur | C36: Relais Songle SRD-05VDC-SL-C (composant seul, pas le module) | D36: K1 | E36: Relais 5V SPDT Songle/Sanyou SRD Form C | F36: 1 | G36: À acheter | H36: =INDEX(Prix!$C$5:$C$79,MATCH($A36,Prix!$A$5:$A$79,0)) -> Moussasoft | I36: =IFERROR(INDEX(Prix!$G$5:$G$79,MATCH($A36,Prix!$A$5:$A$79,0)),"") -> 18 | J36: =IF(I36="","",F36*I36) -> 18 | L36: lien
A37: BORNIER_2P | B37: 6. Connectique carte | C37: Bornier à vis 2 pôles pas 5,08 (KF301-2P) | D37: J1, J12, J18, J19, J25 | E37: Entrée 5V alternative; LDR déportée entre 3V3 et l'ADC; Distribution 5V; Distribution 3V3 capteurs ; … | F37: 5 | G37: À acheter | H37: =INDEX(Prix!$C$5:$C$79,MATCH($A37,Prix!$A$5:$A$79,0)) -> MicroPlanet | I37: =IFERROR(INDEX(Prix!$G$5:$G$79,MATCH($A37,Prix!$A$5:$A$79,0)),"") -> 2 | J37: =IF(I37="","",F37*I37) -> 10 | K37: J2 (jack) pour le chargeur ; J1 en secours. Pas de batterie : relier J25-1 au +5V (J18-1) par un fil, sinon le firmware lit une batterie vide et part en veille d'urgence (ou désactiver la clé serveur 112). À vérifier au 1er allumage. | L37: lien
A38: BORNIER_3P | B38: 6. Connectique carte | C38: Bornier à vis 3 pôles pas 5,08 (KF301-3P) | D38: J3, J10, J31, J32, J33, J34 | E38: Bornier charge 230V; DHT11/DHT22; Entrée analogique ADC_A; Entrée analogique ADC_B ; … | F38: 6 | G38: À acheter | H38: =INDEX(Prix!$C$5:$C$79,MATCH($A38,Prix!$A$5:$A$79,0)) -> MicroPlanet | I38: =IFERROR(INDEX(Prix!$G$5:$G$79,MATCH($A38,Prix!$A$5:$A$79,0)),"") -> 3 | J38: =IF(I38="","",F38*I38) -> 18 | L38: lien
A39: BARRETTE_F | B39: 6. Connectique carte | C39: Barrette femelle sécable 1×40 pas 2,54 | D39: A1 (2×15), J13, J21 | E39: Supports du DevKit (jamais soudé); OLED SSD1306 128x64 I2C 0x3C; Port I2C libre 2 | F39: 2 | G39: À acheter | H39: =INDEX(Prix!$C$5:$C$79,MATCH($A39,Prix!$A$5:$A$79,0)) -> Moussasoft | I39: =IFERROR(INDEX(Prix!$G$5:$G$79,MATCH($A39,Prix!$A$5:$A$79,0)),"") -> 5 | J39: =IF(I39="","",F39*I39) -> 10 | K39: 38 broches femelles utilisées (+ pertes de coupe). | L39: lien
A40: BARRETTE_M | B40: 6. Connectique carte | C40: Barrette mâle sécable 1×40 pas 2,54 | D40: J17, J20, JP1, JP5, JP12, JP13, JP14, JP15, JP16, JP17, JP18, JP19, JP20, JP21 | E40: Header service; Rail Dupont; BYPASS gate : cavalier 1-2 FERME par défaut; Sélecteur K1 : SANS cavalier = AUTO ; … | F40: 2 | G40: À acheter | H40: =INDEX(Prix!$C$5:$C$79,MATCH($A40,Prix!$A$5:$A$79,0)) -> Moussasoft | I40: =IFERROR(INDEX(Prix!$G$5:$G$79,MATCH($A40,Prix!$A$5:$A$79,0)),"") -> 4 | J40: =IF(I40="","",F40*I40) -> 8 | K40: 39 broches mâles utilisées (+ pertes de coupe). | L40: lien
A41: CAVALIER | B41: 6. Connectique carte | C41: Cavalier (jumper) 2,54 mm | D41: JP… | E41: Cavaliers de configuration du profil (+2 de rechange) | F41: 5 | G41: À acheter | H41: =INDEX(Prix!$C$5:$C$79,MATCH($A41,Prix!$A$5:$A$79,0)) -> Shop4Makers | I41: =IFERROR(INDEX(Prix!$G$5:$G$79,MATCH($A41,Prix!$A$5:$A$79,0)),"") -> 0.5 | J41: =IF(I41="","",F41*I41) -> 2.5 | K41: Cavaliers posés : JP1 parqué (rail commuté), JP12 en 2-3, JP20 FERMÉ ; JP5 SANS cavalier (AUTO). | L41: lien
A42: JACK_DC | B42: 6. Connectique carte | C42: Jack DC femelle 5,5×2,1 pour circuit imprimé (DC-005) | D42: J2 | E42: Entrée 5V | F42: 1 | G42: À acheter | H42: =INDEX(Prix!$C$5:$C$79,MATCH($A42,Prix!$A$5:$A$79,0)) -> ShoppingMaroc | I42: =IFERROR(INDEX(Prix!$G$5:$G$79,MATCH($A42,Prix!$A$5:$A$79,0)),"") -> 4 | J42: =IF(I42="","",F42*I42) -> 4 | L42: lien
A43: FIL | B43: 6. Connectique carte | C43: Pont de fil à la place de D5 (chute de patte de résistance) | D43: D5 | E43: PONT DE FIL vers VIN DevKit | F43: 1 | G43: À acheter | H43: =INDEX(Prix!$C$5:$C$79,MATCH($A43,Prix!$A$5:$A$79,0)) -> — | I43: =IFERROR(INDEX(Prix!$G$5:$G$79,MATCH($A43,Prix!$A$5:$A$79,0)),"") -> 0 | J43: =IF(I43="","",F43*I43) -> 0 | K43: D5 = pont de fil (rev 0.2.2). Règle absolue : ne JAMAIS brancher l'USB du DevKit quand la carte est alimentée.
A44: TP_FIL | B44: 6. Connectique carte | C44: Points de test TP1-TP4 : boucle de fil (chute de patte) | D44: TP1, TP2, TP3, TP4 | E44: Point de test GND; Point de test +5V; Point de test +3V3_SW; Point de test +3V3 | F44: 4 | G44: À acheter | H44: =INDEX(Prix!$C$5:$C$79,MATCH($A44,Prix!$A$5:$A$79,0)) -> — | I44: =IFERROR(INDEX(Prix!$G$5:$G$79,MATCH($A44,Prix!$A$5:$A$79,0)),"") -> 0 | J44: =IF(I44="","",F44*I44) -> 0
A45: DHT11 | B45: 7. Capteurs et actionneurs | C45: Capteur température/humidité DHT11 | D45: hors carte | E45: Température/humidité de la serre sur J10 | F45: 1 | G45: À acheter | H45: =INDEX(Prix!$C$5:$C$79,MATCH($A45,Prix!$A$5:$A$79,0)) -> Shop4Makers | I45: =IFERROR(INDEX(Prix!$G$5:$G$79,MATCH($A45,Prix!$A$5:$A$79,0)),"") -> 16.2 | J45: =IF(I45="","",F45*I45) -> 16.2 | K45: BME280 en option (détecté automatiquement). | L45: lien
A46: BME280 | B46: 7. Capteurs et actionneurs | C46: Module BME280 I2C (température, humidité, pression) | D46: hors carte | E46: Remplace le DHT11 (0x76, I2C J21) | F46: 1 | G46: Option | H46: =INDEX(Prix!$C$5:$C$79,MATCH($A46,Prix!$A$5:$A$79,0)) -> Shop4Makers | I46: =IFERROR(INDEX(Prix!$G$5:$G$79,MATCH($A46,Prix!$A$5:$A$79,0)),"") -> 85 | J46: =IF(I46="","",F46*I46) -> 85 | K46: Ajoute la pression atmosphérique. | L46: lien
A47: LDR | B47: 7. Capteurs et actionneurs | C47: Photorésistance LDR GL5528 | D47: hors carte | E47: Luminosité de la serre sur J12 | F47: 1 | G47: À acheter | H47: =INDEX(Prix!$C$5:$C$79,MATCH($A47,Prix!$A$5:$A$79,0)) -> Moussasoft | I47: =IFERROR(INDEX(Prix!$G$5:$G$79,MATCH($A47,Prix!$A$5:$A$79,0)),"") -> 2 | J47: =IF(I47="","",F47*I47) -> 2 | K47: R27 posé, JP20 FERMÉ. | L47: lien
A48: SOL_CAPA | B48: 7. Capteurs et actionneurs | C48: Capteur d'humidité du sol capacitif v1.2 (sortie AO) | D48: hors carte | E48: Humidité du sol 1 à 4 sur J31-J34 | F48: 4 | G48: À acheter | H48: =INDEX(Prix!$C$5:$C$79,MATCH($A48,Prix!$A$5:$A$79,0)) -> Shop4Makers | I48: =IFERROR(INDEX(Prix!$G$5:$G$79,MATCH($A48,Prix!$A$5:$A$79,0)),"") -> 35 | J48: =IF(I48="","",F48*I48) -> 140 | K48: JP16-JP19 OUVERTS, R43-R46 NON posés. Capacitif v1.2 : ne rouille pas comme les sondes résistives. | L48: lien
A49: OLED | B49: 7. Capteurs et actionneurs | C49: Écran OLED 0,96" SSD1306 I2C 128×64 | D49: hors carte | E49: Affichage local sur J13 | F49: 1 | G49: À acheter | H49: =INDEX(Prix!$C$5:$C$79,MATCH($A49,Prix!$A$5:$A$79,0)) -> Shop4Makers | I49: =IFERROR(INDEX(Prix!$G$5:$G$79,MATCH($A49,Prix!$A$5:$A$79,0)),"") -> 70 | J49: =IF(I49="","",F49*I49) -> 70 | L49: lien
A50: 1N4007_EXT | B50: 7. Capteurs et actionneurs | C50: Diode 1N4007 aux bornes d'une pompe DC (roue libre) | D50: hors carte | E50: Roue libre aux bornes de la pompe si pompe DC | F50: 1 | G50: À acheter | H50: =INDEX(Prix!$C$5:$C$79,MATCH($A50,Prix!$A$5:$A$79,0)) -> Shop4Makers | I50: =IFERROR(INDEX(Prix!$G$5:$G$79,MATCH($A50,Prix!$A$5:$A$79,0)),"") -> 0.9 | J50: =IF(I50="","",F50*I50) -> 0.9 | K50: Cathode côté +. Inutile pour une pompe 230 V. | L50: lien
A51: CHARGEUR_5V | B51: 8. Alimentation hors carte | C51: Chargeur 5 V 2 A (ou 3 A) de marque | D51: hors carte | E51: Alimentation de la carte | F51: 1 | G51: À acheter | H51: =INDEX(Prix!$C$5:$C$79,MATCH($A51,Prix!$A$5:$A$79,0)) -> Megma | I51: =IFERROR(INDEX(Prix!$G$5:$G$79,MATCH($A51,Prix!$A$5:$A$79,0)),"") -> 50 | J51: =IF(I51="","",F51*I51) -> 50 | K51: 5 V 2 A minimum, de marque (≥ 4,8 V sur J1/J2 sous charge). | L51: lien
A52: CABLE_USB_JACK | B52: 8. Alimentation hors carte | C52: Cordon USB-A → jack 5,5×2,1 court | D52: hors carte | E52: Du chargeur au jack J2 | F52: 1 | G52: À acheter | H52: =INDEX(Prix!$C$5:$C$79,MATCH($A52,Prix!$A$5:$A$79,0)) -> Moussasoft | I52: =IFERROR(INDEX(Prix!$G$5:$G$79,MATCH($A52,Prix!$A$5:$A$79,0)),"") -> 35 | J52: =IF(I52="","",F52*I52) -> 35 | K52: Le plus COURT et le plus épais possible (≥ 0,5 mm²). | L52: lien
A53: VIS_M3 | B53: 9. Mécanique et câblage | C53: Vis M3 nylon + écrou (H1-H7 ; nylon OBLIGATOIRE en H1/H5) | D53: H1, H2, H3, H4, H5, H6, H7 | E53: Trou de fixation M3 | F53: 7 | G53: À acheter | H53: =INDEX(Prix!$C$5:$C$79,MATCH($A53,Prix!$A$5:$A$79,0)) -> Dsindustrie | I53: =IFERROR(INDEX(Prix!$G$5:$G$79,MATCH($A53,Prix!$A$5:$A$79,0)),"") -> 2 | J53: =IF(I53="","",F53*I53) -> 14 | L53: lien
A54: ENTRETOISE_M3 | B54: 9. Mécanique et câblage | C54: Entretoise M3 nylon ~10 mm | D54: H1-H7 | E54: Entretoises de fixation de la carte | F54: 7 | G54: À acheter | H54: =INDEX(Prix!$C$5:$C$79,MATCH($A54,Prix!$A$5:$A$79,0)) -> Dsindustrie | I54: =IFERROR(INDEX(Prix!$G$5:$G$79,MATCH($A54,Prix!$A$5:$A$79,0)),"") -> 0 | J54: =IF(I54="","",F54*I54) -> 0
A55: BOITIER | B55: 9. Mécanique et câblage | C55: Boîtier étanche IP65 (~200×150 mm ou plus) | D55: hors carte | E55: Boîtier étanche (serre humide) | F55: 1 | G55: À acheter | H55: =INDEX(Prix!$C$5:$C$79,MATCH($A55,Prix!$A$5:$A$79,0)) -> EnergyMarket | I55: =IFERROR(INDEX(Prix!$G$5:$G$79,MATCH($A55,Prix!$A$5:$A$79,0)),"") -> 352 | J55: =IF(I55="","",F55*I55) -> 352 | L55: lien
A56: PRESSE_ETOUPE | B56: 9. Mécanique et câblage | C56: Presse-étoupe PG7 / PG9 | D56: hors carte | E56: Passage des câbles sondes / pompe / alim | F56: 6 | G56: À acheter | H56: =INDEX(Prix!$C$5:$C$79,MATCH($A56,Prix!$A$5:$A$79,0)) -> Quincaillerie | I56: =IFERROR(INDEX(Prix!$G$5:$G$79,MATCH($A56,Prix!$A$5:$A$79,0)),"") | J56: =IF(I56="","",F56*I56)
A57: FIL_05 | B57: 9. Mécanique et câblage | C57: Fil souple 0,5 mm² (mètre) | D57: hors carte | E57: Câblage des capteurs (au mètre) | F57: 5 | G57: À acheter | H57: =INDEX(Prix!$C$5:$C$79,MATCH($A57,Prix!$A$5:$A$79,0)) -> ElectroDelivery | I57: =IFERROR(INDEX(Prix!$G$5:$G$79,MATCH($A57,Prix!$A$5:$A$79,0)),"") -> 3.5 | J57: =IF(I57="","",F57*I57) -> 17.5 | K57: Souple 0,25–0,5 mm² ; embouts sur chaque fil. | L57: lien

Sheet ffp5cs 230V
A1: ffp5cs — aquaponie secteur 230 V (Hi-Link)
A2: Carte n3-universal rev 0.2.2 — composants à poser et à acheter pour UNE unité. Prix du 18/10/2026 (feuille Prix). Les quantités (bleu) sont modifiables ; l'achat groupé arrondi aux lots est dans « Global ».
A4: Consignes de pose de ce profil
B5: • 230 V → J27 (1 = N, 2 = L) → F1 T1A + RV1 → Hi-Link PS1 → +5V. Boîtier isolant fermé, différentiel 30 mA, supervision adulte.
B6: • H1 et H5 : vis NYLON obligatoires. JP1 FERMÉ 1-2 (rail permanent) ; JP13-JP15 FERMÉS (ponts écho) ; JP20 FERMÉ ; JP5-JP10 sans cavalier (AUTO).
B7: • J1 seulement pour les essais sur table SANS secteur : jamais J1 et le Hi-Link en même temps.
B8: • Flash USB : carte HORS secteur et JP1 ôté (le pull-up 1-Wire sur GPIO2 bloque le bootloader). Sinon OTA.
B9: • NE PAS poser : J29-J34, R43-R47, section 12 V (J26, Q11, D8, D9, R40, C5, J36, J37).
C11: Total à acheter, une unité (DH) | J11: =SUMIFS(J18:J66,G18:G66,"À acheter") -> 1199.6
C12: Options (DH) | J12: =SUMIFS(J18:J66,G18:G66,"Option") -> 18
C13: Déjà possédé — valeur indicative (DH) | J13: =SUMIFS(J18:J66,G18:G66,"Déjà possédé") -> 0
C14: Articles à acheter sans prix en ligne (import LCSC, quincaillerie, PCB) | J14: =SUMPRODUCT((G18:G66="À acheter")*(I18:I66="")) -> 3
A17: ID | B17: Catégorie | C17: Article | D17: Réf. carte | E17: Rôle | F17: Qté | G17: Statut | H17: Fournisseur | I17: Prix unitaire (DH) | J17: Coût (DH) | K17: Remarques | L17: Lien
A18: PCB | B18: 1. Carte et cerveau | C18: Circuit imprimé n3-universal rev 0.2.2 (JLCPCB, 2 oz) | D18: — | E18: Circuit imprimé n3-universal rev 0.2.2 | F18: 1 | G18: À acheter | H18: =INDEX(Prix!$C$5:$C$79,MATCH($A18,Prix!$A$5:$A$79,0)) -> JLCPCB | I18: =IFERROR(INDEX(Prix!$G$5:$G$79,MATCH($A18,Prix!$A$5:$A$79,0)),"") | J18: =IF(I18="","",F18*I18) | L18: lien
A19: ESP32_DEVKIT | B19: 1. Carte et cerveau | C19: ESP32 DevKit V1 30 broches (WROOM-32) | D19: A1 | E19: Module ESP32-WROOM-32 DevKit V1 30 broches, sur 2 supports 1x15 | F19: 1 | G19: À acheter | H19: =INDEX(Prix!$C$5:$C$79,MATCH($A19,Prix!$A$5:$A$79,0)) -> Shop4Makers | I19: =IFERROR(INDEX(Prix!$G$5:$G$79,MATCH($A19,Prix!$A$5:$A$79,0)),"") -> 113 | J19: =IF(I19="","",F19*I19) -> 113 | K19: Enfiché sur ses supports, jamais soudé. Vérifier l'écart des rangées (25,4 ou 27,94 mm : support droit sur A ou A'). | L19: lien
A20: R_220 | B20: 2. Résistances | C20: Résistance 220 Ω 1/4 W | D20: R20, R21 | E20: Série signal servo gros; Série signal servo petits | F20: 2 | G20: À acheter | H20: =INDEX(Prix!$C$5:$C$79,MATCH($A20,Prix!$A$5:$A$79,0)) -> MicroPlanet | I20: =IFERROR(INDEX(Prix!$G$5:$G$79,MATCH($A20,Prix!$A$5:$A$79,0)),"") -> 0.3 | J20: =IF(I20="","",F20*I20) -> 0.6 | L20: lien
A21: R_1k | B21: 2. Résistances | C21: Résistance 1 kΩ 1/4 W | D21: R1, R2, R3, R4, R9, R10, R11, R12, R13, R14, R15, R16, R28, R30, … | E21: Résistance base transistor; Résistance LED témoin; Résistance LED présence 5V; Série écho HC-SR04 AQUA ; … | F21: 23 | G21: À acheter | H21: =INDEX(Prix!$C$5:$C$79,MATCH($A21,Prix!$A$5:$A$79,0)) -> MicroPlanet | I21: =IFERROR(INDEX(Prix!$G$5:$G$79,MATCH($A21,Prix!$A$5:$A$79,0)),"") -> 0.3 | J21: =IF(I21="","",F21*I21) -> 6.9 | L21: lien
A22: R_2k | B22: 2. Résistances | C22: Résistance 2 kΩ 1/4 W (2,2 kΩ convient) | D22: R17, R18, R19 | E22: Pont diviseur écho AQUA; Pont diviseur écho TANK; Pont diviseur écho POTA | F22: 3 | G22: À acheter | H22: =INDEX(Prix!$C$5:$C$79,MATCH($A22,Prix!$A$5:$A$79,0)) -> MicroPlanet | I22: =IFERROR(INDEX(Prix!$G$5:$G$79,MATCH($A22,Prix!$A$5:$A$79,0)),"") -> 0.3 | J22: =IF(I22="","",F22*I22) -> 0.9 | K22: R17-R19 : ponts écho HC-SR04, uniquement sur ffp5cs. | L22: lien
A23: R_4.7k | B23: 2. Résistances | C23: Résistance 4,7 kΩ 1/4 W | D23: R24, R25, R26 | E23: Pull-up bus 1-Wire DS18B20; Pull-up I2C SDA; Pull-up I2C SCL | F23: 3 | G23: À acheter | H23: =INDEX(Prix!$C$5:$C$79,MATCH($A23,Prix!$A$5:$A$79,0)) -> MicroPlanet | I23: =IFERROR(INDEX(Prix!$G$5:$G$79,MATCH($A23,Prix!$A$5:$A$79,0)),"") -> 0.3 | J23: =IF(I23="","",F23*I23) -> 0.9 | L23: lien
A24: R_10k | B24: 2. Résistances | C24: Résistance 10 kΩ 1/4 W | D24: R5, R6, R7, R8, R23, R27, R29, R32, R48 | E24: Pull-down base; Pull-up data DHT11; Bas de pont LDR sur ADC_E; Pull-down base Q8 | F24: 9 | G24: À acheter | H24: =INDEX(Prix!$C$5:$C$79,MATCH($A24,Prix!$A$5:$A$79,0)) -> MicroPlanet | I24: =IFERROR(INDEX(Prix!$G$5:$G$79,MATCH($A24,Prix!$A$5:$A$79,0)),"") -> 0.3 | J24: =IF(I24="","",F24*I24) -> 2.7 | L24: lien
A25: R_100k | B25: 2. Résistances | C25: Résistance 100 kΩ 1/4 W | D25: R35, R57 | E25: Pull-up grille P-MOSFET vers +5V; Grille de Q12 vers GND | F25: 2 | G25: À acheter | H25: =INDEX(Prix!$C$5:$C$79,MATCH($A25,Prix!$A$5:$A$79,0)) -> MicroPlanet | I25: =IFERROR(INDEX(Prix!$G$5:$G$79,MATCH($A25,Prix!$A$5:$A$79,0)),"") -> 0.3 | J25: =IF(I25="","",F25*I25) -> 0.6 | L25: lien
A26: C_100n | B26: 3. Condensateurs | C26: Condensateur céramique 100 nF (pas 5 mm) | D26: C3, C4, C10 | E26: Découplage 3V3 capteurs; Découplage 3V3 I2C; Filtre ADC_E | F26: 3 | G26: À acheter | H26: =INDEX(Prix!$C$5:$C$79,MATCH($A26,Prix!$A$5:$A$79,0)) -> A2itronic | I26: =IFERROR(INDEX(Prix!$G$5:$G$79,MATCH($A26,Prix!$A$5:$A$79,0)),"") -> 0.5 | J26: =IF(I26="","",F26*I26) -> 1.5 | L26: lien
A27: C_10u25 | B27: 3. Condensateurs | C27: Condensateur électrolytique 10 µF 25 V | D27: C11 | E27: Entrée LDO | F27: 1 | G27: À acheter | H27: =INDEX(Prix!$C$5:$C$79,MATCH($A27,Prix!$A$5:$A$79,0)) -> A2itronic | I27: =IFERROR(INDEX(Prix!$G$5:$G$79,MATCH($A27,Prix!$A$5:$A$79,0)),"") -> 1 | J27: =IF(I27="","",F27*I27) -> 1 | L27: lien
A28: C_100u16 | B28: 3. Condensateurs | C28: Condensateur électrolytique 100 µF 16 V | D28: C12 | E28: Sortie LDO | F28: 1 | G28: À acheter | H28: =INDEX(Prix!$C$5:$C$79,MATCH($A28,Prix!$A$5:$A$79,0)) -> A2itronic | I28: =IFERROR(INDEX(Prix!$G$5:$G$79,MATCH($A28,Prix!$A$5:$A$79,0)),"") -> 1 | J28: =IF(I28="","",F28*I28) -> 1 | L28: lien
A29: C_470u16 | B29: 3. Condensateurs | C29: Condensateur électrolytique 470 µF 16 V (25 V convient) | D29: C2 | E29: Réservoir du rail 5 V commuté LDO_IN côté servos | F29: 1 | G29: À acheter | H29: =INDEX(Prix!$C$5:$C$79,MATCH($A29,Prix!$A$5:$A$79,0)) -> A2itronic | I29: =IFERROR(INDEX(Prix!$G$5:$G$79,MATCH($A29,Prix!$A$5:$A$79,0)),"") -> 2 | J29: =IF(I29="","",F29*I29) -> 2 | L29: lien
A30: C_1000u16 | B30: 3. Condensateurs | C30: Condensateur électrolytique 1000 µF 16 V (diam. 10 mm) | D30: C1 | E30: Réservoir rail 5V | F30: 1 | G30: À acheter | H30: =INDEX(Prix!$C$5:$C$79,MATCH($A30,Prix!$A$5:$A$79,0)) -> A2itronic | I30: =IFERROR(INDEX(Prix!$G$5:$G$79,MATCH($A30,Prix!$A$5:$A$79,0)),"") -> 3 | J30: =IF(I30="","",F30*I30) -> 3 | L30: lien
A31: 1N4007 | B31: 4. Semi-conducteurs | C31: Diode 1N4007 (roue libre des bobines de relais) | D31: D1, D2, D3, D4, D6, D7 | E31: Diode de roue libre bobine | F31: 6 | G31: À acheter | H31: =INDEX(Prix!$C$5:$C$79,MATCH($A31,Prix!$A$5:$A$79,0)) -> Shop4Makers | I31: =IFERROR(INDEX(Prix!$G$5:$G$79,MATCH($A31,Prix!$A$5:$A$79,0)),"") -> 0.9 | J31: =IF(I31="","",F31*I31) -> 5.4 | L31: lien
A32: TVS_6V8 | B32: 4. Semi-conducteurs | C32: Diode TVS 1.5KE6.8A (ou P6KE6.8A) | D32: D12 | E32: TVS 6,8V sur le rail +5V : surtension / inversion résiduelle | F32: 1 | G32: À acheter | H32: =INDEX(Prix!$C$5:$C$79,MATCH($A32,Prix!$A$5:$A$79,0)) -> LCSC | I32: =IFERROR(INDEX(Prix!$G$5:$G$79,MATCH($A32,Prix!$A$5:$A$79,0)),"") | J32: =IF(I32="","",F32*I32) | K32: Protège le rail 5 V. Commander tôt chez LCSC (stock faible). | L32: lien
A33: BC337 | B33: 4. Semi-conducteurs | C33: Transistor NPN BC337-40 (TO-92) | D33: Q1, Q2, Q3, Q4, Q5, Q6, Q8 | E33: Transistor NPN commande relais; Driver gate | F33: 7 | G33: À acheter | H33: =INDEX(Prix!$C$5:$C$79,MATCH($A33,Prix!$A$5:$A$79,0)) -> A2itronic | I33: =IFERROR(INDEX(Prix!$G$5:$G$79,MATCH($A33,Prix!$A$5:$A$79,0)),"") -> 1 | J33: =IF(I33="","",F33*I33) -> 7 | K33: Brochage C-B-E sérigraphié. | L33: lien
A34: IRF4905 | B34: 4. Semi-conducteurs | C34: MOSFET P IRF4905 (TO-220) | D34: Q7, Q12 | E34: P-MOSFET commutation 5V du LDO capteurs; Anti-inversion entrée 5V (P-MOSFET 55V, VGS = -5V | F34: 2 | G34: À acheter | H34: =INDEX(Prix!$C$5:$C$79,MATCH($A34,Prix!$A$5:$A$79,0)) -> A2itronic | I34: =IFERROR(INDEX(Prix!$G$5:$G$79,MATCH($A34,Prix!$A$5:$A$79,0)),"") -> 10 | J34: =IF(I34="","",F34*I34) -> 20 | K34: Respecter la sérigraphie G-D-S de chaque MOSFET. | L34: lien
A35: LD1117 | B35: 4. Semi-conducteurs | C35: Régulateur LD1117V33 TO-220 (1=GND 2=OUT 3=IN) | D35: U1 | E35: Régulateur 3,3V 800mA du rail capteurs (1=GND 2=OUT 3=IN | F35: 1 | G35: À acheter | H35: =INDEX(Prix!$C$5:$C$79,MATCH($A35,Prix!$A$5:$A$79,0)) -> Megma | I35: =IFERROR(INDEX(Prix!$G$5:$G$79,MATCH($A35,Prix!$A$5:$A$79,0)),"") -> 7.5 | J35: =IF(I35="","",F35*I35) -> 7.5 | K35: Ce n'est pas un 78xx : 1=GND 2=OUT 3=IN (sérigraphié). | L35: lien
A36: LED_R | B36: 4. Semi-conducteurs | C36: LED 5 mm rouge | D36: LED1, LED2, LED3, LED4, LED6, LED7 | E36: LED témoin relais ON | F36: 6 | G36: À acheter | H36: =INDEX(Prix!$C$5:$C$79,MATCH($A36,Prix!$A$5:$A$79,0)) -> Moussasoft | I36: =IFERROR(INDEX(Prix!$G$5:$G$79,MATCH($A36,Prix!$A$5:$A$79,0)),"") -> 1 | J36: =IF(I36="","",F36*I36) -> 6 | L36: lien
A37: LED_V | B37: 4. Semi-conducteurs | C37: LED 5 mm verte | D37: LED5 | E37: LED présence 5V | F37: 1 | G37: À acheter | H37: =INDEX(Prix!$C$5:$C$79,MATCH($A37,Prix!$A$5:$A$79,0)) -> Shop4Makers | I37: =IFERROR(INDEX(Prix!$G$5:$G$79,MATCH($A37,Prix!$A$5:$A$79,0)),"") -> 0.9 | J37: =IF(I37="","",F37*I37) -> 0.9 | K37: LED5 posée (présence 5 V). | L37: lien
A38: SRD05 | B38: 5. Relais et protection secteur | C38: Relais Songle SRD-05VDC-SL-C (composant seul, pas le module) | D38: K1, K2, K3, K4, K5, K6 | E38: Relais 5V SPDT Songle/Sanyou SRD Form C | F38: 6 | G38: À acheter | H38: =INDEX(Prix!$C$5:$C$79,MATCH($A38,Prix!$A$5:$A$79,0)) -> Moussasoft | I38: =IFERROR(INDEX(Prix!$G$5:$G$79,MATCH($A38,Prix!$A$5:$A$79,0)),"") -> 18 | J38: =IF(I38="","",F38*I38) -> 108 | L38: lien
A39: VARISTANCE | B39: 5. Relais et protection secteur | C39: Varistance 14D471K (ou 10D471K), pas 7,5 mm | D39: RV1 | E39: Varistance 300VAC transitoires secteur | F39: 1 | G39: À acheter | H39: =INDEX(Prix!$C$5:$C$79,MATCH($A39,Prix!$A$5:$A$79,0)) -> MicroPlanet | I39: =IFERROR(INDEX(Prix!$G$5:$G$79,MATCH($A39,Prix!$A$5:$A$79,0)),"") -> 4 | J39: =IF(I39="","",F39*I39) -> 4 | L39: lien
A40: PORTEFUS_5x20 | B40: 5. Relais et protection secteur | C40: Porte-fusible 5×20 pour circuit imprimé, à capot (pas 22–22,6 mm) | D40: F1 | E40: Fusible entrée secteur du module alim | F40: 1 | G40: À acheter | H40: =INDEX(Prix!$C$5:$C$79,MATCH($A40,Prix!$A$5:$A$79,0)) -> Moussasoft | I40: =IFERROR(INDEX(Prix!$G$5:$G$79,MATCH($A40,Prix!$A$5:$A$79,0)),"") -> 4 | J40: =IF(I40="","",F40*I40) -> 4 | L40: lien
A41: FUS_T1A | B41: 5. Relais et protection secteur | C41: Fusible verre 5×20 temporisé T1A | D41: hors carte | E41: Cartouche du porte-fusible F1 (1 posée + 2 de rechange) | F41: 3 | G41: À acheter | H41: =INDEX(Prix!$C$5:$C$79,MATCH($A41,Prix!$A$5:$A$79,0)) -> Megma | I41: =IFERROR(INDEX(Prix!$G$5:$G$79,MATCH($A41,Prix!$A$5:$A$79,0)),"") -> 0.5 | J41: =IF(I41="","",F41*I41) -> 1.5 | K41: Temporisé (T), pas rapide (F). | L41: lien
A42: HLK20M05 | B42: 5. Relais et protection secteur | C42: Module Hi-Link HLK-20M05 (230 V → 5 V 3,6 A) | D42: PS1 | E42: Module AC-DC 230V->5V 3,6A | F42: 1 | G42: À acheter | H42: =INDEX(Prix!$C$5:$C$79,MATCH($A42,Prix!$A$5:$A$79,0)) -> Shop4Makers | I42: =IFERROR(INDEX(Prix!$G$5:$G$79,MATCH($A42,Prix!$A$5:$A$79,0)),"") -> 90 | J42: =IF(I42="","",F42*I42) -> 90 | K42: Zone 230 V : montage et raccordement sous supervision adulte. | L42: lien
A43: BORNIER_2P | B43: 6. Connectique carte | C43: Bornier à vis 2 pôles pas 5,08 (KF301-2P) | D43: J1, J12, J18, J19, J27 | E43: Entrée 5V alternative; LDR déportée entre 3V3 et l'ADC; Distribution 5V; Distribution 3V3 capteurs ; … | F43: 5 | G43: À acheter | H43: =INDEX(Prix!$C$5:$C$79,MATCH($A43,Prix!$A$5:$A$79,0)) -> MicroPlanet | I43: =IFERROR(INDEX(Prix!$G$5:$G$79,MATCH($A43,Prix!$A$5:$A$79,0)),"") -> 2 | J43: =IF(I43="","",F43*I43) -> 10 | K43: J1 seulement pour les essais sur table SANS secteur (jamais les deux en même temps). | L43: lien
A44: BORNIER_3P | B44: 6. Connectique carte | C44: Bornier à vis 3 pôles pas 5,08 (KF301-3P) | D44: J3, J4, J5, J6, J10, J11, J23, J24 | E44: Bornier charge 230V; DHT11/DHT22; Sonde DS18B20 étanche | F44: 8 | G44: À acheter | H44: =INDEX(Prix!$C$5:$C$79,MATCH($A44,Prix!$A$5:$A$79,0)) -> MicroPlanet | I44: =IFERROR(INDEX(Prix!$G$5:$G$79,MATCH($A44,Prix!$A$5:$A$79,0)),"") -> 3 | J44: =IF(I44="","",F44*I44) -> 24 | L44: lien
A45: BORNIER_4P | B45: 6. Connectique carte | C45: Bornier à vis 4 pôles pas 5,08 (ou 2+2 emboîtés) | D45: J7, J8, J9 | E45: HC-SR04 AQUA; HC-SR04 TANK; HC-SR04 POTA | F45: 3 | G45: À acheter | H45: =INDEX(Prix!$C$5:$C$79,MATCH($A45,Prix!$A$5:$A$79,0)) -> MicroPlanet | I45: =IFERROR(INDEX(Prix!$G$5:$G$79,MATCH($A45,Prix!$A$5:$A$79,0)),"") -> 5 | J45: =IF(I45="","",F45*I45) -> 15 | L45: lien
A46: BARRETTE_F | B46: 6. Connectique carte | C46: Barrette femelle sécable 1×40 pas 2,54 | D46: A1 (2×15), J13, J14 | E46: Supports du DevKit (jamais soudé); OLED SSD1306 128x64 I2C 0x3C; Extension I2C | F46: 2 | G46: À acheter | H46: =INDEX(Prix!$C$5:$C$79,MATCH($A46,Prix!$A$5:$A$79,0)) -> Moussasoft | I46: =IFERROR(INDEX(Prix!$G$5:$G$79,MATCH($A46,Prix!$A$5:$A$79,0)),"") -> 5 | J46: =IF(I46="","",F46*I46) -> 10 | K46: 38 broches femelles utilisées (+ pertes de coupe). | L46: lien
A47: BARRETTE_M | B47: 6. Connectique carte | C47: Barrette mâle sécable 1×40 pas 2,54 | D47: J15, J16, J17, J20, J38, JP1, JP5, JP6, JP7, JP8, JP9, JP10, JP13, JP14, … | E47: Servo GROS; Servo PETITS; Header service; Rail Dupont ; … | F47: 2 | G47: À acheter | H47: =INDEX(Prix!$C$5:$C$79,MATCH($A47,Prix!$A$5:$A$79,0)) -> Moussasoft | I47: =IFERROR(INDEX(Prix!$G$5:$G$79,MATCH($A47,Prix!$A$5:$A$79,0)),"") -> 4 | J47: =IF(I47="","",F47*I47) -> 8 | K47: 65 broches mâles utilisées (+ pertes de coupe). | L47: lien
A48: CAVALIER | B48: 6. Connectique carte | C48: Cavalier (jumper) 2,54 mm | D48: JP… | E48: Cavaliers de configuration du profil (+2 de rechange) | F48: 7 | G48: À acheter | H48: =INDEX(Prix!$C$5:$C$79,MATCH($A48,Prix!$A$5:$A$79,0)) -> Shop4Makers | I48: =IFERROR(INDEX(Prix!$G$5:$G$79,MATCH($A48,Prix!$A$5:$A$79,0)),"") -> 0.5 | J48: =IF(I48="","",F48*I48) -> 3.5 | K48: Cavaliers posés : JP1 FERMÉ 1-2, JP13-JP15 et JP20 FERMÉS ; JP5-JP10 SANS cavalier (AUTO). | L48: lien
A49: FIL | B49: 6. Connectique carte | C49: Pont de fil à la place de D5 (chute de patte de résistance) | D49: D5 | E49: PONT DE FIL vers VIN DevKit | F49: 1 | G49: À acheter | H49: =INDEX(Prix!$C$5:$C$79,MATCH($A49,Prix!$A$5:$A$79,0)) -> — | I49: =IFERROR(INDEX(Prix!$G$5:$G$79,MATCH($A49,Prix!$A$5:$A$79,0)),"") -> 0 | J49: =IF(I49="","",F49*I49) -> 0 | K49: D5 = pont de fil (rev 0.2.2). Règle absolue : ne JAMAIS brancher l'USB du DevKit quand la carte est alimentée.
A50: TP_FIL | B50: 6. Connectique carte | C50: Points de test TP1-TP4 : boucle de fil (chute de patte) | D50: TP1, TP2, TP3, TP4 | E50: Point de test GND; Point de test +5V; Point de test +3V3_SW; Point de test +3V3 | F50: 4 | G50: À acheter | H50: =INDEX(Prix!$C$5:$C$79,MATCH($A50,Prix!$A$5:$A$79,0)) -> — | I50: =IFERROR(INDEX(Prix!$G$5:$G$79,MATCH($A50,Prix!$A$5:$A$79,0)),"") -> 0 | J50: =IF(I50="","",F50*I50) -> 0
A51: DHT11 | B51: 7. Capteurs et actionneurs | C51: Capteur température/humidité DHT11 | D51: hors carte | E51: Température/humidité de l'air sur J10 | F51: 1 | G51: À acheter | H51: =INDEX(Prix!$C$5:$C$79,MATCH($A51,Prix!$A$5:$A$79,0)) -> Shop4Makers | I51: =IFERROR(INDEX(Prix!$G$5:$G$79,MATCH($A51,Prix!$A$5:$A$79,0)),"") -> 16.2 | J51: =IF(I51="","",F51*I51) -> 16.2 | K51: DHT22 possible (flag -DUSE_DHT22). | L51: lien
A52: DS18B20 | B52: 7. Capteurs et actionneurs | C52: Sonde DS18B20 étanche (câble 1 m) | D52: hors carte | E52: Température de l'eau (régule le chauffage) sur J11 | F52: 1 | G52: À acheter | H52: =INDEX(Prix!$C$5:$C$79,MATCH($A52,Prix!$A$5:$A$79,0)) -> A2itronic | I52: =IFERROR(INDEX(Prix!$G$5:$G$79,MATCH($A52,Prix!$A$5:$A$79,0)),"") -> 50 | J52: =IF(I52="","",F52*I52) -> 50 | K52: GPIO2 = broche de démarrage : ôter JP1 pour flasher par USB (carte HORS secteur). | L52: lien
A53: LDR | B53: 7. Capteurs et actionneurs | C53: Photorésistance LDR GL5528 | D53: hors carte | E53: Luminosité ambiante sur J12 | F53: 1 | G53: À acheter | H53: =INDEX(Prix!$C$5:$C$79,MATCH($A53,Prix!$A$5:$A$79,0)) -> Moussasoft | I53: =IFERROR(INDEX(Prix!$G$5:$G$79,MATCH($A53,Prix!$A$5:$A$79,0)),"") -> 2 | J53: =IF(I53="","",F53*I53) -> 2 | K53: R27 posé, JP20 FERMÉ. | L53: lien
A54: HCSR04 | B54: 7. Capteurs et actionneurs | C54: Capteur ultrason HC-SR04 | D54: hors carte | E54: Niveaux d'eau aquarium (J7), réservoir (J8), potager (J9) | F54: 3 | G54: À acheter | H54: =INDEX(Prix!$C$5:$C$79,MATCH($A54,Prix!$A$5:$A$79,0)) -> Moussasoft | I54: =IFERROR(INDEX(Prix!$G$5:$G$79,MATCH($A54,Prix!$A$5:$A$79,0)),"") -> 25 | J54: =IF(I54="","",F54*I54) -> 75 | K54: JP13-JP15 FERMÉS + R17-R19 posés (écho 5 V ramené à 3,3 V) : OBLIGATOIRE. | L54: lien
A55: SG90 | B55: 7. Capteurs et actionneurs | C55: Servomoteur SG90 | D55: hors carte | E55: Nourrisseurs gros (J15) et petits poissons (J16) | F55: 2 | G55: À acheter | H55: =INDEX(Prix!$C$5:$C$79,MATCH($A55,Prix!$A$5:$A$79,0)) -> Moussasoft | I55: =IFERROR(INDEX(Prix!$G$5:$G$79,MATCH($A55,Prix!$A$5:$A$79,0)),"") -> 30 | J55: =IF(I55="","",F55*I55) -> 60 | K55: JP1 fermé : alimentés en permanence. | L55: lien
A56: OLED | B56: 7. Capteurs et actionneurs | C56: Écran OLED 0,96" SSD1306 I2C 128×64 | D56: hors carte | E56: Affichage local sur J13 | F56: 1 | G56: À acheter | H56: =INDEX(Prix!$C$5:$C$79,MATCH($A56,Prix!$A$5:$A$79,0)) -> Shop4Makers | I56: =IFERROR(INDEX(Prix!$G$5:$G$79,MATCH($A56,Prix!$A$5:$A$79,0)),"") -> 70 | J56: =IF(I56="","",F56*I56) -> 70 | L56: lien
A57: DS3231 | B57: 7. Capteurs et actionneurs | C57: Module horloge RTC DS3231 (ZS-042) | D57: hors carte | E57: Horloge hors ligne sur J14 | F57: 1 | G57: À acheter | H57: =INDEX(Prix!$C$5:$C$79,MATCH($A57,Prix!$A$5:$A$79,0)) -> A2itronic | I57: =IFERROR(INDEX(Prix!$G$5:$G$79,MATCH($A57,Prix!$A$5:$A$79,0)),"") -> 29 | J57: =IF(I57="","",F57*I57) -> 29 | K57: Dessouder la résistance/diode de charge du module (pile non rechargeable). | L57: lien
A58: CR2032 | B58: 7. Capteurs et actionneurs | C58: Pile bouton CR2032 | D58: hors carte | E58: Pile du DS3231 | F58: 1 | G58: À acheter | H58: =INDEX(Prix!$C$5:$C$79,MATCH($A58,Prix!$A$5:$A$79,0)) -> Shop4Makers | I58: =IFERROR(INDEX(Prix!$G$5:$G$79,MATCH($A58,Prix!$A$5:$A$79,0)),"") -> 3 | J58: =IF(I58="","",F58*I58) -> 3 | L58: lien
A59: MICROSD | B59: 7. Capteurs et actionneurs | C59: Module lecteur microSD SPI 3,3 V direct | D59: hors carte | E59: Journal sur carte SD (J35) | F59: 1 | G59: Option | H59: =INDEX(Prix!$C$5:$C$79,MATCH($A59,Prix!$A$5:$A$79,0)) -> Moussasoft | I59: =IFERROR(INDEX(Prix!$G$5:$G$79,MATCH($A59,Prix!$A$5:$A$79,0)),"") -> 18 | J59: =IF(I59="","",F59*I59) -> 18 | K59: Seulement avec un ESP32-S3 (site A2) ou après efuse VDD_SDIO=3V3 sur WROOM. PAS de module Catalex. | L59: lien
A60: CORDON_SECTEUR | B60: 8. Alimentation hors carte | C60: Cordon secteur 2 fils avec fiche | D60: hors carte | E60: Arrivée 230 V sur J27 | F60: 1 | G60: À acheter | H60: =INDEX(Prix!$C$5:$C$79,MATCH($A60,Prix!$A$5:$A$79,0)) -> La-Librairie.ma | I60: =IFERROR(INDEX(Prix!$G$5:$G$79,MATCH($A60,Prix!$A$5:$A$79,0)),"") -> 12 | J60: =IF(I60="","",F60*I60) -> 12 | K60: Raccordement sous supervision adulte, boîtier fermé. | L60: lien
A61: VIS_M3 | B61: 9. Mécanique et câblage | C61: Vis M3 nylon + écrou (H1-H7 ; nylon OBLIGATOIRE en H1/H5) | D61: H1, H2, H3, H4, H5, H6, H7 | E61: Trou de fixation M3 | F61: 7 | G61: À acheter | H61: =INDEX(Prix!$C$5:$C$79,MATCH($A61,Prix!$A$5:$A$79,0)) -> Dsindustrie | I61: =IFERROR(INDEX(Prix!$G$5:$G$79,MATCH($A61,Prix!$A$5:$A$79,0)),"") -> 2 | J61: =IF(I61="","",F61*I61) -> 14 | K61: H1 et H5 : vis NYLON OBLIGATOIRES (230 V à < 5 mm). | L61: lien
A62: ENTRETOISE_M3 | B62: 9. Mécanique et câblage | C62: Entretoise M3 nylon ~10 mm | D62: H1-H7 | E62: Entretoises de fixation de la carte | F62: 7 | G62: À acheter | H62: =INDEX(Prix!$C$5:$C$79,MATCH($A62,Prix!$A$5:$A$79,0)) -> Dsindustrie | I62: =IFERROR(INDEX(Prix!$G$5:$G$79,MATCH($A62,Prix!$A$5:$A$79,0)),"") -> 0 | J62: =IF(I62="","",F62*I62) -> 0
A63: BOITIER | B63: 9. Mécanique et câblage | C63: Boîtier étanche IP65 (~200×150 mm ou plus) | D63: hors carte | E63: Boîtier isolant (classe II) OBLIGATOIRE | F63: 1 | G63: À acheter | H63: =INDEX(Prix!$C$5:$C$79,MATCH($A63,Prix!$A$5:$A$79,0)) -> EnergyMarket | I63: =IFERROR(INDEX(Prix!$G$5:$G$79,MATCH($A63,Prix!$A$5:$A$79,0)),"") -> 352 | J63: =IF(I63="","",F63*I63) -> 352 | K63: Plastique, pas de boîtier métallique (pas de terre sur la carte). | L63: lien
A64: PRESSE_ETOUPE | B64: 9. Mécanique et câblage | C64: Presse-étoupe PG7 / PG9 | D64: hors carte | E64: Passage cordon secteur, charges 230 V, sondes | F64: 8 | G64: À acheter | H64: =INDEX(Prix!$C$5:$C$79,MATCH($A64,Prix!$A$5:$A$79,0)) -> Quincaillerie | I64: =IFERROR(INDEX(Prix!$G$5:$G$79,MATCH($A64,Prix!$A$5:$A$79,0)),"") | J64: =IF(I64="","",F64*I64)
A65: FIL_05 | B65: 9. Mécanique et câblage | C65: Fil souple 0,5 mm² (mètre) | D65: hors carte | E65: Câblage des capteurs (au mètre) | F65: 5 | G65: À acheter | H65: =INDEX(Prix!$C$5:$C$79,MATCH($A65,Prix!$A$5:$A$79,0)) -> ElectroDelivery | I65: =IFERROR(INDEX(Prix!$G$5:$G$79,MATCH($A65,Prix!$A$5:$A$79,0)),"") -> 3.5 | J65: =IF(I65="","",F65*I65) -> 17.5 | K65: Souple 0,25–0,5 mm² ; embouts sur chaque fil. | L65: lien
A66: FIL_15 | B66: 9. Mécanique et câblage | C66: Fil souple 1,5 mm² (mètre) | D66: hors carte | E66: Câblage des charges 230 V (pompes, chauffage, lumière) | F66: 5 | G66: À acheter | H66: =INDEX(Prix!$C$5:$C$79,MATCH($A66,Prix!$A$5:$A$79,0)) -> ElectroDelivery | I66: =IFERROR(INDEX(Prix!$G$5:$G$79,MATCH($A66,Prix!$A$5:$A$79,0)),"") -> 8 | J66: =IF(I66="","",F66*I66) -> 40 | K66: Au mètre, 1,5 mm² souple + embouts. | L66: lien

Sheet ffp5cs 12V
A1: ffp5cs — aquaponie 12 V (AGM + PWM solaire)
A2: Carte n3-universal rev 0.2.2 — composants à poser et à acheter pour UNE unité. Prix du 18/10/2026 (feuille Prix). Les quantités (bleu) sont modifiables ; l'achat groupé arrondi aux lots est dans « Global ».
A4: Consignes de pose de ce profil
B5: • Batterie AGM (bornes batterie, pas la sortie « charge » du PWM) → fusible lame 7,5-10 A → J26 → Q11/D8/D9 → J36 → buck réglé 5,1 V → J37.
B6: • JP1 FERMÉ ; JP12 en 1-2 (18k) ; JP13-JP15 FERMÉS ; JP20 FERMÉ ; JP5-JP10 sans cavalier (AUTO).
B7: • Les pompes 12 V passent par les CONTACTS des relais, directement sur le bus ; diode de roue libre aux bornes de chaque pompe.
B8: • Relais collés = poste dominant (≈ 10 Wh/jour par pompe maintenue) : cycles de pompe et chauffage interdit sur batterie (firmware).
B9: • NE PAS poser : Hi-Link PS1, F1, RV1, J27, J29-J34, R43-R47.
C11: Total à acheter, une unité (DH) | J11: =SUMIFS(J18:J73,G18:G73,"À acheter") -> 1189.4
C12: Options (DH) | J12: =SUMIFS(J18:J73,G18:G73,"Option") -> 100
C13: Déjà possédé — valeur indicative (DH) | J13: =SUMIFS(J18:J73,G18:G73,"Déjà possédé") -> 968
C14: Articles à acheter sans prix en ligne (import LCSC, quincaillerie, PCB) | J14: =SUMPRODUCT((G18:G73="À acheter")*(I18:I73="")) -> 5
A17: ID | B17: Catégorie | C17: Article | D17: Réf. carte | E17: Rôle | F17: Qté | G17: Statut | H17: Fournisseur | I17: Prix unitaire (DH) | J17: Coût (DH) | K17: Remarques | L17: Lien
A18: PCB | B18: 1. Carte et cerveau | C18: Circuit imprimé n3-universal rev 0.2.2 (JLCPCB, 2 oz) | D18: — | E18: Circuit imprimé n3-universal rev 0.2.2 | F18: 1 | G18: À acheter | H18: =INDEX(Prix!$C$5:$C$79,MATCH($A18,Prix!$A$5:$A$79,0)) -> JLCPCB | I18: =IFERROR(INDEX(Prix!$G$5:$G$79,MATCH($A18,Prix!$A$5:$A$79,0)),"") | J18: =IF(I18="","",F18*I18) | L18: lien
A19: ESP32_DEVKIT | B19: 1. Carte et cerveau | C19: ESP32 DevKit V1 30 broches (WROOM-32) | D19: A1 | E19: Module ESP32-WROOM-32 DevKit V1 30 broches, sur 2 supports 1x15 | F19: 1 | G19: À acheter | H19: =INDEX(Prix!$C$5:$C$79,MATCH($A19,Prix!$A$5:$A$79,0)) -> Shop4Makers | I19: =IFERROR(INDEX(Prix!$G$5:$G$79,MATCH($A19,Prix!$A$5:$A$79,0)),"") -> 113 | J19: =IF(I19="","",F19*I19) -> 113 | K19: Enfiché sur ses supports, jamais soudé. Vérifier l'écart des rangées (25,4 ou 27,94 mm : support droit sur A ou A'). | L19: lien
A20: R_220 | B20: 2. Résistances | C20: Résistance 220 Ω 1/4 W | D20: R20, R21 | E20: Série signal servo gros; Série signal servo petits | F20: 2 | G20: À acheter | H20: =INDEX(Prix!$C$5:$C$79,MATCH($A20,Prix!$A$5:$A$79,0)) -> MicroPlanet | I20: =IFERROR(INDEX(Prix!$G$5:$G$79,MATCH($A20,Prix!$A$5:$A$79,0)),"") -> 0.3 | J20: =IF(I20="","",F20*I20) -> 0.6 | L20: lien
A21: R_1k | B21: 2. Résistances | C21: Résistance 1 kΩ 1/4 W | D21: R1, R2, R3, R4, R9, R10, R11, R12, R13, R14, R15, R16, R28, R30, … | E21: Résistance base transistor; Résistance LED témoin; Résistance LED présence 5V; Série écho HC-SR04 AQUA ; … | F21: 24 | G21: À acheter | H21: =INDEX(Prix!$C$5:$C$79,MATCH($A21,Prix!$A$5:$A$79,0)) -> MicroPlanet | I21: =IFERROR(INDEX(Prix!$G$5:$G$79,MATCH($A21,Prix!$A$5:$A$79,0)),"") -> 0.3 | J21: =IF(I21="","",F21*I21) -> 7.2 | L21: lien
A22: R_2k | B22: 2. Résistances | C22: Résistance 2 kΩ 1/4 W (2,2 kΩ convient) | D22: R17, R18, R19 | E22: Pont diviseur écho AQUA; Pont diviseur écho TANK; Pont diviseur écho POTA | F22: 3 | G22: À acheter | H22: =INDEX(Prix!$C$5:$C$79,MATCH($A22,Prix!$A$5:$A$79,0)) -> MicroPlanet | I22: =IFERROR(INDEX(Prix!$G$5:$G$79,MATCH($A22,Prix!$A$5:$A$79,0)),"") -> 0.3 | J22: =IF(I22="","",F22*I22) -> 0.9 | K22: R17-R19 : ponts écho HC-SR04, uniquement sur ffp5cs. | L22: lien
A23: R_4.7k | B23: 2. Résistances | C23: Résistance 4,7 kΩ 1/4 W | D23: R24, R25, R26 | E23: Pull-up bus 1-Wire DS18B20; Pull-up I2C SDA; Pull-up I2C SCL | F23: 3 | G23: À acheter | H23: =INDEX(Prix!$C$5:$C$79,MATCH($A23,Prix!$A$5:$A$79,0)) -> MicroPlanet | I23: =IFERROR(INDEX(Prix!$G$5:$G$79,MATCH($A23,Prix!$A$5:$A$79,0)),"") -> 0.3 | J23: =IF(I23="","",F23*I23) -> 0.9 | L23: lien
A24: R_10k | B24: 2. Résistances | C24: Résistance 10 kΩ 1/4 W | D24: R5, R6, R7, R8, R23, R27, R29, R32, R48 | E24: Pull-down base; Pull-up data DHT11; Bas de pont LDR sur ADC_E; Pull-down base Q8 | F24: 9 | G24: À acheter | H24: =INDEX(Prix!$C$5:$C$79,MATCH($A24,Prix!$A$5:$A$79,0)) -> MicroPlanet | I24: =IFERROR(INDEX(Prix!$G$5:$G$79,MATCH($A24,Prix!$A$5:$A$79,0)),"") -> 0.3 | J24: =IF(I24="","",F24*I24) -> 2.7 | L24: lien
A25: R_18k | B25: 2. Résistances | C25: Résistance 18 kΩ 1/4 W | D25: R39 | E25: Bas du pont VBAT profil bus 12V : 100k/18k | F25: 1 | G25: À acheter | H25: =INDEX(Prix!$C$5:$C$79,MATCH($A25,Prix!$A$5:$A$79,0)) -> MicroPlanet | I25: =IFERROR(INDEX(Prix!$G$5:$G$79,MATCH($A25,Prix!$A$5:$A$79,0)),"") -> 0.3 | J25: =IF(I25="","",F25*I25) -> 0.3 | L25: lien
A26: R_100k | B26: 2. Résistances | C26: Résistance 100 kΩ 1/4 W | D26: R35, R38, R40, R57, R58 | E26: Pull-up grille P-MOSFET vers +5V; Haut du pont VBAT; Grille anti-inversion vers GND; Grille de Q12 vers GND ; … | F26: 5 | G26: À acheter | H26: =INDEX(Prix!$C$5:$C$79,MATCH($A26,Prix!$A$5:$A$79,0)) -> MicroPlanet | I26: =IFERROR(INDEX(Prix!$G$5:$G$79,MATCH($A26,Prix!$A$5:$A$79,0)),"") -> 0.3 | J26: =IF(I26="","",F26*I26) -> 1.5 | L26: lien
A27: C_100n | B27: 3. Condensateurs | C27: Condensateur céramique 100 nF (pas 5 mm) | D27: C3, C4, C10, C13 | E27: Découplage 3V3 capteurs; Découplage 3V3 I2C; Filtre ADC_E; Filtre ADC_VBAT | F27: 4 | G27: À acheter | H27: =INDEX(Prix!$C$5:$C$79,MATCH($A27,Prix!$A$5:$A$79,0)) -> A2itronic | I27: =IFERROR(INDEX(Prix!$G$5:$G$79,MATCH($A27,Prix!$A$5:$A$79,0)),"") -> 0.5 | J27: =IF(I27="","",F27*I27) -> 2 | L27: lien
A28: C_10u25 | B28: 3. Condensateurs | C28: Condensateur électrolytique 10 µF 25 V | D28: C11 | E28: Entrée LDO | F28: 1 | G28: À acheter | H28: =INDEX(Prix!$C$5:$C$79,MATCH($A28,Prix!$A$5:$A$79,0)) -> A2itronic | I28: =IFERROR(INDEX(Prix!$G$5:$G$79,MATCH($A28,Prix!$A$5:$A$79,0)),"") -> 1 | J28: =IF(I28="","",F28*I28) -> 1 | L28: lien
A29: C_100u16 | B29: 3. Condensateurs | C29: Condensateur électrolytique 100 µF 16 V | D29: C12 | E29: Sortie LDO | F29: 1 | G29: À acheter | H29: =INDEX(Prix!$C$5:$C$79,MATCH($A29,Prix!$A$5:$A$79,0)) -> A2itronic | I29: =IFERROR(INDEX(Prix!$G$5:$G$79,MATCH($A29,Prix!$A$5:$A$79,0)),"") -> 1 | J29: =IF(I29="","",F29*I29) -> 1 | L29: lien
A30: C_470u16 | B30: 3. Condensateurs | C30: Condensateur électrolytique 470 µF 16 V (25 V convient) | D30: C2 | E30: Réservoir du rail 5 V commuté LDO_IN côté servos | F30: 1 | G30: À acheter | H30: =INDEX(Prix!$C$5:$C$79,MATCH($A30,Prix!$A$5:$A$79,0)) -> A2itronic | I30: =IFERROR(INDEX(Prix!$G$5:$G$79,MATCH($A30,Prix!$A$5:$A$79,0)),"") -> 2 | J30: =IF(I30="","",F30*I30) -> 2 | L30: lien
A31: C_470u25 | B31: 3. Condensateurs | C31: Condensateur électrolytique 470 µF 25 V (35 V convient) | D31: C5 | E31: Réservoir bus 12V protégé | F31: 1 | G31: À acheter | H31: =INDEX(Prix!$C$5:$C$79,MATCH($A31,Prix!$A$5:$A$79,0)) -> A2itronic | I31: =IFERROR(INDEX(Prix!$G$5:$G$79,MATCH($A31,Prix!$A$5:$A$79,0)),"") -> 2 | J31: =IF(I31="","",F31*I31) -> 2 | L31: lien
A32: C_1000u16 | B32: 3. Condensateurs | C32: Condensateur électrolytique 1000 µF 16 V (diam. 10 mm) | D32: C1 | E32: Réservoir rail 5V | F32: 1 | G32: À acheter | H32: =INDEX(Prix!$C$5:$C$79,MATCH($A32,Prix!$A$5:$A$79,0)) -> A2itronic | I32: =IFERROR(INDEX(Prix!$G$5:$G$79,MATCH($A32,Prix!$A$5:$A$79,0)),"") -> 3 | J32: =IF(I32="","",F32*I32) -> 3 | L32: lien
A33: 1N4007 | B33: 4. Semi-conducteurs | C33: Diode 1N4007 (roue libre des bobines de relais) | D33: D1, D2, D3, D4, D6, D7 | E33: Diode de roue libre bobine | F33: 6 | G33: À acheter | H33: =INDEX(Prix!$C$5:$C$79,MATCH($A33,Prix!$A$5:$A$79,0)) -> Shop4Makers | I33: =IFERROR(INDEX(Prix!$G$5:$G$79,MATCH($A33,Prix!$A$5:$A$79,0)),"") -> 0.9 | J33: =IF(I33="","",F33*I33) -> 5.4 | L33: lien
A34: BAT85 | B34: 4. Semi-conducteurs | C34: Diode Schottky BAT85 / BAT43 / BAT42 (DO-35) | D34: D11 | E34: Clamp ADC_VBAT sur +3V3 | F34: 1 | G34: À acheter | H34: =INDEX(Prix!$C$5:$C$79,MATCH($A34,Prix!$A$5:$A$79,0)) -> Moussasoft | I34: =IFERROR(INDEX(Prix!$G$5:$G$79,MATCH($A34,Prix!$A$5:$A$79,0)),"") -> 2 | J34: =IF(I34="","",F34*I34) -> 2 | L34: lien
A35: TVS_6V8 | B35: 4. Semi-conducteurs | C35: Diode TVS 1.5KE6.8A (ou P6KE6.8A) | D35: D12 | E35: TVS 6,8V sur le rail +5V : surtension / inversion résiduelle | F35: 1 | G35: À acheter | H35: =INDEX(Prix!$C$5:$C$79,MATCH($A35,Prix!$A$5:$A$79,0)) -> LCSC | I35: =IFERROR(INDEX(Prix!$G$5:$G$79,MATCH($A35,Prix!$A$5:$A$79,0)),"") | J35: =IF(I35="","",F35*I35) | K35: Protège le rail 5 V. Commander tôt chez LCSC (stock faible). | L35: lien
A36: TVS_18 | B36: 4. Semi-conducteurs | C36: Diode TVS 1.5KE18A (ou P6KE18A) — PAS 15 V | D36: D8 | E36: TVS 18V transitoires bus batterie | F36: 1 | G36: À acheter | H36: =INDEX(Prix!$C$5:$C$79,MATCH($A36,Prix!$A$5:$A$79,0)) -> LCSC | I36: =IFERROR(INDEX(Prix!$G$5:$G$79,MATCH($A36,Prix!$A$5:$A$79,0)),"") | J36: =IF(I36="","",F36*I36) | L36: lien
A37: Z15 | B37: 4. Semi-conducteurs | C37: Diode Zener 15 V 1 W 1N4744A | D37: D9 | E37: Zener 15V grille-source de Q11 : VGS borné à -15 V | F37: 1 | G37: À acheter | H37: =INDEX(Prix!$C$5:$C$79,MATCH($A37,Prix!$A$5:$A$79,0)) -> MicroPlanet | I37: =IFERROR(INDEX(Prix!$G$5:$G$79,MATCH($A37,Prix!$A$5:$A$79,0)),"") -> 2 | J37: =IF(I37="","",F37*I37) -> 2 | L37: lien
A38: BC337 | B38: 4. Semi-conducteurs | C38: Transistor NPN BC337-40 (TO-92) | D38: Q1, Q2, Q3, Q4, Q5, Q6, Q8 | E38: Transistor NPN commande relais; Driver gate | F38: 7 | G38: À acheter | H38: =INDEX(Prix!$C$5:$C$79,MATCH($A38,Prix!$A$5:$A$79,0)) -> A2itronic | I38: =IFERROR(INDEX(Prix!$G$5:$G$79,MATCH($A38,Prix!$A$5:$A$79,0)),"") -> 1 | J38: =IF(I38="","",F38*I38) -> 7 | K38: Brochage C-B-E sérigraphié. | L38: lien
A39: IRF4905 | B39: 4. Semi-conducteurs | C39: MOSFET P IRF4905 (TO-220) | D39: Q7, Q11, Q12 | E39: P-MOSFET commutation 5V du LDO capteurs; Anti-inversion P-MOSFET 55V ±20V VGS; Anti-inversion entrée 5V (P-MOSFET 55V, VGS = -5V | F39: 3 | G39: À acheter | H39: =INDEX(Prix!$C$5:$C$79,MATCH($A39,Prix!$A$5:$A$79,0)) -> A2itronic | I39: =IFERROR(INDEX(Prix!$G$5:$G$79,MATCH($A39,Prix!$A$5:$A$79,0)),"") -> 10 | J39: =IF(I39="","",F39*I39) -> 30 | K39: Respecter la sérigraphie G-D-S de chaque MOSFET. | L39: lien
A40: LD1117 | B40: 4. Semi-conducteurs | C40: Régulateur LD1117V33 TO-220 (1=GND 2=OUT 3=IN) | D40: U1 | E40: Régulateur 3,3V 800mA du rail capteurs (1=GND 2=OUT 3=IN | F40: 1 | G40: À acheter | H40: =INDEX(Prix!$C$5:$C$79,MATCH($A40,Prix!$A$5:$A$79,0)) -> Megma | I40: =IFERROR(INDEX(Prix!$G$5:$G$79,MATCH($A40,Prix!$A$5:$A$79,0)),"") -> 7.5 | J40: =IF(I40="","",F40*I40) -> 7.5 | K40: Ce n'est pas un 78xx : 1=GND 2=OUT 3=IN (sérigraphié). | L40: lien
A41: LED_R | B41: 4. Semi-conducteurs | C41: LED 5 mm rouge | D41: LED1, LED2, LED3, LED4, LED6, LED7 | E41: LED témoin relais ON | F41: 6 | G41: À acheter | H41: =INDEX(Prix!$C$5:$C$79,MATCH($A41,Prix!$A$5:$A$79,0)) -> Moussasoft | I41: =IFERROR(INDEX(Prix!$G$5:$G$79,MATCH($A41,Prix!$A$5:$A$79,0)),"") -> 1 | J41: =IF(I41="","",F41*I41) -> 6 | L41: lien
A42: LED_V | B42: 4. Semi-conducteurs | C42: LED 5 mm verte | D42: LED5 | E42: LED présence 5V | F42: 1 | G42: À acheter | H42: =INDEX(Prix!$C$5:$C$79,MATCH($A42,Prix!$A$5:$A$79,0)) -> Shop4Makers | I42: =IFERROR(INDEX(Prix!$G$5:$G$79,MATCH($A42,Prix!$A$5:$A$79,0)),"") -> 0.9 | J42: =IF(I42="","",F42*I42) -> 0.9 | K42: LED5 posée (présence 5 V). | L42: lien
A43: SRD05 | B43: 5. Relais et protection secteur | C43: Relais Songle SRD-05VDC-SL-C (composant seul, pas le module) | D43: K1, K2, K3, K4, K5, K6 | E43: Relais 5V SPDT Songle/Sanyou SRD Form C | F43: 6 | G43: À acheter | H43: =INDEX(Prix!$C$5:$C$79,MATCH($A43,Prix!$A$5:$A$79,0)) -> Moussasoft | I43: =IFERROR(INDEX(Prix!$G$5:$G$79,MATCH($A43,Prix!$A$5:$A$79,0)),"") -> 18 | J43: =IF(I43="","",F43*I43) -> 108 | L43: lien
A44: BORNIER_2P | B44: 6. Connectique carte | C44: Bornier à vis 2 pôles pas 5,08 (KF301-2P) | D44: J1, J12, J18, J19, J25, J26, J36, J37 | E44: Entrée 5V alternative; LDR déportée entre 3V3 et l'ADC; Distribution 5V; Distribution 3V3 capteurs ; … | F44: 8 | G44: À acheter | H44: =INDEX(Prix!$C$5:$C$79,MATCH($A44,Prix!$A$5:$A$79,0)) -> MicroPlanet | I44: =IFERROR(INDEX(Prix!$G$5:$G$79,MATCH($A44,Prix!$A$5:$A$79,0)),"") -> 2 | J44: =IF(I44="","",F44*I44) -> 16 | K44: J1 seulement pour les essais sur table, buck débranché. Sonde bus 12 V (JP12 en 1-2, ratio 118/18) : facultatif, aucun firmware ne la lit aujourd'hui. | L44: lien
A45: BORNIER_3P | B45: 6. Connectique carte | C45: Bornier à vis 3 pôles pas 5,08 (KF301-3P) | D45: J3, J4, J5, J6, J10, J11, J23, J24 | E45: Bornier charge 230V; DHT11/DHT22; Sonde DS18B20 étanche | F45: 8 | G45: À acheter | H45: =INDEX(Prix!$C$5:$C$79,MATCH($A45,Prix!$A$5:$A$79,0)) -> MicroPlanet | I45: =IFERROR(INDEX(Prix!$G$5:$G$79,MATCH($A45,Prix!$A$5:$A$79,0)),"") -> 3 | J45: =IF(I45="","",F45*I45) -> 24 | L45: lien
A46: BORNIER_4P | B46: 6. Connectique carte | C46: Bornier à vis 4 pôles pas 5,08 (ou 2+2 emboîtés) | D46: J7, J8, J9 | E46: HC-SR04 AQUA; HC-SR04 TANK; HC-SR04 POTA | F46: 3 | G46: À acheter | H46: =INDEX(Prix!$C$5:$C$79,MATCH($A46,Prix!$A$5:$A$79,0)) -> MicroPlanet | I46: =IFERROR(INDEX(Prix!$G$5:$G$79,MATCH($A46,Prix!$A$5:$A$79,0)),"") -> 5 | J46: =IF(I46="","",F46*I46) -> 15 | L46: lien
A47: BARRETTE_F | B47: 6. Connectique carte | C47: Barrette femelle sécable 1×40 pas 2,54 | D47: A1 (2×15), J13, J14, J21, J22, J28 | E47: Supports du DevKit (jamais soudé); OLED SSD1306 128x64 I2C 0x3C; Extension I2C; Port I2C libre 2 ; … | F47: 2 | G47: À acheter | H47: =INDEX(Prix!$C$5:$C$79,MATCH($A47,Prix!$A$5:$A$79,0)) -> Moussasoft | I47: =IFERROR(INDEX(Prix!$G$5:$G$79,MATCH($A47,Prix!$A$5:$A$79,0)),"") -> 5 | J47: =IF(I47="","",F47*I47) -> 10 | K47: 50 broches femelles utilisées (+ pertes de coupe). | L47: lien
A48: BARRETTE_M | B48: 6. Connectique carte | C48: Barrette mâle sécable 1×40 pas 2,54 | D48: J15, J16, J17, J20, J38, JP1, JP5, JP6, JP7, JP8, JP9, JP10, JP12, JP13, … | E48: Servo GROS; Servo PETITS; Header service; Rail Dupont ; … | F48: 2 | G48: À acheter | H48: =INDEX(Prix!$C$5:$C$79,MATCH($A48,Prix!$A$5:$A$79,0)) -> Moussasoft | I48: =IFERROR(INDEX(Prix!$G$5:$G$79,MATCH($A48,Prix!$A$5:$A$79,0)),"") -> 4 | J48: =IF(I48="","",F48*I48) -> 8 | K48: 68 broches mâles utilisées (+ pertes de coupe). | L48: lien
A49: CAVALIER | B49: 6. Connectique carte | C49: Cavalier (jumper) 2,54 mm | D49: JP… | E49: Cavaliers de configuration du profil (+2 de rechange) | F49: 8 | G49: À acheter | H49: =INDEX(Prix!$C$5:$C$79,MATCH($A49,Prix!$A$5:$A$79,0)) -> Shop4Makers | I49: =IFERROR(INDEX(Prix!$G$5:$G$79,MATCH($A49,Prix!$A$5:$A$79,0)),"") -> 0.5 | J49: =IF(I49="","",F49*I49) -> 4 | K49: Cavaliers posés : JP1 FERMÉ, JP12 en 1-2 (18k), JP13-JP15 et JP20 FERMÉS ; JP5-JP10 SANS cavalier. | L49: lien
A50: FIL | B50: 6. Connectique carte | C50: Pont de fil à la place de D5 (chute de patte de résistance) | D50: D5 | E50: PONT DE FIL vers VIN DevKit | F50: 1 | G50: À acheter | H50: =INDEX(Prix!$C$5:$C$79,MATCH($A50,Prix!$A$5:$A$79,0)) -> — | I50: =IFERROR(INDEX(Prix!$G$5:$G$79,MATCH($A50,Prix!$A$5:$A$79,0)),"") -> 0 | J50: =IF(I50="","",F50*I50) -> 0 | K50: D5 = pont de fil (rev 0.2.2). Règle absolue : ne JAMAIS brancher l'USB du DevKit quand la carte est alimentée.
A51: TP_FIL | B51: 6. Connectique carte | C51: Points de test TP1-TP4 : boucle de fil (chute de patte) | D51: TP1, TP2, TP3, TP4 | E51: Point de test GND; Point de test +5V; Point de test +3V3_SW; Point de test +3V3 | F51: 4 | G51: À acheter | H51: =INDEX(Prix!$C$5:$C$79,MATCH($A51,Prix!$A$5:$A$79,0)) -> — | I51: =IFERROR(INDEX(Prix!$G$5:$G$79,MATCH($A51,Prix!$A$5:$A$79,0)),"") -> 0 | J51: =IF(I51="","",F51*I51) -> 0
A52: DHT11 | B52: 7. Capteurs et actionneurs | C52: Capteur température/humidité DHT11 | D52: hors carte | E52: Température/humidité de l'air sur J10 | F52: 1 | G52: À acheter | H52: =INDEX(Prix!$C$5:$C$79,MATCH($A52,Prix!$A$5:$A$79,0)) -> Shop4Makers | I52: =IFERROR(INDEX(Prix!$G$5:$G$79,MATCH($A52,Prix!$A$5:$A$79,0)),"") -> 16.2 | J52: =IF(I52="","",F52*I52) -> 16.2 | K52: DHT22 possible (flag -DUSE_DHT22). | L52: lien
A53: DS18B20 | B53: 7. Capteurs et actionneurs | C53: Sonde DS18B20 étanche (câble 1 m) | D53: hors carte | E53: Température de l'eau sur J11 | F53: 1 | G53: À acheter | H53: =INDEX(Prix!$C$5:$C$79,MATCH($A53,Prix!$A$5:$A$79,0)) -> A2itronic | I53: =IFERROR(INDEX(Prix!$G$5:$G$79,MATCH($A53,Prix!$A$5:$A$79,0)),"") -> 50 | J53: =IF(I53="","",F53*I53) -> 50 | K53: Chauffage interdit sur batterie (firmware) : surplus solaire seulement. | L53: lien
A54: LDR | B54: 7. Capteurs et actionneurs | C54: Photorésistance LDR GL5528 | D54: hors carte | E54: Luminosité ambiante sur J12 | F54: 1 | G54: À acheter | H54: =INDEX(Prix!$C$5:$C$79,MATCH($A54,Prix!$A$5:$A$79,0)) -> Moussasoft | I54: =IFERROR(INDEX(Prix!$G$5:$G$79,MATCH($A54,Prix!$A$5:$A$79,0)),"") -> 2 | J54: =IF(I54="","",F54*I54) -> 2 | K54: R27 posé, JP20 FERMÉ. | L54: lien
A55: HCSR04 | B55: 7. Capteurs et actionneurs | C55: Capteur ultrason HC-SR04 | D55: hors carte | E55: Niveaux d'eau aquarium (J7), réservoir (J8), potager (J9) | F55: 3 | G55: À acheter | H55: =INDEX(Prix!$C$5:$C$79,MATCH($A55,Prix!$A$5:$A$79,0)) -> Moussasoft | I55: =IFERROR(INDEX(Prix!$G$5:$G$79,MATCH($A55,Prix!$A$5:$A$79,0)),"") -> 25 | J55: =IF(I55="","",F55*I55) -> 75 | K55: JP13-JP15 FERMÉS + R17-R19 posés : OBLIGATOIRE. | L55: lien
A56: SG90 | B56: 7. Capteurs et actionneurs | C56: Servomoteur SG90 | D56: hors carte | E56: Nourrisseurs gros (J15) et petits poissons (J16) | F56: 2 | G56: À acheter | H56: =INDEX(Prix!$C$5:$C$79,MATCH($A56,Prix!$A$5:$A$79,0)) -> Moussasoft | I56: =IFERROR(INDEX(Prix!$G$5:$G$79,MATCH($A56,Prix!$A$5:$A$79,0)),"") -> 30 | J56: =IF(I56="","",F56*I56) -> 60 | K56: JP1 fermé : alimentés en permanence. | L56: lien
A57: OLED | B57: 7. Capteurs et actionneurs | C57: Écran OLED 0,96" SSD1306 I2C 128×64 | D57: hors carte | E57: Affichage local sur J13 | F57: 1 | G57: À acheter | H57: =INDEX(Prix!$C$5:$C$79,MATCH($A57,Prix!$A$5:$A$79,0)) -> Shop4Makers | I57: =IFERROR(INDEX(Prix!$G$5:$G$79,MATCH($A57,Prix!$A$5:$A$79,0)),"") -> 70 | J57: =IF(I57="","",F57*I57) -> 70 | L57: lien
A58: DS3231 | B58: 7. Capteurs et actionneurs | C58: Module horloge RTC DS3231 (ZS-042) | D58: hors carte | E58: Horloge hors ligne sur J14 | F58: 1 | G58: À acheter | H58: =INDEX(Prix!$C$5:$C$79,MATCH($A58,Prix!$A$5:$A$79,0)) -> A2itronic | I58: =IFERROR(INDEX(Prix!$G$5:$G$79,MATCH($A58,Prix!$A$5:$A$79,0)),"") -> 29 | J58: =IF(I58="","",F58*I58) -> 29 | K58: Dessouder le circuit de charge du module. | L58: lien
A59: CR2032 | B59: 7. Capteurs et actionneurs | C59: Pile bouton CR2032 | D59: hors carte | E59: Pile du DS3231 | F59: 1 | G59: À acheter | H59: =INDEX(Prix!$C$5:$C$79,MATCH($A59,Prix!$A$5:$A$79,0)) -> Shop4Makers | I59: =IFERROR(INDEX(Prix!$G$5:$G$79,MATCH($A59,Prix!$A$5:$A$79,0)),"") -> 3 | J59: =IF(I59="","",F59*I59) -> 3 | L59: lien
A60: INA226 | B60: 7. Capteurs et actionneurs | C60: Module INA226 (mesure tension/courant I2C) | D60: hors carte | E60: Mesure tension/courant batterie (délestage AGM, n3_power) sur J21 | F60: 1 | G60: À acheter | H60: =INDEX(Prix!$C$5:$C$79,MATCH($A60,Prix!$A$5:$A$79,0)) -> Shop4Makers | I60: =IFERROR(INDEX(Prix!$G$5:$G$79,MATCH($A60,Prix!$A$5:$A$79,0)),"") -> 50 | J60: =IF(I60="","",F60*I60) -> 50 | K60: Le shunt R100 du module plafonne à 0,8 A : shunt externe 5–10 mΩ câblé en Kelvin pour mesurer les pompes. | L60: lien
A61: INA226 | B61: 7. Capteurs et actionneurs | C61: Module INA226 (mesure tension/courant I2C) | D61: hors carte | E61: 2e et 3e INA226 : panneau (0x40) et charges (0x44) sur J22/J28 | F61: 2 | G61: Option | H61: =INDEX(Prix!$C$5:$C$79,MATCH($A61,Prix!$A$5:$A$79,0)) -> Shop4Makers | I61: =IFERROR(INDEX(Prix!$G$5:$G$79,MATCH($A61,Prix!$A$5:$A$79,0)),"") -> 50 | J61: =IF(I61="","",F61*I61) -> 100 | K61: Adresses à régler par ponts A0/A1. | L61: lien
A62: 1N4007_EXT | B62: 7. Capteurs et actionneurs | C62: Diode 1N4007 aux bornes d'une pompe DC (roue libre) | D62: hors carte | E62: Roue libre aux bornes des pompes 12 V (aquarium, réservoir) | F62: 2 | G62: À acheter | H62: =INDEX(Prix!$C$5:$C$79,MATCH($A62,Prix!$A$5:$A$79,0)) -> Shop4Makers | I62: =IFERROR(INDEX(Prix!$G$5:$G$79,MATCH($A62,Prix!$A$5:$A$79,0)),"") -> 0.9 | J62: =IF(I62="","",F62*I62) -> 1.8 | K62: Cathode côté +. Pompe > 1 A : préférer une 1N5408 (3 A). | L62: lien
A63: BUCK | B63: 8. Alimentation hors carte | C63: Module buck MP1584EN (12 V → 5,1 V) | D63: hors carte | E63: 12 V → 5,1 V pour la carte (J36 → J37) | F63: 1 | G63: À acheter | H63: =INDEX(Prix!$C$5:$C$79,MATCH($A63,Prix!$A$5:$A$79,0)) -> Shop4Makers | I63: =IFERROR(INDEX(Prix!$G$5:$G$79,MATCH($A63,Prix!$A$5:$A$79,0)),"") -> 25 | J63: =IF(I63="","",F63*I63) -> 25 | K63: RÉGLER À 5,1 V AVANT de raccorder J37. Sur entretoises au-dessus de la carte. | L63: lien
A64: FUSIBLE_LAME | B64: 8. Alimentation hors carte | C64: Porte-fusible lame en ligne + fusible 10 A | D64: hors carte | E64: Fusible 7,5–10 A en ligne, au plus près de la batterie, avant J26 | F64: 1 | G64: À acheter | H64: =INDEX(Prix!$C$5:$C$79,MATCH($A64,Prix!$A$5:$A$79,0)) -> Accessoires auto | I64: =IFERROR(INDEX(Prix!$G$5:$G$79,MATCH($A64,Prix!$A$5:$A$79,0)),"") | J64: =IF(I64="","",F64*I64) | K64: OBLIGATOIRE.
A65: AGM_12V | B65: 8. Alimentation hors carte | C65: Batterie AGM 12 V (12 Ah) | D65: hors carte | E65: Batterie du bus 12 V | F65: 1 | G65: Déjà possédé | H65: =INDEX(Prix!$C$5:$C$79,MATCH($A65,Prix!$A$5:$A$79,0)) -> Jumia.ma | I65: =IFERROR(INDEX(Prix!$G$5:$G$79,MATCH($A65,Prix!$A$5:$A$79,0)),"") -> 490 | J65: =IF(I65="","",F65*I65) -> 490 | K65: Brancher la carte sur les bornes BATTERIE, pas sur la sortie « charge » du régulateur. | L65: lien
A66: PWM_SOLAIRE | B66: 8. Alimentation hors carte | C66: Régulateur de charge solaire PWM 12 V 10 A | D66: hors carte | E66: Charge l'AGM depuis le panneau (14,5 V mesurés en absorption) | F66: 1 | G66: Déjà possédé | H66: =INDEX(Prix!$C$5:$C$79,MATCH($A66,Prix!$A$5:$A$79,0)) -> Jumia.ma (AM NEWS) | I66: =IFERROR(INDEX(Prix!$G$5:$G$79,MATCH($A66,Prix!$A$5:$A$79,0)),"") -> 299 | J66: =IF(I66="","",F66*I66) -> 299 | K66: Déjà en place. | L66: lien
A67: PANNEAU_12V | B67: 8. Alimentation hors carte | C67: Panneau solaire 12 V | D67: hors carte | E67: Production solaire du bus 12 V | F67: 1 | G67: Déjà possédé | H67: =INDEX(Prix!$C$5:$C$79,MATCH($A67,Prix!$A$5:$A$79,0)) -> Jumia.ma (XARIUM TECH) | I67: =IFERROR(INDEX(Prix!$G$5:$G$79,MATCH($A67,Prix!$A$5:$A$79,0)),"") -> 179 | J67: =IF(I67="","",F67*I67) -> 179 | K67: Déjà en place. | L67: lien
A68: VIS_M3 | B68: 9. Mécanique et câblage | C68: Vis M3 nylon + écrou (H1-H7 ; nylon OBLIGATOIRE en H1/H5) | D68: H1, H2, H3, H4, H5, H6, H7 | E68: Trou de fixation M3 | F68: 7 | G68: À acheter | H68: =INDEX(Prix!$C$5:$C$79,MATCH($A68,Prix!$A$5:$A$79,0)) -> Dsindustrie | I68: =IFERROR(INDEX(Prix!$G$5:$G$79,MATCH($A68,Prix!$A$5:$A$79,0)),"") -> 2 | J68: =IF(I68="","",F68*I68) -> 14 | L68: lien
A69: ENTRETOISE_M3 | B69: 9. Mécanique et câblage | C69: Entretoise M3 nylon ~10 mm | D69: H1-H7 | E69: Entretoises de fixation de la carte | F69: 7 | G69: À acheter | H69: =INDEX(Prix!$C$5:$C$79,MATCH($A69,Prix!$A$5:$A$79,0)) -> Dsindustrie | I69: =IFERROR(INDEX(Prix!$G$5:$G$79,MATCH($A69,Prix!$A$5:$A$79,0)),"") -> 0 | J69: =IF(I69="","",F69*I69) -> 0
A70: BOITIER | B70: 9. Mécanique et câblage | C70: Boîtier étanche IP65 (~200×150 mm ou plus) | D70: hors carte | E70: Boîtier étanche | F70: 1 | G70: À acheter | H70: =INDEX(Prix!$C$5:$C$79,MATCH($A70,Prix!$A$5:$A$79,0)) -> EnergyMarket | I70: =IFERROR(INDEX(Prix!$G$5:$G$79,MATCH($A70,Prix!$A$5:$A$79,0)),"") -> 352 | J70: =IF(I70="","",F70*I70) -> 352 | L70: lien
A71: PRESSE_ETOUPE | B71: 9. Mécanique et câblage | C71: Presse-étoupe PG7 / PG9 | D71: hors carte | E71: Passage bus 12 V, pompes, sondes | F71: 8 | G71: À acheter | H71: =INDEX(Prix!$C$5:$C$79,MATCH($A71,Prix!$A$5:$A$79,0)) -> Quincaillerie | I71: =IFERROR(INDEX(Prix!$G$5:$G$79,MATCH($A71,Prix!$A$5:$A$79,0)),"") | J71: =IF(I71="","",F71*I71)
A72: FIL_05 | B72: 9. Mécanique et câblage | C72: Fil souple 0,5 mm² (mètre) | D72: hors carte | E72: Câblage des capteurs (au mètre) | F72: 5 | G72: À acheter | H72: =INDEX(Prix!$C$5:$C$79,MATCH($A72,Prix!$A$5:$A$79,0)) -> ElectroDelivery | I72: =IFERROR(INDEX(Prix!$G$5:$G$79,MATCH($A72,Prix!$A$5:$A$79,0)),"") -> 3.5 | J72: =IF(I72="","",F72*I72) -> 17.5 | K72: Souple 0,25–0,5 mm² ; embouts sur chaque fil. | L72: lien
A73: FIL_15 | B73: 9. Mécanique et câblage | C73: Fil souple 1,5 mm² (mètre) | D73: hors carte | E73: Câblage bus 12 V et pompes | F73: 5 | G73: À acheter | H73: =INDEX(Prix!$C$5:$C$79,MATCH($A73,Prix!$A$5:$A$79,0)) -> ElectroDelivery | I73: =IFERROR(INDEX(Prix!$G$5:$G$79,MATCH($A73,Prix!$A$5:$A$79,0)),"") -> 8 | J73: =IF(I73="","",F73*I73) -> 40 | K73: Au mètre ; 2,5 mm² entre batterie et fusible si pompes > 5 A. | L73: lien
